Workbook
Name SG01_: Control!$B$2
Name SG02_: Control!$B$3
Name SG03_: Control!$B$4
Name SG04_: Control!$B$5
Name SG05_: Control!$B$6
Name SG06_: Control!$B$7
Name SG07_: Control!$B$8
Name SG08_: Control!$B$9
Name SG09_: Control!$B$10
Name SG10_: Control!$B$11
Name SG11_: Control!$B$12
Name SG12_: Control!$B$13
Name SG13_: Control!$B$14
Name SG14_: Control!$B$15
Name SG15_: Control!$B$16
Name Slicer_Cửa_hàng: #N/A

Sheet Control
A1: Cửa hàng | B1: Check | C1: DK1 | D1: DK2 | F1: Row Labels | G1: Sum of Check | L1: Cửa hàng | M1: Check
A2: SG01 | B2: =C2*D2 -> 1 | C2: =IFERROR(VLOOKUP(A2,$F$2:$G$14,2,0),0) -> 1 | D2: =IF(INDIRECT(A2&"!K10",TRUE)="",0,1) -> 1 | F2: SG01 | G2: 1 | L2: SG01 | M2: 1
A3: SG02 | B3: =C3*D3 -> 0 | C3: =IFERROR(VLOOKUP(A3,$F$2:$G$14,2,0),0) -> 0 | D3: =IF(INDIRECT(A3&"!K10",TRUE)="",0,1) -> 1 | F3: Grand Total | G3: 1 | L3: SG02 | M3: 1
A4: SG03 | B4: =C4*D4 -> 0 | C4: =IFERROR(VLOOKUP(A4,$F$2:$G$14,2,0),0) -> 0 | D4: =IF(INDIRECT(A4&"!K10",TRUE)="",0,1) -> 1 | L4: SG03 | M4: 1
A5: SG04 | B5: =C5*D5 -> 0 | C5: =IFERROR(VLOOKUP(A5,$F$2:$G$14,2,0),0) -> 0 | D5: =IF(INDIRECT(A5&"!K10",TRUE)="",0,1) -> 0 | L5: SG04 | M5: 1
A6: SG05 | B6: =C6*D6 -> 0 | C6: =IFERROR(VLOOKUP(A6,$F$2:$G$14,2,0),0) -> 0 | D6: =IF(INDIRECT(A6&"!K10",TRUE)="",0,1) -> 0 | L6: SG05 | M6: 1
A7: SG06 | B7: =C7*D7 -> 0 | C7: =IFERROR(VLOOKUP(A7,$F$2:$G$14,2,0),0) -> 0 | D7: =IF(INDIRECT(A7&"!K10",TRUE)="",0,1) -> 0 | L7: SG06 | M7: 1
A8: SG07 | B8: =C8*D8 -> 0 | C8: =IFERROR(VLOOKUP(A8,$F$2:$G$14,2,0),0) -> 0 | D8: =IF(INDIRECT(A8&"!K10",TRUE)="",0,1) -> 0 | L8: SG07 | M8: 1
A9: SG08 | B9: =C9*D9 -> 0 | C9: =IFERROR(VLOOKUP(A9,$F$2:$G$14,2,0),0) -> 0 | D9: =IF(INDIRECT(A9&"!K10",TRUE)="",0,1) -> 0 | L9: SG08 | M9: 1
A10: SG09 | B10: =C10*D10 -> 0 | C10: =IFERROR(VLOOKUP(A10,$F$2:$G$14,2,0),0) -> 0 | D10: =IF(INDIRECT(A10&"!K10",TRUE)="",0,1) -> 0 | L10: SG09 | M10: 1
A11: SG10 | B11: =C11*D11 -> 0 | C11: =IFERROR(VLOOKUP(A11,$F$2:$G$14,2,0),0) -> 0 | D11: =IF(INDIRECT(A11&"!K10",TRUE)="",0,1) -> 0 | L11: SG10 | M11: 1
A12: SG11 | B12: =C12*D12 -> 0 | C12: =IFERROR(VLOOKUP(A12,$F$2:$G$14,2,0),0) -> 0 | D12: =IF(INDIRECT(A12&"!K10",TRUE)="",0,1) -> 0 | L12: SG11 | M12: 1
A13: SG12 | B13: =C13*D13 -> 0 | C13: =IFERROR(VLOOKUP(A13,$F$2:$G$14,2,0),0) -> 0 | D13: =IF(INDIRECT(A13&"!K10",TRUE)="",0,1) -> 0 | L13: SG12 | M13: 1
A14: SG13 | B14: =C14*D14 -> 0 | C14: =IFERROR(VLOOKUP(A14,$F$2:$G$14,2,0),0) -> 0 | D14: =IF(INDIRECT(A14&"!K10",TRUE)="",0,1) -> 0 | L14: SG13 | M14: 1
A15: SG14 | B15: =C15*D15 -> 0 | C15: =IFERROR(VLOOKUP(A15,$F$2:$G$14,2,0),0) -> 0 | D15: =IF(INDIRECT(A15&"!K10",TRUE)="",0,1) -> 0 | L15: SG14 | M15: 1
A16: SG15 | B16: =C16*D16 -> 0 | C16: =IFERROR(VLOOKUP(A16,$F$2:$G$14,2,0),0) -> 0 | D16: =IF(INDIRECT(A16&"!K10",TRUE)="",0,1) -> 0 | L16: SG15 | M16: 1

Sheet MENU MIX GMSG T09.2026
B2: CTY CP TẦM NHÌN QUỐC TẾ ALADDIN - CHUỖI NHÀ HÀNG G.MASTER SÀI GÒN | G2: =L5 -> 1550563000 | M2: 4.2210468e+08 | V2: Star | W2: Bán nhiều - Lợi nhuận cao --> Phát huy
B3: BÁO CÁO MENU MIX (PRODUCT MIX) ĐỊNH KỲ | P3: =O3/7 -> 0 | V3: Horse | W3: Bán nhiều - Lợi nhuận thấp -->Điều chỉnh giá
B4: NHÀ HÀNG: | C4: (chọn NH muốn xem báo cáo menu mix trong danh sách) | K4: TC | L4: SALES | N4: TA | P4: COS | S4: Số bàn | T4: =(SUMIF('SG01'!$S$4,$S$4,'SG01'!$T$4)*SG01_+SUMIF('SG02'!$S$4,$S$4,'SG02'!$T$4)*SG02_+SUMIF('SG03'!$S$4,$S$4,'SG03'!$T$4)*SG03_+SUMIF('SG04'!$S$4,$S$4,'SG04'!$T$4)*SG04_+SUMIF('SG05'!$S$4,$S$4,'SG05'!$T$4)*SG05_+SUMIF('SG06'!$S$4,$S$4,'SG06'!$T$4)*SG06_+SUMIF('SG07'!$S$4,$S$4,'SG07'!$T$4)*SG07_+SUMIF('SG08'!$S$4,$S$4,'SG08'!$T$4)*SG08_+SUMIF('SG09'!$S$4,$S$4,'SG09'!$T$4)*SG09_+SUMIF('SG10'!$S$4,$S$4,'SG10'!$T$4)*SG10_+SUMIF('SG11'!$S$4,$S$4,'SG11'!$T$4)*SG11_+SUMIF('SG12'!$S$4,$S$4,'SG12'!$T$4)*SG12_+SUMIF('SG13'!$S$4,$S$4,'SG13'!$T$4)*SG13_+SUMIF('SG14'!$S$4,$S$4,'SG14'!$T$4)*SG14_+SUMIF('SG15'!$S$4,$S$4,'SG15'!$T$4)*SG15_) -> 1257 | V4: Puzzle | W4: Bán ít - Lợi nhuận cao --> Thúc đẩy bán hàng
B5: THÁNG: | C5: ='SG01'!C5:D5 -> 01.09.2026->30.09.2026 | G5: (Giữ phím Ctrl nếu muốn chọn nhiều nhà hàng xem cùng lúc) | K5: =(SUMIF('SG01'!$K$4,$K4,'SG01'!$K$5)*SG01_+SUMIF('SG02'!$K$4,$K4,'SG02'!$K$5)*SG02_+SUMIF('SG03'!$K$4,$K4,'SG03'!$K$5)*SG03_+SUMIF('SG04'!$K$4,$K4,'SG04'!$K$5)*SG04_+SUMIF('SG05'!$K$4,$K4,'SG05'!$K$5)*SG05_+SUMIF('SG06'!$K$4,$K4,'SG06'!$K$5)*SG06_+SUMIF('SG07'!$K$4,$K4,'SG07'!$K$5)*SG07_+SUMIF('SG08'!$K$4,$K4,'SG08'!$K$5)*SG08_+SUMIF('SG09'!$K$4,$K4,'SG09'!$K$5)*SG09_+SUMIF('SG10'!$K$4,$K4,'SG10'!$K$5)*SG10_+SUMIF('SG11'!$K$4,$K4,'SG11'!$K$5)*SG11_+SUMIF('SG12'!$K$4,$K4,'SG12'!$K$5)*SG12_+SUMIF('SG13'!$K$4,$K4,'SG13'!$K$5)*SG13_+SUMIF('SG14'!$K$4,$K4,'SG14'!$K$5)*SG14_+SUMIF('SG15'!$K$4,$K4,'SG15'!$K$5)*SG15_) -> 3693 | L5: =L10 -> 1550563000 | N5: =L5/K5 -> 419865.42 | P5: =K10/L10 -> 0.3364693 | S5: Số TC / Bàn: | T5: =K5/T4 -> 2.9379475 | V5: Dog | W5: Bán ít - lợi nhuận thấp --> Cân nhắc có thể thay thế | AC5: TC | AE5: =K5 -> 3693 | AI5: =(SUMIF('SG01'!$AB:$AB,$AC5,'SG01'!AH:AH)*SG01_+SUMIF('SG02'!$AB:$AB,$AC5,'SG02'!AH:AH)*SG02_+SUMIF('SG03'!$AB:$AB,$AC5,'SG03'!AH:AH)*SG03_+SUMIF('SG04'!$AB:$AB,$AC5,'SG04'!AH:AH)*SG04_+SUMIF('SG05'!$AB:$AB,$AC5,'SG05'!AH:AH)*SG05_+SUMIF('SG06'!$AB:$AB,$AC5,'SG06'!AH:AH)*SG06_+SUMIF('SG07'!$AB:$AB,$AC5,'SG07'!AH:AH)*SG07_+SUMIF('SG08'!$AB:$AB,$AC5,'SG08'!AH:AH)*SG08_+SUMIF('SG09'!$AB:$AB,$AC5,'SG09'!AH:AH)*SG09_+SUMIF('SG10'!$AB:$AB,$AC5,'SG10'!AH:AH)*SG10_+SUMIF('SG11'!$AB:$AB,$AC5,'SG11'!AH:AH)*SG11_+SUMIF('SG12'!$AB:$AB,$AC5,'SG12'!AH:AH)*SG12_+SUMIF('SG13'!$AB:$AB,$AC5,'SG13'!AH:AH)*SG13_+SUMIF('SG14'!$AB:$AB,$AC5,'SG14'!AH:AH)*SG14_+SUMIF('SG15'!$AB:$AB,$AC5,'SG15'!AH:AH)*SG15_) -> 3521
B6: 1 | C6: 2 | D6: 3 | E6: 4 | F6: 5 | G6: 6 | H6: 7 | I6: 8 | J6: 9 | K6: 10 | L6: 11 | M6: 12 | N6: 13 | O6: 14 | P6: 15 | Q6: 16 | R6: 17 | S6: 18 | T6: 19 | U6: 18 | V6: 19 | W6: 20 | X6: 21 | AD6: ='SG01'!AC6 -> 01.09.2026->30.09.2026 | AH6: ='SG01'!AG6 -> 01.09.2026->27.09.2026
B7: MÃ HÀNG | C7: TÊN HÀNG | D7: Ghi Chú | E7: Đơn Vị Tính | F7: Giá Vốn | G7: Giá Bán | H7: LN Món Bán | I7: Số Bán | K7: ITEM COST | L7: ITEM SALES | M7: MARGIN | N7: % COS | O7: % SALES MIX | P7: % MARGIN MIX | Q7: % PRODUCT MIX | R7: Per 100 TC | S7: Số Lượng Bán /100 Bàn | T7: Doanh Số Bán /100 Bàn | V7: Popularity | W7: Profitability | X7: Items class | AB7: MÃ NHÓM | AC7: TÊN NHÓM | AD7: ITEM SALES | AE7: TA | AF7: Item Sold | AG7: Per 100 TC | AH7: ITEM SALES | AI7: TA | AJ7: Item Sold | AK7: Per 100 TC | AL7: CLệch TA | AM7: CLệch Per 100TC
F8: Cost Price | G8: Selling Price | H8: Margin | I8: Item Sold | AD8: =SUM(AD9:AD43) -> 1471703000 | AE8: =SUM(AE9:AE43) -> 398511.51 | AF8: =SUM(AF9:AF43) -> 13974 | AG8: =SUM(AG9:AG43) -> 378.39155 | AH8: =SUM(AH9:AH43) -> 1403621000 | AI8: =SUM(AI9:AI43) -> 398642.72 | AJ8: =SUM(AJ9:AJ43) -> 13393 | AK8: =SUM(AK9:AK43) -> 380.37489 | ... AM8: =SUM(AM9:AM43) -> -1.9833419
AB9: CPL.BEP | AC9: CHI PHÍ QUẦY LINE NƯỚC CHẤM | AD9: =VLOOKUP(AB9,$B:$R,11,0) -> 0 | AE9: =AD9/AE$5 -> 0 | AF9: =VLOOKUP(AB9,$B:$R,8,0) -> 1 | AG9: =AF9/$AE$5*100 -> 0.027078256 | AH9: =(SUMIF('SG01'!$AA:$AA,$AB9,'SG01'!AG:AG)*SG01_+SUMIF('SG02'!$AA:$AA,$AB9,'SG02'!AG:AG)*SG02_+SUMIF('SG03'!$AA:$AA,$AB9,'SG03'!AG:AG)*SG03_+SUMIF('SG04'!$AA:$AA,$AB9,'SG04'!AG:AG)*SG04_+SUMIF('SG05'!$AA:$AA,$AB9,'SG05'!AG:AG)*SG05_+SUMIF('SG06'!$AA:$AA,$AB9,'SG06'!AG:AG)*SG06_+SUMIF('SG07'!$AA:$AA,$AB9,'SG07'!AG:AG)*SG07_+SUMIF('SG08'!$AA:$AA,$AB9,'SG08'!AG:AG)*SG08_+SUMIF('SG09'!$AA:$AA,$AB9,'SG09'!AG:AG)*SG09_+SUMIF('SG10'!$AA:$AA,$AB9,'SG10'!AG:AG)*SG10_+SUMIF('SG11'!$AA:$AA,$AB9,'SG11'!AG:AG)*SG11_+SUMIF('SG12'!$AA:$AA,$AB9,'SG12'!AG:AG)*SG12_+SUMIF('SG13'!$AA:$AA,$AB9,'SG13'!AG:AG)*SG13_+SUMIF('SG14'!$AA:$AA,$AB9,'SG14'!AG:AG)*SG14_+SUMIF('SG15'!$AA:$AA,$AB9,'SG15'!AG:AG)*SG15_) -> 0 | AI9: =AH9/AI$5 -> 0 | AJ9: =(SUMIF('SG01'!$AA:$AA,$AB9,'SG01'!AI:AI)*SG01_+SUMIF('SG02'!$AA:$AA,$AB9,'SG02'!AI:AI)*SG02_+SUMIF('SG03'!$AA:$AA,$AB9,'SG03'!AI:AI)*SG03_+SUMIF('SG04'!$AA:$AA,$AB9,'SG04'!AI:AI)*SG04_+SUMIF('SG05'!$AA:$AA,$AB9,'SG05'!AI:AI)*SG05_+SUMIF('SG06'!$AA:$AA,$AB9,'SG06'!AI:AI)*SG06_+SUMIF('SG07'!$AA:$AA,$AB9,'SG07'!AI:AI)*SG07_+SUMIF('SG08'!$AA:$AA,$AB9,'SG08'!AI:AI)*SG08_+SUMIF('SG09'!$AA:$AA,$AB9,'SG09'!AI:AI)*SG09_+SUMIF('SG10'!$AA:$AA,$AB9,'SG10'!AI:AI)*SG10_+SUMIF('SG11'!$AA:$AA,$AB9,'SG11'!AI:AI)*SG11_+SUMIF('SG12'!$AA:$AA,$AB9,'SG12'!AI:AI)*SG12_+SUMIF('SG13'!$AA:$AA,$AB9,'SG13'!AI:AI)*SG13_+SUMIF('SG14'!$AA:$AA,$AB9,'SG14'!AI:AI)*SG14_+SUMIF('SG15'!$AA:$AA,$AB9,'SG15'!AI:AI)*SG15_) -> 1 | AK9: =AJ9/$AI$5*100 -> 0.028401022 | AL9: =AE9-AI9 -> 0 | AM9: =AG9-AK9 -> -0.0013227663
B10: TỔNG MENU | I10: =SUBTOTAL(9,I12:I155) -> 16052 | K10: =SUBTOTAL(9,K12:K156) -> 5.2171684e+08 | L10: =SUBTOTAL(9,L12:L156) -> 1550563000 | M10: =SUBTOTAL(9,M12:M156) -> 1.0288462e+09 | N10: =K10/L10 -> 0.3364693 | O10: =L10/L$10 -> 1 | P10: =M10/M$10 -> 1 | Q10: =I10/I$10 -> 1 | R10: =I10/$K$5*100 -> 434.66017 | S10: =R10*T$5 -> 1277.0088 | T10: =SUBTOTAL(9,T12:T342) -> 1.2432959e+08 | V10: MIN Menu Selling | X10: 100 | AB10: KVI.GSG | AC10: KHAI VỊ | AD10: =VLOOKUP(AB10,$B:$M,11,0) -> 51978000 | AE10: =AD10/AE$5 -> 14074.736 | AF10: =VLOOKUP(AB10,$B:$R,8,0) -> 633 | AG10: =AF10/$AE$5*100 -> 17.140536 | AH10: =(SUMIF('SG01'!$AA:$AA,$AB10,'SG01'!AG:AG)*SG01_+SUMIF('SG02'!$AA:$AA,$AB10,'SG02'!AG:AG)*SG02_+SUMIF('SG03'!$AA:$AA,$AB10,'SG03'!AG:AG)*SG03_+SUMIF('SG04'!$AA:$AA,$AB10,'SG04'!AG:AG)*SG04_+SUMIF('SG05'!$AA:$AA,$AB10,'SG05'!AG:AG)*SG05_+SUMIF('SG06'!$AA:$AA,$AB10,'SG06'!AG:AG)*SG06_+SUMIF('SG07'!$AA:$AA,$AB10,'SG07'!AG:AG)*SG07_+SUMIF('SG08'!$AA:$AA,$AB10,'SG08'!AG:AG)*SG08_+SUMIF('SG09'!$AA:$AA,$AB10,'SG09'!AG:AG)*SG09_+SUMIF('SG10'!$AA:$AA,$AB10,'SG10'!AG:AG)*SG10_+SUMIF('SG11'!$AA:$AA,$AB10,'SG11'!AG:AG)*SG11_+SUMIF('SG12'!$AA:$AA,$AB10,'SG12'!AG:AG)*SG12_+SUMIF('SG13'!$AA:$AA,$AB10,'SG13'!AG:AG)*SG13_+SUMIF('SG14'!$AA:$AA,$AB10,'SG14'!AG:AG)*SG14_+SUMIF('SG15'!$AA:$AA,$AB10,'SG15'!AG:AG)*SG15_) -> 50538000 | AI10: =AH10/AI$5 -> 14353.309 | AJ10: =(SUMIF('SG01'!$AA:$AA,$AB10,'SG01'!AI:AI)*SG01_+SUMIF('SG02'!$AA:$AA,$AB10,'SG02'!AI:AI)*SG02_+SUMIF('SG03'!$AA:$AA,$AB10,'SG03'!AI:AI)*SG03_+SUMIF('SG04'!$AA:$AA,$AB10,'SG04'!AI:AI)*SG04_+SUMIF('SG05'!$AA:$AA,$AB10,'SG05'!AI:AI)*SG05_+SUMIF('SG06'!$AA:$AA,$AB10,'SG06'!AI:AI)*SG06_+SUMIF('SG07'!$AA:$AA,$AB10,'SG07'!AI:AI)*SG07_+SUMIF('SG08'!$AA:$AA,$AB10,'SG08'!AI:AI)*SG08_+SUMIF('SG09'!$AA:$AA,$AB10,'SG09'!AI:AI)*SG09_+SUMIF('SG10'!$AA:$AA,$AB10,'SG10'!AI:AI)*SG10_+SUMIF('SG11'!$AA:$AA,$AB10,'SG11'!AI:AI)*SG11_+SUMIF('SG12'!$AA:$AA,$AB10,'SG12'!AI:AI)*SG12_+SUMIF('SG13'!$AA:$AA,$AB10,'SG13'!AI:AI)*SG13_+SUMIF('SG14'!$AA:$AA,$AB10,'SG14'!AI:AI)*SG14_+SUMIF('SG15'!$AA:$AA,$AB10,'SG15'!AI:AI)*SG15_) -> 613 | AK10: =AJ10/$AI$5*100 -> 17.409827 | AL10: =AE10-AI10 -> -278.57273 | AM10: =AG10-AK10 -> -0.2692906
S11: =R11*T$5 -> 0 | T11: =IFERROR(S11*G11,0) -> 0 | AB11: XIENRCN.GSG | AC11: XIÊN RAU - CỦ - NẤM NƯỚNG | AD11: =VLOOKUP(AB11,$B:$M,11,0) -> 13427000 | AE11: =AD11/AE$5 -> 3635.7975 | AF11: =VLOOKUP(AB11,$B:$R,8,0) -> 755 | AG11: =AF11/$AE$5*100 -> 20.444083 | AH11: =(SUMIF('SG01'!$AA:$AA,$AB11,'SG01'!AG:AG)*SG01_+SUMIF('SG02'!$AA:$AA,$AB11,'SG02'!AG:AG)*SG02_+SUMIF('SG03'!$AA:$AA,$AB11,'SG03'!AG:AG)*SG03_+SUMIF('SG04'!$AA:$AA,$AB11,'SG04'!AG:AG)*SG04_+SUMIF('SG05'!$AA:$AA,$AB11,'SG05'!AG:AG)*SG05_+SUMIF('SG06'!$AA:$AA,$AB11,'SG06'!AG:AG)*SG06_+SUMIF('SG07'!$AA:$AA,$AB11,'SG07'!AG:AG)*SG07_+SUMIF('SG08'!$AA:$AA,$AB11,'SG08'!AG:AG)*SG08_+SUMIF('SG09'!$AA:$AA,$AB11,'SG09'!AG:AG)*SG09_+SUMIF('SG10'!$AA:$AA,$AB11,'SG10'!AG:AG)*SG10_+SUMIF('SG11'!$AA:$AA,$AB11,'SG11'!AG:AG)*SG11_+SUMIF('SG12'!$AA:$AA,$AB11,'SG12'!AG:AG)*SG12_+SUMIF('SG13'!$AA:$AA,$AB11,'SG13'!AG:AG)*SG13_+SUMIF('SG14'!$AA:$AA,$AB11,'SG14'!AG:AG)*SG14_+SUMIF('SG15'!$AA:$AA,$AB11,'SG15'!AG:AG)*SG15_) -> 13055000 | AI11: =AH11/AI$5 -> 3707.7535 | AJ11: =(SUMIF('SG01'!$AA:$AA,$AB11,'SG01'!AI:AI)*SG01_+SUMIF('SG02'!$AA:$AA,$AB11,'SG02'!AI:AI)*SG02_+SUMIF('SG03'!$AA:$AA,$AB11,'SG03'!AI:AI)*SG03_+SUMIF('SG04'!$AA:$AA,$AB11,'SG04'!AI:AI)*SG04_+SUMIF('SG05'!$AA:$AA,$AB11,'SG05'!AI:AI)*SG05_+SUMIF('SG06'!$AA:$AA,$AB11,'SG06'!AI:AI)*SG06_+SUMIF('SG07'!$AA:$AA,$AB11,'SG07'!AI:AI)*SG07_+SUMIF('SG08'!$AA:$AA,$AB11,'SG08'!AI:AI)*SG08_+SUMIF('SG09'!$AA:$AA,$AB11,'SG09'!AI:AI)*SG09_+SUMIF('SG10'!$AA:$AA,$AB11,'SG10'!AI:AI)*SG10_+SUMIF('SG11'!$AA:$AA,$AB11,'SG11'!AI:AI)*SG11_+SUMIF('SG12'!$AA:$AA,$AB11,'SG12'!AI:AI)*SG12_+SUMIF('SG13'!$AA:$AA,$AB11,'SG13'!AI:AI)*SG13_+SUMIF('SG14'!$AA:$AA,$AB11,'SG14'!AI:AI)*SG14_+SUMIF('SG15'!$AA:$AA,$AB11,'SG15'!AI:AI)*SG15_) -> 733 | AK11: =AJ11/$AI$5*100 -> 20.817949 | AL11: =AE11-AI11 -> -71.956024 | AM11: =AG11-AK11 -> -0.37386605
B12: MÓN ĂN | I12: =SUBTOTAL(9,I14:I112) -> 8244 | K12: =SUBTOTAL(9,K14:K112) -> 4.6307738e+08 | L12: =SUBTOTAL(9,L14:L112) -> 1403263000 | M12: =SUBTOTAL(9,M14:M112) -> 9.4018562e+08 | N12: =K12/L12 -> 0.33000042 | O12: =L12/L$10 -> 0.90500225 | P12: =M12/M$10 -> 0.91382527 | Q12: =I12/I$10 -> 0.51358086 | R12: =I12/$K$5*100 -> 223.23314 | S12: =R12*T$5 -> 655.84726 | T12: =IFERROR(S12*G12,0) -> 0 | V12: MIN Sales Contribution | X12: =3000000*SUM(Control!$B$2:$B$11) -> 3000000 | AB12: XIENTHIT.GSG | AC12: XIÊN THỊT NƯỚNG | AD12: =VLOOKUP(AB12,$B:$M,11,0) -> 66828000 | AE12: =AD12/AE$5 -> 18095.857 | AF12: =VLOOKUP(AB12,$B:$R,8,0) -> 1651 | AG12: =AF12/$AE$5*100 -> 44.706201 | AH12: =(SUMIF('SG01'!$AA:$AA,$AB12,'SG01'!AG:AG)*SG01_+SUMIF('SG02'!$AA:$AA,$AB12,'SG02'!AG:AG)*SG02_+SUMIF('SG03'!$AA:$AA,$AB12,'SG03'!AG:AG)*SG03_+SUMIF('SG04'!$AA:$AA,$AB12,'SG04'!AG:AG)*SG04_+SUMIF('SG05'!$AA:$AA,$AB12,'SG05'!AG:AG)*SG05_+SUMIF('SG06'!$AA:$AA,$AB12,'SG06'!AG:AG)*SG06_+SUMIF('SG07'!$AA:$AA,$AB12,'SG07'!AG:AG)*SG07_+SUMIF('SG08'!$AA:$AA,$AB12,'SG08'!AG:AG)*SG08_+SUMIF('SG09'!$AA:$AA,$AB12,'SG09'!AG:AG)*SG09_+SUMIF('SG10'!$AA:$AA,$AB12,'SG10'!AG:AG)*SG10_+SUMIF('SG11'!$AA:$AA,$AB12,'SG11'!AG:AG)*SG11_+SUMIF('SG12'!$AA:$AA,$AB12,'SG12'!AG:AG)*SG12_+SUMIF('SG13'!$AA:$AA,$AB12,'SG13'!AG:AG)*SG13_+SUMIF('SG14'!$AA:$AA,$AB12,'SG14'!AG:AG)*SG14_+SUMIF('SG15'!$AA:$AA,$AB12,'SG15'!AG:AG)*SG15_) -> 64692000 | AI12: =AH12/AI$5 -> 18373.189 | AJ12: =(SUMIF('SG01'!$AA:$AA,$AB12,'SG01'!AI:AI)*SG01_+SUMIF('SG02'!$AA:$AA,$AB12,'SG02'!AI:AI)*SG02_+SUMIF('SG03'!$AA:$AA,$AB12,'SG03'!AI:AI)*SG03_+SUMIF('SG04'!$AA:$AA,$AB12,'SG04'!AI:AI)*SG04_+SUMIF('SG05'!$AA:$AA,$AB12,'SG05'!AI:AI)*SG05_+SUMIF('SG06'!$AA:$AA,$AB12,'SG06'!AI:AI)*SG06_+SUMIF('SG07'!$AA:$AA,$AB12,'SG07'!AI:AI)*SG07_+SUMIF('SG08'!$AA:$AA,$AB12,'SG08'!AI:AI)*SG08_+SUMIF('SG09'!$AA:$AA,$AB12,'SG09'!AI:AI)*SG09_+SUMIF('SG10'!$AA:$AA,$AB12,'SG10'!AI:AI)*SG10_+SUMIF('SG11'!$AA:$AA,$AB12,'SG11'!AI:AI)*SG11_+SUMIF('SG12'!$AA:$AA,$AB12,'SG12'!AI:AI)*SG12_+SUMIF('SG13'!$AA:$AA,$AB12,'SG13'!AI:AI)*SG13_+SUMIF('SG14'!$AA:$AA,$AB12,'SG14'!AI:AI)*SG14_+SUMIF('SG15'!$AA:$AA,$AB12,'SG15'!AI:AI)*SG15_) -> 1594 | AK12: =AJ12/$AI$5*100 -> 45.27123 | AL12: =AE12-AI12 -> -277.33241 | AM12: =AG12-AK12 -> -0.56502884
AB13: THITBO.GSG | AC13: THỊT BÒ | AD13: =VLOOKUP(AB13,$B:$M,11,0) -> 346497000 | AE13: =AD13/AE$5 -> 93825.345 | AF13: =VLOOKUP(AB13,$B:$R,8,0) -> 1717 | AG13: =AF13/$AE$5*100 -> 46.493366 | AH13: =(SUMIF('SG01'!$AA:$AA,$AB13,'SG01'!AG:AG)*SG01_+SUMIF('SG02'!$AA:$AA,$AB13,'SG02'!AG:AG)*SG02_+SUMIF('SG03'!$AA:$AA,$AB13,'SG03'!AG:AG)*SG03_+SUMIF('SG04'!$AA:$AA,$AB13,'SG04'!AG:AG)*SG04_+SUMIF('SG05'!$AA:$AA,$AB13,'SG05'!AG:AG)*SG05_+SUMIF('SG06'!$AA:$AA,$AB13,'SG06'!AG:AG)*SG06_+SUMIF('SG07'!$AA:$AA,$AB13,'SG07'!AG:AG)*SG07_+SUMIF('SG08'!$AA:$AA,$AB13,'SG08'!AG:AG)*SG08_+SUMIF('SG09'!$AA:$AA,$AB13,'SG09'!AG:AG)*SG09_+SUMIF('SG10'!$AA:$AA,$AB13,'SG10'!AG:AG)*SG10_+SUMIF('SG11'!$AA:$AA,$AB13,'SG11'!AG:AG)*SG11_+SUMIF('SG12'!$AA:$AA,$AB13,'SG12'!AG:AG)*SG12_+SUMIF('SG13'!$AA:$AA,$AB13,'SG13'!AG:AG)*SG13_+SUMIF('SG14'!$AA:$AA,$AB13,'SG14'!AG:AG)*SG14_+SUMIF('SG15'!$AA:$AA,$AB13,'SG15'!AG:AG)*SG15_) -> 334514000 | AI13: =AH13/AI$5 -> 95005.396 | AJ13: =(SUMIF('SG01'!$AA:$AA,$AB13,'SG01'!AI:AI)*SG01_+SUMIF('SG02'!$AA:$AA,$AB13,'SG02'!AI:AI)*SG02_+SUMIF('SG03'!$AA:$AA,$AB13,'SG03'!AI:AI)*SG03_+SUMIF('SG04'!$AA:$AA,$AB13,'SG04'!AI:AI)*SG04_+SUMIF('SG05'!$AA:$AA,$AB13,'SG05'!AI:AI)*SG05_+SUMIF('SG06'!$AA:$AA,$AB13,'SG06'!AI:AI)*SG06_+SUMIF('SG07'!$AA:$AA,$AB13,'SG07'!AI:AI)*SG07_+SUMIF('SG08'!$AA:$AA,$AB13,'SG08'!AI:AI)*SG08_+SUMIF('SG09'!$AA:$AA,$AB13,'SG09'!AI:AI)*SG09_+SUMIF('SG10'!$AA:$AA,$AB13,'SG10'!AI:AI)*SG10_+SUMIF('SG11'!$AA:$AA,$AB13,'SG11'!AI:AI)*SG11_+SUMIF('SG12'!$AA:$AA,$AB13,'SG12'!AI:AI)*SG12_+SUMIF('SG13'!$AA:$AA,$AB13,'SG13'!AI:AI)*SG13_+SUMIF('SG14'!$AA:$AA,$AB13,'SG14'!AI:AI)*SG14_+SUMIF('SG15'!$AA:$AA,$AB13,'SG15'!AI:AI)*SG15_) -> 1655 | AK13: =AJ13/$AI$5*100 -> 47.003692 | AL13: =AE13-AI13 -> -1180.0509 | AM13: =AG13-AK13 -> -0.51032631
B14: CPL.BEP | C14: CHI PHÍ QUẦY LINE NƯỚC CHẤM | I14: =SUBTOTAL(9,I15:I16) -> 1 | K14: =SUBTOTAL(9,K15:K16) -> 34599678 | L14: =SUBTOTAL(9,L15:L16) -> 0 | M14: =SUBTOTAL(9,M15:M16) -> -34599678 | N14: =K14/L14 -> #DIV/0! | O14: =L14/L$10 -> 0 | P14: =M14/M$10 -> -0.033629594 | Q14: =I14/I$10 -> 6.2297533e-05 | R14: =I14/$K$5*100 -> 0.027078256 | S14: =R14*T$5 -> 0.079554495 | T14: =IFERROR(S14*G14,0) -> 0 | AB14: THITHEO.GSG | AC14: THỊT HEO | AD14: =VLOOKUP(AB14,$B:$M,11,0) -> 75740000 | AE14: =AD14/AE$5 -> 20509.071 | AF14: =VLOOKUP(AB14,$B:$R,8,0) -> 750 | AG14: =AF14/$AE$5*100 -> 20.308692 | AH14: =(SUMIF('SG01'!$AA:$AA,$AB14,'SG01'!AG:AG)*SG01_+SUMIF('SG02'!$AA:$AA,$AB14,'SG02'!AG:AG)*SG02_+SUMIF('SG03'!$AA:$AA,$AB14,'SG03'!AG:AG)*SG03_+SUMIF('SG04'!$AA:$AA,$AB14,'SG04'!AG:AG)*SG04_+SUMIF('SG05'!$AA:$AA,$AB14,'SG05'!AG:AG)*SG05_+SUMIF('SG06'!$AA:$AA,$AB14,'SG06'!AG:AG)*SG06_+SUMIF('SG07'!$AA:$AA,$AB14,'SG07'!AG:AG)*SG07_+SUMIF('SG08'!$AA:$AA,$AB14,'SG08'!AG:AG)*SG08_+SUMIF('SG09'!$AA:$AA,$AB14,'SG09'!AG:AG)*SG09_+SUMIF('SG10'!$AA:$AA,$AB14,'SG10'!AG:AG)*SG10_+SUMIF('SG11'!$AA:$AA,$AB14,'SG11'!AG:AG)*SG11_+SUMIF('SG12'!$AA:$AA,$AB14,'SG12'!AG:AG)*SG12_+SUMIF('SG13'!$AA:$AA,$AB14,'SG13'!AG:AG)*SG13_+SUMIF('SG14'!$AA:$AA,$AB14,'SG14'!AG:AG)*SG14_+SUMIF('SG15'!$AA:$AA,$AB14,'SG15'!AG:AG)*SG15_) -> 72275000 | AI14: =AH14/AI$5 -> 20526.839 | AJ14: =(SUMIF('SG01'!$AA:$AA,$AB14,'SG01'!AI:AI)*SG01_+SUMIF('SG02'!$AA:$AA,$AB14,'SG02'!AI:AI)*SG02_+SUMIF('SG03'!$AA:$AA,$AB14,'SG03'!AI:AI)*SG03_+SUMIF('SG04'!$AA:$AA,$AB14,'SG04'!AI:AI)*SG04_+SUMIF('SG05'!$AA:$AA,$AB14,'SG05'!AI:AI)*SG05_+SUMIF('SG06'!$AA:$AA,$AB14,'SG06'!AI:AI)*SG06_+SUMIF('SG07'!$AA:$AA,$AB14,'SG07'!AI:AI)*SG07_+SUMIF('SG08'!$AA:$AA,$AB14,'SG08'!AI:AI)*SG08_+SUMIF('SG09'!$AA:$AA,$AB14,'SG09'!AI:AI)*SG09_+SUMIF('SG10'!$AA:$AA,$AB14,'SG10'!AI:AI)*SG10_+SUMIF('SG11'!$AA:$AA,$AB14,'SG11'!AI:AI)*SG11_+SUMIF('SG12'!$AA:$AA,$AB14,'SG12'!AI:AI)*SG12_+SUMIF('SG13'!$AA:$AA,$AB14,'SG13'!AI:AI)*SG13_+SUMIF('SG14'!$AA:$AA,$AB14,'SG14'!AI:AI)*SG14_+SUMIF('SG15'!$AA:$AA,$AB14,'SG15'!AI:AI)*SG15_) -> 715 | AK14: =AJ14/$AI$5*100 -> 20.306731 | AL14: =AE14-AI14 -> -17.76775 | AM14: =AG14-AK14 -> 0.0019610779
A15: 1 | B15: LINEBEP | C15: =VLOOKUP(B15,'SG01'!$B:$E,2,0) -> Chi phí quầy line nước chấm | F15: 9368.9895 | G15: =L15/I15 -> 0 | H15: =G15-F15 -> -9368.9895 | I15: =(SUMIF('SG01'!$B:$B,$B15,'SG01'!I:I)*SG01_+SUMIF('SG02'!$B:$B,$B15,'SG02'!I:I)*SG02_+SUMIF('SG03'!$B:$B,$B15,'SG03'!I:I)*SG03_+SUMIF('SG04'!$B:$B,$B15,'SG04'!I:I)*SG04_+SUMIF('SG05'!$B:$B,$B15,'SG05'!I:I)*SG05_+SUMIF('SG06'!$B:$B,$B15,'SG06'!I:I)*SG06_+SUMIF('SG07'!$B:$B,$B15,'SG07'!I:I)*SG07_+SUMIF('SG08'!$B:$B,$B15,'SG08'!I:I)*SG08_+SUMIF('SG09'!$B:$B,$B15,'SG09'!I:I)*SG09_+SUMIF('SG10'!$B:$B,$B15,'SG10'!I:I)*SG10_+SUMIF('SG11'!$B:$B,$B15,'SG11'!I:I)*SG11_+SUMIF('SG12'!$B:$B,$B15,'SG12'!I:I)*SG12_+SUMIF('SG13'!$B:$B,$B15,'SG13'!I:I)*SG13_+SUMIF('SG14'!$B:$B,$B15,'SG14'!I:I)*SG14_+SUMIF('SG15'!$B:$B,$B15,'SG15'!I:I)*SG15_) -> 1 | K15: =(SUMIF('SG01'!$B:$B,$B15,'SG01'!K:K)*SG01_+SUMIF('SG02'!$B:$B,$B15,'SG02'!K:K)*SG02_+SUMIF('SG03'!$B:$B,$B15,'SG03'!K:K)*SG03_+SUMIF('SG04'!$B:$B,$B15,'SG04'!K:K)*SG04_+SUMIF('SG05'!$B:$B,$B15,'SG05'!K:K)*SG05_+SUMIF('SG06'!$B:$B,$B15,'SG06'!K:K)*SG06_+SUMIF('SG07'!$B:$B,$B15,'SG07'!K:K)*SG07_+SUMIF('SG08'!$B:$B,$B15,'SG08'!K:K)*SG08_+SUMIF('SG09'!$B:$B,$B15,'SG09'!K:K)*SG09_+SUMIF('SG10'!$B:$B,$B15,'SG10'!K:K)*SG10_+SUMIF('SG11'!$B:$B,$B15,'SG11'!K:K)*SG11_+SUMIF('SG12'!$B:$B,$B15,'SG12'!K:K)*SG12_+SUMIF('SG13'!$B:$B,$B15,'SG13'!K:K)*SG13_+SUMIF('SG14'!$B:$B,$B15,'SG14'!K:K)*SG14_+SUMIF('SG15'!$B:$B,$B15,'SG15'!K:K)*SG15_) -> 34599678 | L15: =(SUMIF('SG01'!$B:$B,$B15,'SG01'!L:L)*SG01_+SUMIF('SG02'!$B:$B,$B15,'SG02'!L:L)*SG02_+SUMIF('SG03'!$B:$B,$B15,'SG03'!L:L)*SG03_+SUMIF('SG04'!$B:$B,$B15,'SG04'!L:L)*SG04_+SUMIF('SG05'!$B:$B,$B15,'SG05'!L:L)*SG05_+SUMIF('SG06'!$B:$B,$B15,'SG06'!L:L)*SG06_+SUMIF('SG07'!$B:$B,$B15,'SG07'!L:L)*SG07_+SUMIF('SG08'!$B:$B,$B15,'SG08'!L:L)*SG08_+SUMIF('SG09'!$B:$B,$B15,'SG09'!L:L)*SG09_+SUMIF('SG10'!$B:$B,$B15,'SG10'!L:L)*SG10_+SUMIF('SG11'!$B:$B,$B15,'SG11'!L:L)*SG11_+SUMIF('SG12'!$B:$B,$B15,'SG12'!L:L)*SG12_+SUMIF('SG13'!$B:$B,$B15,'SG13'!L:L)*SG13_+SUMIF('SG14'!$B:$B,$B15,'SG14'!L:L)*SG14_+SUMIF('SG15'!$B:$B,$B15,'SG15'!L:L)*SG15_) -> 0 | M15: =L15-K15 -> -34599678 | N15: =K15/L15 -> #DIV/0! | O15: =L15/L$10 -> 0 | P15: =M15/M$10 -> -0.033629594 | Q15: =I15/I$10 -> 6.2297533e-05 | R15: =I15/$K$5*100 -> 0.027078256 | S15: =R15*T$5 -> 0.079554495 | T15: =IFERROR(S15*G15,0) -> 0 | V15: =IF(B15<>"",IFERROR(IF($I15>=$X$10,"High","Low"),""),"") -> Low | W15: =IF(B15<>"",IFERROR(IF($L15>=$X$12,"High","Low"),""),"") -> Low | X15: =IF(B15<>"",IFERROR(IF(AND(V15="high",W15="high"),"Star",IF(AND(V15="low",W15="high"),"Puzzle",(IF(AND(V15="high",W15="low"),"Horse","Dog")))),""),"") -> Dog | AB15: HSAN.GSG | AC15: HẢI SẢN | AD15: =VLOOKUP(AB15,$B:$M,11,0) -> 66870000 | AE15: =AD15/AE$5 -> 18107.23 | AF15: =VLOOKUP(AB15,$B:$R,8,0) -> 521 | AG15: =AF15/$AE$5*100 -> 14.107771 | AH15: =(SUMIF('SG01'!$AA:$AA,$AB15,'SG01'!AG:AG)*SG01_+SUMIF('SG02'!$AA:$AA,$AB15,'SG02'!AG:AG)*SG02_+SUMIF('SG03'!$AA:$AA,$AB15,'SG03'!AG:AG)*SG03_+SUMIF('SG04'!$AA:$AA,$AB15,'SG04'!AG:AG)*SG04_+SUMIF('SG05'!$AA:$AA,$AB15,'SG05'!AG:AG)*SG05_+SUMIF('SG06'!$AA:$AA,$AB15,'SG06'!AG:AG)*SG06_+SUMIF('SG07'!$AA:$AA,$AB15,'SG07'!AG:AG)*SG07_+SUMIF('SG08'!$AA:$AA,$AB15,'SG08'!AG:AG)*SG08_+SUMIF('SG09'!$AA:$AA,$AB15,'SG09'!AG:AG)*SG09_+SUMIF('SG10'!$AA:$AA,$AB15,'SG10'!AG:AG)*SG10_+SUMIF('SG11'!$AA:$AA,$AB15,'SG11'!AG:AG)*SG11_+SUMIF('SG12'!$AA:$AA,$AB15,'SG12'!AG:AG)*SG12_+SUMIF('SG13'!$AA:$AA,$AB15,'SG13'!AG:AG)*SG13_+SUMIF('SG14'!$AA:$AA,$AB15,'SG14'!AG:AG)*SG14_+SUMIF('SG15'!$AA:$AA,$AB15,'SG15'!AG:AG)*SG15_) -> 65500000 | AI15: =AH15/AI$5 -> 18602.67 | AJ15: =(SUMIF('SG01'!$AA:$AA,$AB15,'SG01'!AI:AI)*SG01_+SUMIF('SG02'!$AA:$AA,$AB15,'SG02'!AI:AI)*SG02_+SUMIF('SG03'!$AA:$AA,$AB15,'SG03'!AI:AI)*SG03_+SUMIF('SG04'!$AA:$AA,$AB15,'SG04'!AI:AI)*SG04_+SUMIF('SG05'!$AA:$AA,$AB15,'SG05'!AI:AI)*SG05_+SUMIF('SG06'!$AA:$AA,$AB15,'SG06'!AI:AI)*SG06_+SUMIF('SG07'!$AA:$AA,$AB15,'SG07'!AI:AI)*SG07_+SUMIF('SG08'!$AA:$AA,$AB15,'SG08'!AI:AI)*SG08_+SUMIF('SG09'!$AA:$AA,$AB15,'SG09'!AI:AI)*SG09_+SUMIF('SG10'!$AA:$AA,$AB15,'SG10'!AI:AI)*SG10_+SUMIF('SG11'!$AA:$AA,$AB15,'SG11'!AI:AI)*SG11_+SUMIF('SG12'!$AA:$AA,$AB15,'SG12'!AI:AI)*SG12_+SUMIF('SG13'!$AA:$AA,$AB15,'SG13'!AI:AI)*SG13_+SUMIF('SG14'!$AA:$AA,$AB15,'SG14'!AI:AI)*SG14_+SUMIF('SG15'!$AA:$AA,$AB15,'SG15'!AI:AI)*SG15_) -> 508 | AK15: =AJ15/$AI$5*100 -> 14.427719 | AL15: =AE15-AI15 -> -495.4398 | AM15: =AG15-AK15 -> -0.31994794
AB16: ANKEM.GSG | AC16: CÁC MÓN DÙNG KÈM | AD16: =VLOOKUP(AB16,$B:$M,11,0) -> 104162000 | AE16: =AD16/AE$5 -> 28205.253 | AF16: =VLOOKUP(AB16,$B:$R,8,0) -> 1369 | AG16: =AF16/$AE$5*100 -> 37.070133 | AH16: =(SUMIF('SG01'!$AA:$AA,$AB16,'SG01'!AG:AG)*SG01_+SUMIF('SG02'!$AA:$AA,$AB16,'SG02'!AG:AG)*SG02_+SUMIF('SG03'!$AA:$AA,$AB16,'SG03'!AG:AG)*SG03_+SUMIF('SG04'!$AA:$AA,$AB16,'SG04'!AG:AG)*SG04_+SUMIF('SG05'!$AA:$AA,$AB16,'SG05'!AG:AG)*SG05_+SUMIF('SG06'!$AA:$AA,$AB16,'SG06'!AG:AG)*SG06_+SUMIF('SG07'!$AA:$AA,$AB16,'SG07'!AG:AG)*SG07_+SUMIF('SG08'!$AA:$AA,$AB16,'SG08'!AG:AG)*SG08_+SUMIF('SG09'!$AA:$AA,$AB16,'SG09'!AG:AG)*SG09_+SUMIF('SG10'!$AA:$AA,$AB16,'SG10'!AG:AG)*SG10_+SUMIF('SG11'!$AA:$AA,$AB16,'SG11'!AG:AG)*SG11_+SUMIF('SG12'!$AA:$AA,$AB16,'SG12'!AG:AG)*SG12_+SUMIF('SG13'!$AA:$AA,$AB16,'SG13'!AG:AG)*SG13_+SUMIF('SG14'!$AA:$AA,$AB16,'SG14'!AG:AG)*SG14_+SUMIF('SG15'!$AA:$AA,$AB16,'SG15'!AG:AG)*SG15_) -> 100737000 | AI16: =AH16/AI$5 -> 28610.338 | AJ16: =(SUMIF('SG01'!$AA:$AA,$AB16,'SG01'!AI:AI)*SG01_+SUMIF('SG02'!$AA:$AA,$AB16,'SG02'!AI:AI)*SG02_+SUMIF('SG03'!$AA:$AA,$AB16,'SG03'!AI:AI)*SG03_+SUMIF('SG04'!$AA:$AA,$AB16,'SG04'!AI:AI)*SG04_+SUMIF('SG05'!$AA:$AA,$AB16,'SG05'!AI:AI)*SG05_+SUMIF('SG06'!$AA:$AA,$AB16,'SG06'!AI:AI)*SG06_+SUMIF('SG07'!$AA:$AA,$AB16,'SG07'!AI:AI)*SG07_+SUMIF('SG08'!$AA:$AA,$AB16,'SG08'!AI:AI)*SG08_+SUMIF('SG09'!$AA:$AA,$AB16,'SG09'!AI:AI)*SG09_+SUMIF('SG10'!$AA:$AA,$AB16,'SG10'!AI:AI)*SG10_+SUMIF('SG11'!$AA:$AA,$AB16,'SG11'!AI:AI)*SG11_+SUMIF('SG12'!$AA:$AA,$AB16,'SG12'!AI:AI)*SG12_+SUMIF('SG13'!$AA:$AA,$AB16,'SG13'!AI:AI)*SG13_+SUMIF('SG14'!$AA:$AA,$AB16,'SG14'!AI:AI)*SG14_+SUMIF('SG15'!$AA:$AA,$AB16,'SG15'!AI:AI)*SG15_) -> 1318 | AK16: =AJ16/$AI$5*100 -> 37.432548 | AL16: =AE16-AI16 -> -405.08479 | AM16: =AG16-AK16 -> -0.36241489
B17: KVI.GSG | C17: KHAI VỊ | I17: =SUBTOTAL(9,I18:I31) -> 633 | K17: =SUBTOTAL(9,K18:K31) -> 14750648 | L17: =SUBTOTAL(9,L18:L31) -> 51978000 | M17: =SUBTOTAL(9,M18:M31) -> 37227352 | N17: =K17/L17 -> 0.28378638 | O17: =L17/L$10 -> 0.033522017 | P17: =M17/M$10 -> 0.036183594 | Q17: =I17/I$10 -> 0.039434338 | R17: =I17/$K$5*100 -> 17.140536 | S17: =R17*T$5 -> 50.357995 | T17: =IFERROR(S17*G17,0) -> 0 | AB17: COMBO.GSG | AC17: COMBO HONG KONG | AD17: =VLOOKUP(AB17,$B:$M,11,0) -> 677761000 | AE17: =AD17/AE$5 -> 183525.86 | AF17: =VLOOKUP(AB17,$B:$R,8,0) -> 847 | AG17: =AF17/$AE$5*100 -> 22.935283 | AH17: =(SUMIF('SG01'!$AA:$AA,$AB17,'SG01'!AG:AG)*SG01_+SUMIF('SG02'!$AA:$AA,$AB17,'SG02'!AG:AG)*SG02_+SUMIF('SG03'!$AA:$AA,$AB17,'SG03'!AG:AG)*SG03_+SUMIF('SG04'!$AA:$AA,$AB17,'SG04'!AG:AG)*SG04_+SUMIF('SG05'!$AA:$AA,$AB17,'SG05'!AG:AG)*SG05_+SUMIF('SG06'!$AA:$AA,$AB17,'SG06'!AG:AG)*SG06_+SUMIF('SG07'!$AA:$AA,$AB17,'SG07'!AG:AG)*SG07_+SUMIF('SG08'!$AA:$AA,$AB17,'SG08'!AG:AG)*SG08_+SUMIF('SG09'!$AA:$AA,$AB17,'SG09'!AG:AG)*SG09_+SUMIF('SG10'!$AA:$AA,$AB17,'SG10'!AG:AG)*SG10_+SUMIF('SG11'!$AA:$AA,$AB17,'SG11'!AG:AG)*SG11_+SUMIF('SG12'!$AA:$AA,$AB17,'SG12'!AG:AG)*SG12_+SUMIF('SG13'!$AA:$AA,$AB17,'SG13'!AG:AG)*SG13_+SUMIF('SG14'!$AA:$AA,$AB17,'SG14'!AG:AG)*SG14_+SUMIF('SG15'!$AA:$AA,$AB17,'SG15'!AG:AG)*SG15_) -> 637403000 | AI17: =AH17/AI$5 -> 181028.97 | AJ17: =(SUMIF('SG01'!$AA:$AA,$AB17,'SG01'!AI:AI)*SG01_+SUMIF('SG02'!$AA:$AA,$AB17,'SG02'!AI:AI)*SG02_+SUMIF('SG03'!$AA:$AA,$AB17,'SG03'!AI:AI)*SG03_+SUMIF('SG04'!$AA:$AA,$AB17,'SG04'!AI:AI)*SG04_+SUMIF('SG05'!$AA:$AA,$AB17,'SG05'!AI:AI)*SG05_+SUMIF('SG06'!$AA:$AA,$AB17,'SG06'!AI:AI)*SG06_+SUMIF('SG07'!$AA:$AA,$AB17,'SG07'!AI:AI)*SG07_+SUMIF('SG08'!$AA:$AA,$AB17,'SG08'!AI:AI)*SG08_+SUMIF('SG09'!$AA:$AA,$AB17,'SG09'!AI:AI)*SG09_+SUMIF('SG10'!$AA:$AA,$AB17,'SG10'!AI:AI)*SG10_+SUMIF('SG11'!$AA:$AA,$AB17,'SG11'!AI:AI)*SG11_+SUMIF('SG12'!$AA:$AA,$AB17,'SG12'!AI:AI)*SG12_+SUMIF('SG13'!$AA:$AA,$AB17,'SG13'!AI:AI)*SG13_+SUMIF('SG14'!$AA:$AA,$AB17,'SG14'!AI:AI)*SG14_+SUMIF('SG15'!$AA:$AA,$AB17,'SG15'!AI:AI)*SG15_) -> 796 | AK17: =AJ17/$AI$5*100 -> 22.607214 | AL17: =AE17-AI17 -> 2496.8907 | AM17: =AG17-AK17 -> 0.32806911
A18: 1 | B18: GSKVI002 | C18: =VLOOKUP(B18,'SG01'!$B:$E,2,0) -> Khoai Tây Lắc Phô Mai | E18: =VLOOKUP(B18,'SG01'!$B:$E,4,0) -> Phần | F18: =K18/I18 -> 15238.609 | G18: =L18/I18 -> 61084.337 | H18: =G18-F18 -> 45845.728 | I18: =(SUMIF('SG01'!$B:$B,$B18,'SG01'!I:I)*SG01_+SUMIF('SG02'!$B:$B,$B18,'SG02'!I:I)*SG02_+SUMIF('SG03'!$B:$B,$B18,'SG03'!I:I)*SG03_+SUMIF('SG04'!$B:$B,$B18,'SG04'!I:I)*SG04_+SUMIF('SG05'!$B:$B,$B18,'SG05'!I:I)*SG05_+SUMIF('SG06'!$B:$B,$B18,'SG06'!I:I)*SG06_+SUMIF('SG07'!$B:$B,$B18,'SG07'!I:I)*SG07_+SUMIF('SG08'!$B:$B,$B18,'SG08'!I:I)*SG08_+SUMIF('SG09'!$B:$B,$B18,'SG09'!I:I)*SG09_+SUMIF('SG10'!$B:$B,$B18,'SG10'!I:I)*SG10_+SUMIF('SG11'!$B:$B,$B18,'SG11'!I:I)*SG11_+SUMIF('SG12'!$B:$B,$B18,'SG12'!I:I)*SG12_+SUMIF('SG13'!$B:$B,$B18,'SG13'!I:I)*SG13_+SUMIF('SG14'!$B:$B,$B18,'SG14'!I:I)*SG14_+SUMIF('SG15'!$B:$B,$B18,'SG15'!I:I)*SG15_) -> 83 | K18: =(SUMIF('SG01'!$B:$B,$B18,'SG01'!K:K)*SG01_+SUMIF('SG02'!$B:$B,$B18,'SG02'!K:K)*SG02_+SUMIF('SG03'!$B:$B,$B18,'SG03'!K:K)*SG03_+SUMIF('SG04'!$B:$B,$B18,'SG04'!K:K)*SG04_+SUMIF('SG05'!$B:$B,$B18,'SG05'!K:K)*SG05_+SUMIF('SG06'!$B:$B,$B18,'SG06'!K:K)*SG06_+SUMIF('SG07'!$B:$B,$B18,'SG07'!K:K)*SG07_+SUMIF('SG08'!$B:$B,$B18,'SG08'!K:K)*SG08_+SUMIF('SG09'!$B:$B,$B18,'SG09'!K:K)*SG09_+SUMIF('SG10'!$B:$B,$B18,'SG10'!K:K)*SG10_+SUMIF('SG11'!$B:$B,$B18,'SG11'!K:K)*SG11_+SUMIF('SG12'!$B:$B,$B18,'SG12'!K:K)*SG12_+SUMIF('SG13'!$B:$B,$B18,'SG13'!K:K)*SG13_+SUMIF('SG14'!$B:$B,$B18,'SG14'!K:K)*SG14_+SUMIF('SG15'!$B:$B,$B18,'SG15'!K:K)*SG15_) -> 1264804.6 | L18: =(SUMIF('SG01'!$B:$B,$B18,'SG01'!L:L)*SG01_+SUMIF('SG02'!$B:$B,$B18,'SG02'!L:L)*SG02_+SUMIF('SG03'!$B:$B,$B18,'SG03'!L:L)*SG03_+SUMIF('SG04'!$B:$B,$B18,'SG04'!L:L)*SG04_+SUMIF('SG05'!$B:$B,$B18,'SG05'!L:L)*SG05_+SUMIF('SG06'!$B:$B,$B18,'SG06'!L:L)*SG06_+SUMIF('SG07'!$B:$B,$B18,'SG07'!L:L)*SG07_+SUMIF('SG08'!$B:$B,$B18,'SG08'!L:L)*SG08_+SUMIF('SG09'!$B:$B,$B18,'SG09'!L:L)*SG09_+SUMIF('SG10'!$B:$B,$B18,'SG10'!L:L)*SG10_+SUMIF('SG11'!$B:$B,$B18,'SG11'!L:L)*SG11_+SUMIF('SG12'!$B:$B,$B18,'SG12'!L:L)*SG12_+SUMIF('SG13'!$B:$B,$B18,'SG13'!L:L)*SG13_+SUMIF('SG14'!$B:$B,$B18,'SG14'!L:L)*SG14_+SUMIF('SG15'!$B:$B,$B18,'SG15'!L:L)*SG15_) -> 5070000 | M18: =L18-K18 -> 3805195.4 | N18: =K18/L18 -> 0.24946835 | O18: =L18/L$10 -> 0.0032697801 | P18: =M18/M$10 -> 0.0036985077 | Q18: =I18/I$10 -> 0.0051706952 | R18: =I18/$K$5*100 -> 2.2474953 | S18: =R18*T$5 -> 6.6030231 | T18: =IFERROR(S18*G18,0) -> 403341.29 | V18: =IF(B18<>"",IFERROR(IF($I18>=$X$10,"High","Low"),""),"") -> Low | W18: =IF(B18<>"",IFERROR(IF($L18>=$X$12,"High","Low"),""),"") -> High | X18: =IF(B18<>"",IFERROR(IF(AND(V18="high",W18="high"),"Star",IF(AND(V18="low",W18="high"),"Puzzle",(IF(AND(V18="high",W18="low"),"Horse","Dog")))),""),"") -> Puzzle | AB18: DUPC.GSG | AC18: ĐỒ UỐNG PHA CHẾ | AD18: =VLOOKUP(AB18,$B:$M,11,0) -> 57601000 | AE18: =AD18/AE$5 -> 15597.346 | AF18: =VLOOKUP(AB18,$B:$R,8,0) -> 1205 | AG18: =AF18/$AE$5*100 -> 32.629299 | AH18: =(SUMIF('SG01'!$AA:$AA,$AB18,'SG01'!AG:AG)*SG01_+SUMIF('SG02'!$AA:$AA,$AB18,'SG02'!AG:AG)*SG02_+SUMIF('SG03'!$AA:$AA,$AB18,'SG03'!AG:AG)*SG03_+SUMIF('SG04'!$AA:$AA,$AB18,'SG04'!AG:AG)*SG04_+SUMIF('SG05'!$AA:$AA,$AB18,'SG05'!AG:AG)*SG05_+SUMIF('SG06'!$AA:$AA,$AB18,'SG06'!AG:AG)*SG06_+SUMIF('SG07'!$AA:$AA,$AB18,'SG07'!AG:AG)*SG07_+SUMIF('SG08'!$AA:$AA,$AB18,'SG08'!AG:AG)*SG08_+SUMIF('SG09'!$AA:$AA,$AB18,'SG09'!AG:AG)*SG09_+SUMIF('SG10'!$AA:$AA,$AB18,'SG10'!AG:AG)*SG10_+SUMIF('SG11'!$AA:$AA,$AB18,'SG11'!AG:AG)*SG11_+SUMIF('SG12'!$AA:$AA,$AB18,'SG12'!AG:AG)*SG12_+SUMIF('SG13'!$AA:$AA,$AB18,'SG13'!AG:AG)*SG13_+SUMIF('SG14'!$AA:$AA,$AB18,'SG14'!AG:AG)*SG14_+SUMIF('SG15'!$AA:$AA,$AB18,'SG15'!AG:AG)*SG15_) -> 54516000 | AI18: =AH18/AI$5 -> 15483.101 | AJ18: =(SUMIF('SG01'!$AA:$AA,$AB18,'SG01'!AI:AI)*SG01_+SUMIF('SG02'!$AA:$AA,$AB18,'SG02'!AI:AI)*SG02_+SUMIF('SG03'!$AA:$AA,$AB18,'SG03'!AI:AI)*SG03_+SUMIF('SG04'!$AA:$AA,$AB18,'SG04'!AI:AI)*SG04_+SUMIF('SG05'!$AA:$AA,$AB18,'SG05'!AI:AI)*SG05_+SUMIF('SG06'!$AA:$AA,$AB18,'SG06'!AI:AI)*SG06_+SUMIF('SG07'!$AA:$AA,$AB18,'SG07'!AI:AI)*SG07_+SUMIF('SG08'!$AA:$AA,$AB18,'SG08'!AI:AI)*SG08_+SUMIF('SG09'!$AA:$AA,$AB18,'SG09'!AI:AI)*SG09_+SUMIF('SG10'!$AA:$AA,$AB18,'SG10'!AI:AI)*SG10_+SUMIF('SG11'!$AA:$AA,$AB18,'SG11'!AI:AI)*SG11_+SUMIF('SG12'!$AA:$AA,$AB18,'SG12'!AI:AI)*SG12_+SUMIF('SG13'!$AA:$AA,$AB18,'SG13'!AI:AI)*SG13_+SUMIF('SG14'!$AA:$AA,$AB18,'SG14'!AI:AI)*SG14_+SUMIF('SG15'!$AA:$AA,$AB18,'SG15'!AI:AI)*SG15_) -> 1140 | AK18: =AJ18/$AI$5*100 -> 32.377166 | AL18: =AE18-AI18 -> 114.24494 | AM18: =AG18-AK18 -> 0.2521331
A19: 2 | B19: GSKVI005 | C19: =VLOOKUP(B19,'SG02'!$B:$E,2,0) -> Rau Salad Hải Sản | E19: =VLOOKUP(B19,'SG01'!$B:$E,4,0) -> Phần | F19: =K19/I19 -> 34202.473 | G19: =L19/I19 -> 123125 | H19: =G19-F19 -> 88922.527 | I19: =(SUMIF('SG01'!$B:$B,$B19,'SG01'!I:I)*SG01_+SUMIF('SG02'!$B:$B,$B19,'SG02'!I:I)*SG02_+SUMIF('SG03'!$B:$B,$B19,'SG03'!I:I)*SG03_+SUMIF('SG04'!$B:$B,$B19,'SG04'!I:I)*SG04_+SUMIF('SG05'!$B:$B,$B19,'SG05'!I:I)*SG05_+SUMIF('SG06'!$B:$B,$B19,'SG06'!I:I)*SG06_+SUMIF('SG07'!$B:$B,$B19,'SG07'!I:I)*SG07_+SUMIF('SG08'!$B:$B,$B19,'SG08'!I:I)*SG08_+SUMIF('SG09'!$B:$B,$B19,'SG09'!I:I)*SG09_+SUMIF('SG10'!$B:$B,$B19,'SG10'!I:I)*SG10_+SUMIF('SG11'!$B:$B,$B19,'SG11'!I:I)*SG11_+SUMIF('SG12'!$B:$B,$B19,'SG12'!I:I)*SG12_+SUMIF('SG13'!$B:$B,$B19,'SG13'!I:I)*SG13_+SUMIF('SG14'!$B:$B,$B19,'SG14'!I:I)*SG14_+SUMIF('SG15'!$B:$B,$B19,'SG15'!I:I)*SG15_) -> 48 | K19: =(SUMIF('SG01'!$B:$B,$B19,'SG01'!K:K)*SG01_+SUMIF('SG02'!$B:$B,$B19,'SG02'!K:K)*SG02_+SUMIF('SG03'!$B:$B,$B19,'SG03'!K:K)*SG03_+SUMIF('SG04'!$B:$B,$B19,'SG04'!K:K)*SG04_+SUMIF('SG05'!$B:$B,$B19,'SG05'!K:K)*SG05_+SUMIF('SG06'!$B:$B,$B19,'SG06'!K:K)*SG06_+SUMIF('SG07'!$B:$B,$B19,'SG07'!K:K)*SG07_+SUMIF('SG08'!$B:$B,$B19,'SG08'!K:K)*SG08_+SUMIF('SG09'!$B:$B,$B19,'SG09'!K:K)*SG09_+SUMIF('SG10'!$B:$B,$B19,'SG10'!K:K)*SG10_+SUMIF('SG11'!$B:$B,$B19,'SG11'!K:K)*SG11_+SUMIF('SG12'!$B:$B,$B19,'SG12'!K:K)*SG12_+SUMIF('SG13'!$B:$B,$B19,'SG13'!K:K)*SG13_+SUMIF('SG14'!$B:$B,$B19,'SG14'!K:K)*SG14_+SUMIF('SG15'!$B:$B,$B19,'SG15'!K:K)*SG15_) -> 1641718.7 | L19: =(SUMIF('SG01'!$B:$B,$B19,'SG01'!L:L)*SG01_+SUMIF('SG02'!$B:$B,$B19,'SG02'!L:L)*SG02_+SUMIF('SG03'!$B:$B,$B19,'SG03'!L:L)*SG03_+SUMIF('SG04'!$B:$B,$B19,'SG04'!L:L)*SG04_+SUMIF('SG05'!$B:$B,$B19,'SG05'!L:L)*SG05_+SUMIF('SG06'!$B:$B,$B19,'SG06'!L:L)*SG06_+SUMIF('SG07'!$B:$B,$B19,'SG07'!L:L)*SG07_+SUMIF('SG08'!$B:$B,$B19,'SG08'!L:L)*SG08_+SUMIF('SG09'!$B:$B,$B19,'SG09'!L:L)*SG09_+SUMIF('SG10'!$B:$B,$B19,'SG10'!L:L)*SG10_+SUMIF('SG11'!$B:$B,$B19,'SG11'!L:L)*SG11_+SUMIF('SG12'!$B:$B,$B19,'SG12'!L:L)*SG12_+SUMIF('SG13'!$B:$B,$B19,'SG13'!L:L)*SG13_+SUMIF('SG14'!$B:$B,$B19,'SG14'!L:L)*SG14_+SUMIF('SG15'!$B:$B,$B19,'SG15'!L:L)*SG15_) -> 5910000 | M19: =L19-K19 -> 4268281.3 | N19: =K19/L19 -> 0.27778658 | O19: =L19/L$10 -> 0.0038115188 | P19: =M19/M$10 -> 0.0041486098 | Q19: =I19/I$10 -> 0.0029902816 | R19: =I19/$K$5*100 -> 1.2997563 | S19: =R19*T$5 -> 3.8186158 | T19: =IFERROR(S19*G19,0) -> 470167.06 | V19: =IF(B19<>"",IFERROR(IF($I19>=$X$10,"High","Low"),""),"") -> Low | W19: =IF(B19<>"",IFERROR(IF($L19>=$X$12,"High","Low"),""),"") -> High | X19: =IF(B19<>"",IFERROR(IF(AND(V19="high",W19="high"),"Star",IF(AND(V19="low",W19="high"),"Puzzle",(IF(AND(V19="high",W19="low"),"Horse","Dog")))),""),"") -> Puzzle | AB19: CPL.BAR | AC19: CHI PHÍ QUẦY LINE BAR | AD19: =VLOOKUP(AB19,$B:$M,11,0) -> 1350000 | AE19: =AD19/AE$5 -> 365.55646 | AF19: =VLOOKUP(AB19,$B:$R,8,0) -> 1362 | AG19: =AF19/$AE$5*100 -> 36.880585 | AH19: =(SUMIF('SG01'!$AA:$AA,$AB19,'SG01'!AG:AG)*SG01_+SUMIF('SG02'!$AA:$AA,$AB19,'SG02'!AG:AG)*SG02_+SUMIF('SG03'!$AA:$AA,$AB19,'SG03'!AG:AG)*SG03_+SUMIF('SG04'!$AA:$AA,$AB19,'SG04'!AG:AG)*SG04_+SUMIF('SG05'!$AA:$AA,$AB19,'SG05'!AG:AG)*SG05_+SUMIF('SG06'!$AA:$AA,$AB19,'SG06'!AG:AG)*SG06_+SUMIF('SG07'!$AA:$AA,$AB19,'SG07'!AG:AG)*SG07_+SUMIF('SG08'!$AA:$AA,$AB19,'SG08'!AG:AG)*SG08_+SUMIF('SG09'!$AA:$AA,$AB19,'SG09'!AG:AG)*SG09_+SUMIF('SG10'!$AA:$AA,$AB19,'SG10'!AG:AG)*SG10_+SUMIF('SG11'!$AA:$AA,$AB19,'SG11'!AG:AG)*SG11_+SUMIF('SG12'!$AA:$AA,$AB19,'SG12'!AG:AG)*SG12_+SUMIF('SG13'!$AA:$AA,$AB19,'SG13'!AG:AG)*SG13_+SUMIF('SG14'!$AA:$AA,$AB19,'SG14'!AG:AG)*SG14_+SUMIF('SG15'!$AA:$AA,$AB19,'SG15'!AG:AG)*SG15_) -> 1310000 | AI19: =AH19/AI$5 -> 372.05339 | AJ19: =(SUMIF('SG01'!$AA:$AA,$AB19,'SG01'!AI:AI)*SG01_+SUMIF('SG02'!$AA:$AA,$AB19,'SG02'!AI:AI)*SG02_+SUMIF('SG03'!$AA:$AA,$AB19,'SG03'!AI:AI)*SG03_+SUMIF('SG04'!$AA:$AA,$AB19,'SG04'!AI:AI)*SG04_+SUMIF('SG05'!$AA:$AA,$AB19,'SG05'!AI:AI)*SG05_+SUMIF('SG06'!$AA:$AA,$AB19,'SG06'!AI:AI)*SG06_+SUMIF('SG07'!$AA:$AA,$AB19,'SG07'!AI:AI)*SG07_+SUMIF('SG08'!$AA:$AA,$AB19,'SG08'!AI:AI)*SG08_+SUMIF('SG09'!$AA:$AA,$AB19,'SG09'!AI:AI)*SG09_+SUMIF('SG10'!$AA:$AA,$AB19,'SG10'!AI:AI)*SG10_+SUMIF('SG11'!$AA:$AA,$AB19,'SG11'!AI:AI)*SG11_+SUMIF('SG12'!$AA:$AA,$AB19,'SG12'!AI:AI)*SG12_+SUMIF('SG13'!$AA:$AA,$AB19,'SG13'!AI:AI)*SG13_+SUMIF('SG14'!$AA:$AA,$AB19,'SG14'!AI:AI)*SG14_+SUMIF('SG15'!$AA:$AA,$AB19,'SG15'!AI:AI)*SG15_) -> 1293 | AK19: =AJ19/$AI$5*100 -> 36.722522 | AL19: =AE19-AI19 -> -6.4969358 | AM19: =AG19-AK19 -> 0.15806288
A20: 3 | B20: GSKVI006 | C20: =VLOOKUP(B20,'SG02'!$B:$E,2,0) -> Rau Salad Rong Biển | E20: =VLOOKUP(B20,'SG01'!$B:$E,4,0) -> Phần | F20: =K20/I20 -> 27302.912 | G20: =L20/I20 -> 81421.053 | H20: =G20-F20 -> 54118.141 | I20: =(SUMIF('SG01'!$B:$B,$B20,'SG01'!I:I)*SG01_+SUMIF('SG02'!$B:$B,$B20,'SG02'!I:I)*SG02_+SUMIF('SG03'!$B:$B,$B20,'SG03'!I:I)*SG03_+SUMIF('SG04'!$B:$B,$B20,'SG04'!I:I)*SG04_+SUMIF('SG05'!$B:$B,$B20,'SG05'!I:I)*SG05_+SUMIF('SG06'!$B:$B,$B20,'SG06'!I:I)*SG06_+SUMIF('SG07'!$B:$B,$B20,'SG07'!I:I)*SG07_+SUMIF('SG08'!$B:$B,$B20,'SG08'!I:I)*SG08_+SUMIF('SG09'!$B:$B,$B20,'SG09'!I:I)*SG09_+SUMIF('SG10'!$B:$B,$B20,'SG10'!I:I)*SG10_+SUMIF('SG11'!$B:$B,$B20,'SG11'!I:I)*SG11_+SUMIF('SG12'!$B:$B,$B20,'SG12'!I:I)*SG12_+SUMIF('SG13'!$B:$B,$B20,'SG13'!I:I)*SG13_+SUMIF('SG14'!$B:$B,$B20,'SG14'!I:I)*SG14_+SUMIF('SG15'!$B:$B,$B20,'SG15'!I:I)*SG15_) -> 38 | K20: =(SUMIF('SG01'!$B:$B,$B20,'SG01'!K:K)*SG01_+SUMIF('SG02'!$B:$B,$B20,'SG02'!K:K)*SG02_+SUMIF('SG03'!$B:$B,$B20,'SG03'!K:K)*SG03_+SUMIF('SG04'!$B:$B,$B20,'SG04'!K:K)*SG04_+SUMIF('SG05'!$B:$B,$B20,'SG05'!K:K)*SG05_+SUMIF('SG06'!$B:$B,$B20,'SG06'!K:K)*SG06_+SUMIF('SG07'!$B:$B,$B20,'SG07'!K:K)*SG07_+SUMIF('SG08'!$B:$B,$B20,'SG08'!K:K)*SG08_+SUMIF('SG09'!$B:$B,$B20,'SG09'!K:K)*SG09_+SUMIF('SG10'!$B:$B,$B20,'SG10'!K:K)*SG10_+SUMIF('SG11'!$B:$B,$B20,'SG11'!K:K)*SG11_+SUMIF('SG12'!$B:$B,$B20,'SG12'!K:K)*SG12_+SUMIF('SG13'!$B:$B,$B20,'SG13'!K:K)*SG13_+SUMIF('SG14'!$B:$B,$B20,'SG14'!K:K)*SG14_+SUMIF('SG15'!$B:$B,$B20,'SG15'!K:K)*SG15_) -> 1037510.6 | L20: =(SUMIF('SG01'!$B:$B,$B20,'SG01'!L:L)*SG01_+SUMIF('SG02'!$B:$B,$B20,'SG02'!L:L)*SG02_+SUMIF('SG03'!$B:$B,$B20,'SG03'!L:L)*SG03_+SUMIF('SG04'!$B:$B,$B20,'SG04'!L:L)*SG04_+SUMIF('SG05'!$B:$B,$B20,'SG05'!L:L)*SG05_+SUMIF('SG06'!$B:$B,$B20,'SG06'!L:L)*SG06_+SUMIF('SG07'!$B:$B,$B20,'SG07'!L:L)*SG07_+SUMIF('SG08'!$B:$B,$B20,'SG08'!L:L)*SG08_+SUMIF('SG09'!$B:$B,$B20,'SG09'!L:L)*SG09_+SUMIF('SG10'!$B:$B,$B20,'SG10'!L:L)*SG10_+SUMIF('SG11'!$B:$B,$B20,'SG11'!L:L)*SG11_+SUMIF('SG12'!$B:$B,$B20,'SG12'!L:L)*SG12_+SUMIF('SG13'!$B:$B,$B20,'SG13'!L:L)*SG13_+SUMIF('SG14'!$B:$B,$B20,'SG14'!L:L)*SG14_+SUMIF('SG15'!$B:$B,$B20,'SG15'!L:L)*SG15_) -> 3094000 | M20: =L20-K20 -> 2056489.4 | N20: =K20/L20 -> 0.33532988 | O20: =L20/L$10 -> 0.0019954042 | P20: =M20/M$10 -> 0.0019988308 | Q20: =I20/I$10 -> 0.0023673063 | R20: =I20/$K$5*100 -> 1.0289737 | S20: =R20*T$5 -> 3.0230708 | T20: =IFERROR(S20*G20,0) -> 246141.61 | V20: =IF(B20<>"",IFERROR(IF($I20>=$X$10,"High","Low"),""),"") -> Low | W20: =IF(B20<>"",IFERROR(IF($L20>=$X$12,"High","Low"),""),"") -> High | X20: =IF(B20<>"",IFERROR(IF(AND(V20="high",W20="high"),"Star",IF(AND(V20="low",W20="high"),"Puzzle",(IF(AND(V20="high",W20="low"),"Horse","Dog")))),""),"") -> Puzzle | AB20: DVU.GSG | AC20: DỊCH VỤ/SERVICE | AD20: =VLOOKUP(AB20,$B:$M,11,0) -> 9489000 | AE20: =AD20/AE$5 -> 2569.4557 | AF20: =VLOOKUP(AB20,$B:$R,8,0) -> 3163 | AG20: =AF20/$AE$5*100 -> 85.648524 | AH20: =(SUMIF('SG01'!$AA:$AA,$AB20,'SG01'!AG:AG)*SG01_+SUMIF('SG02'!$AA:$AA,$AB20,'SG02'!AG:AG)*SG02_+SUMIF('SG03'!$AA:$AA,$AB20,'SG03'!AG:AG)*SG03_+SUMIF('SG04'!$AA:$AA,$AB20,'SG04'!AG:AG)*SG04_+SUMIF('SG05'!$AA:$AA,$AB20,'SG05'!AG:AG)*SG05_+SUMIF('SG06'!$AA:$AA,$AB20,'SG06'!AG:AG)*SG06_+SUMIF('SG07'!$AA:$AA,$AB20,'SG07'!AG:AG)*SG07_+SUMIF('SG08'!$AA:$AA,$AB20,'SG08'!AG:AG)*SG08_+SUMIF('SG09'!$AA:$AA,$AB20,'SG09'!AG:AG)*SG09_+SUMIF('SG10'!$AA:$AA,$AB20,'SG10'!AG:AG)*SG10_+SUMIF('SG11'!$AA:$AA,$AB20,'SG11'!AG:AG)*SG11_+SUMIF('SG12'!$AA:$AA,$AB20,'SG12'!AG:AG)*SG12_+SUMIF('SG13'!$AA:$AA,$AB20,'SG13'!AG:AG)*SG13_+SUMIF('SG14'!$AA:$AA,$AB20,'SG14'!AG:AG)*SG14_+SUMIF('SG15'!$AA:$AA,$AB20,'SG15'!AG:AG)*SG15_) -> 9081000 | AI20: =AH20/AI$5 -> 2579.0968 | AJ20: =(SUMIF('SG01'!$AA:$AA,$AB20,'SG01'!AI:AI)*SG01_+SUMIF('SG02'!$AA:$AA,$AB20,'SG02'!AI:AI)*SG02_+SUMIF('SG03'!$AA:$AA,$AB20,'SG03'!AI:AI)*SG03_+SUMIF('SG04'!$AA:$AA,$AB20,'SG04'!AI:AI)*SG04_+SUMIF('SG05'!$AA:$AA,$AB20,'SG05'!AI:AI)*SG05_+SUMIF('SG06'!$AA:$AA,$AB20,'SG06'!AI:AI)*SG06_+SUMIF('SG07'!$AA:$AA,$AB20,'SG07'!AI:AI)*SG07_+SUMIF('SG08'!$AA:$AA,$AB20,'SG08'!AI:AI)*SG08_+SUMIF('SG09'!$AA:$AA,$AB20,'SG09'!AI:AI)*SG09_+SUMIF('SG10'!$AA:$AA,$AB20,'SG10'!AI:AI)*SG10_+SUMIF('SG11'!$AA:$AA,$AB20,'SG11'!AI:AI)*SG11_+SUMIF('SG12'!$AA:$AA,$AB20,'SG12'!AI:AI)*SG12_+SUMIF('SG13'!$AA:$AA,$AB20,'SG13'!AI:AI)*SG13_+SUMIF('SG14'!$AA:$AA,$AB20,'SG14'!AI:AI)*SG14_+SUMIF('SG15'!$AA:$AA,$AB20,'SG15'!AI:AI)*SG15_) -> 3027 | AK20: =AJ20/$AI$5*100 -> 85.969895 | AL20: =AE20-AI20 -> -9.6411204 | AM20: =AG20-AK20 -> -0.32137068
A21: =+A20+1 -> 4 | B21: GSKVI007 | C21: =VLOOKUP(B21,'SG02'!$B:$E,2,0) -> Rau Salad Bơ Xốt Mè Rang | E21: =VLOOKUP(B21,'SG01'!$B:$E,4,0) -> Phần | F21: =K21/I21 -> 20205.796 | G21: =L21/I21 -> 81594.937 | H21: =G21-F21 -> 61389.14 | I21: =(SUMIF('SG01'!$B:$B,$B21,'SG01'!I:I)*SG01_+SUMIF('SG02'!$B:$B,$B21,'SG02'!I:I)*SG02_+SUMIF('SG03'!$B:$B,$B21,'SG03'!I:I)*SG03_+SUMIF('SG04'!$B:$B,$B21,'SG04'!I:I)*SG04_+SUMIF('SG05'!$B:$B,$B21,'SG05'!I:I)*SG05_+SUMIF('SG06'!$B:$B,$B21,'SG06'!I:I)*SG06_+SUMIF('SG07'!$B:$B,$B21,'SG07'!I:I)*SG07_+SUMIF('SG08'!$B:$B,$B21,'SG08'!I:I)*SG08_+SUMIF('SG09'!$B:$B,$B21,'SG09'!I:I)*SG09_+SUMIF('SG10'!$B:$B,$B21,'SG10'!I:I)*SG10_+SUMIF('SG11'!$B:$B,$B21,'SG11'!I:I)*SG11_+SUMIF('SG12'!$B:$B,$B21,'SG12'!I:I)*SG12_+SUMIF('SG13'!$B:$B,$B21,'SG13'!I:I)*SG13_+SUMIF('SG14'!$B:$B,$B21,'SG14'!I:I)*SG14_+SUMIF('SG15'!$B:$B,$B21,'SG15'!I:I)*SG15_) -> 79 | K21: =(SUMIF('SG01'!$B:$B,$B21,'SG01'!K:K)*SG01_+SUMIF('SG02'!$B:$B,$B21,'SG02'!K:K)*SG02_+SUMIF('SG03'!$B:$B,$B21,'SG03'!K:K)*SG03_+SUMIF('SG04'!$B:$B,$B21,'SG04'!K:K)*SG04_+SUMIF('SG05'!$B:$B,$B21,'SG05'!K:K)*SG05_+SUMIF('SG06'!$B:$B,$B21,'SG06'!K:K)*SG06_+SUMIF('SG07'!$B:$B,$B21,'SG07'!K:K)*SG07_+SUMIF('SG08'!$B:$B,$B21,'SG08'!K:K)*SG08_+SUMIF('SG09'!$B:$B,$B21,'SG09'!K:K)*SG09_+SUMIF('SG10'!$B:$B,$B21,'SG10'!K:K)*SG10_+SUMIF('SG11'!$B:$B,$B21,'SG11'!K:K)*SG11_+SUMIF('SG12'!$B:$B,$B21,'SG12'!K:K)*SG12_+SUMIF('SG13'!$B:$B,$B21,'SG13'!K:K)*SG13_+SUMIF('SG14'!$B:$B,$B21,'SG14'!K:K)*SG14_+SUMIF('SG15'!$B:$B,$B21,'SG15'!K:K)*SG15_) -> 1596257.9 | L21: =(SUMIF('SG01'!$B:$B,$B21,'SG01'!L:L)*SG01_+SUMIF('SG02'!$B:$B,$B21,'SG02'!L:L)*SG02_+SUMIF('SG03'!$B:$B,$B21,'SG03'!L:L)*SG03_+SUMIF('SG04'!$B:$B,$B21,'SG04'!L:L)*SG04_+SUMIF('SG05'!$B:$B,$B21,'SG05'!L:L)*SG05_+SUMIF('SG06'!$B:$B,$B21,'SG06'!L:L)*SG06_+SUMIF('SG07'!$B:$B,$B21,'SG07'!L:L)*SG07_+SUMIF('SG08'!$B:$B,$B21,'SG08'!L:L)*SG08_+SUMIF('SG09'!$B:$B,$B21,'SG09'!L:L)*SG09_+SUMIF('SG10'!$B:$B,$B21,'SG10'!L:L)*SG10_+SUMIF('SG11'!$B:$B,$B21,'SG11'!L:L)*SG11_+SUMIF('SG12'!$B:$B,$B21,'SG12'!L:L)*SG12_+SUMIF('SG13'!$B:$B,$B21,'SG13'!L:L)*SG13_+SUMIF('SG14'!$B:$B,$B21,'SG14'!L:L)*SG14_+SUMIF('SG15'!$B:$B,$B21,'SG15'!L:L)*SG15_) -> 6446000 | M21: =L21-K21 -> 4849742.1 | N21: =K21/L21 -> 0.24763542 | O21: =L21/L$10 -> 0.0041571997 | P21: =M21/M$10 -> 0.004713768 | Q21: =I21/I$10 -> 0.0049215051 | R21: =I21/$K$5*100 -> 2.1391822 | S21: =R21*T$5 -> 6.2848051 | T21: =IFERROR(S21*G21,0) -> 512808.27 | V21: =IF(B21<>"",IFERROR(IF($I21>=$X$10,"High","Low"),""),"") -> Low | W21: =IF(B21<>"",IFERROR(IF($L21>=$X$12,"High","Low"),""),"") -> High | X21: =IF(B21<>"",IFERROR(IF(AND(V21="high",W21="high"),"Star",IF(AND(V21="low",W21="high"),"Puzzle",(IF(AND(V21="high",W21="low"),"Horse","Dog")))),""),"") -> Puzzle
A22: =+A21+1 -> 5 | B22: GSKVI008 | C22: =VLOOKUP(B22,'SG02'!$B:$E,2,0) -> Rau Củ Muối Chua Ngọt | E22: =VLOOKUP(B22,'SG01'!$B:$E,4,0) -> Phần | F22: =K22/I22 -> 7147.2 | G22: =L22/I22 -> 51666.667 | H22: =G22-F22 -> 44519.467 | I22: =(SUMIF('SG01'!$B:$B,$B22,'SG01'!I:I)*SG01_+SUMIF('SG02'!$B:$B,$B22,'SG02'!I:I)*SG02_+SUMIF('SG03'!$B:$B,$B22,'SG03'!I:I)*SG03_+SUMIF('SG04'!$B:$B,$B22,'SG04'!I:I)*SG04_+SUMIF('SG05'!$B:$B,$B22,'SG05'!I:I)*SG05_+SUMIF('SG06'!$B:$B,$B22,'SG06'!I:I)*SG06_+SUMIF('SG07'!$B:$B,$B22,'SG07'!I:I)*SG07_+SUMIF('SG08'!$B:$B,$B22,'SG08'!I:I)*SG08_+SUMIF('SG09'!$B:$B,$B22,'SG09'!I:I)*SG09_+SUMIF('SG10'!$B:$B,$B22,'SG10'!I:I)*SG10_+SUMIF('SG11'!$B:$B,$B22,'SG11'!I:I)*SG11_+SUMIF('SG12'!$B:$B,$B22,'SG12'!I:I)*SG12_+SUMIF('SG13'!$B:$B,$B22,'SG13'!I:I)*SG13_+SUMIF('SG14'!$B:$B,$B22,'SG14'!I:I)*SG14_+SUMIF('SG15'!$B:$B,$B22,'SG15'!I:I)*SG15_) -> 12 | K22: =(SUMIF('SG01'!$B:$B,$B22,'SG01'!K:K)*SG01_+SUMIF('SG02'!$B:$B,$B22,'SG02'!K:K)*SG02_+SUMIF('SG03'!$B:$B,$B22,'SG03'!K:K)*SG03_+SUMIF('SG04'!$B:$B,$B22,'SG04'!K:K)*SG04_+SUMIF('SG05'!$B:$B,$B22,'SG05'!K:K)*SG05_+SUMIF('SG06'!$B:$B,$B22,'SG06'!K:K)*SG06_+SUMIF('SG07'!$B:$B,$B22,'SG07'!K:K)*SG07_+SUMIF('SG08'!$B:$B,$B22,'SG08'!K:K)*SG08_+SUMIF('SG09'!$B:$B,$B22,'SG09'!K:K)*SG09_+SUMIF('SG10'!$B:$B,$B22,'SG10'!K:K)*SG10_+SUMIF('SG11'!$B:$B,$B22,'SG11'!K:K)*SG11_+SUMIF('SG12'!$B:$B,$B22,'SG12'!K:K)*SG12_+SUMIF('SG13'!$B:$B,$B22,'SG13'!K:K)*SG13_+SUMIF('SG14'!$B:$B,$B22,'SG14'!K:K)*SG14_+SUMIF('SG15'!$B:$B,$B22,'SG15'!K:K)*SG15_) -> 85766.4 | L22: =(SUMIF('SG01'!$B:$B,$B22,'SG01'!L:L)*SG01_+SUMIF('SG02'!$B:$B,$B22,'SG02'!L:L)*SG02_+SUMIF('SG03'!$B:$B,$B22,'SG03'!L:L)*SG03_+SUMIF('SG04'!$B:$B,$B22,'SG04'!L:L)*SG04_+SUMIF('SG05'!$B:$B,$B22,'SG05'!L:L)*SG05_+SUMIF('SG06'!$B:$B,$B22,'SG06'!L:L)*SG06_+SUMIF('SG07'!$B:$B,$B22,'SG07'!L:L)*SG07_+SUMIF('SG08'!$B:$B,$B22,'SG08'!L:L)*SG08_+SUMIF('SG09'!$B:$B,$B22,'SG09'!L:L)*SG09_+SUMIF('SG10'!$B:$B,$B22,'SG10'!L:L)*SG10_+SUMIF('SG11'!$B:$B,$B22,'SG11'!L:L)*SG11_+SUMIF('SG12'!$B:$B,$B22,'SG12'!L:L)*SG12_+SUMIF('SG13'!$B:$B,$B22,'SG13'!L:L)*SG13_+SUMIF('SG14'!$B:$B,$B22,'SG14'!L:L)*SG14_+SUMIF('SG15'!$B:$B,$B22,'SG15'!L:L)*SG15_) -> 620000 | M22: =L22-K22 -> 534233.6 | N22: =K22/L22 -> 0.1383329 | O22: =L22/L$10 -> 0.00039985476 | P22: =M22/M$10 -> 0.00051925509 | Q22: =I22/I$10 -> 0.0007475704 | R22: =I22/$K$5*100 -> 0.32493907 | S22: =R22*T$5 -> 0.95465394 | T22: =IFERROR(S22*G22,0) -> 49323.787 | V22: =IF(B22<>"",IFERROR(IF($I22>=$X$10,"High","Low"),""),"") -> Low | W22: =IF(B22<>"",IFERROR(IF($L22>=$X$12,"High","Low"),""),"") -> Low | X22: =IF(B22<>"",IFERROR(IF(AND(V22="high",W22="high"),"Star",IF(AND(V22="low",W22="high"),"Puzzle",(IF(AND(V22="high",W22="low"),"Horse","Dog")))),""),"") -> Dog
A23: =+A22+1 -> 6 | B23: GSKVI009 | C23: =VLOOKUP(B23,'SG02'!$B:$E,2,0) -> Bạch Quả | E23: =VLOOKUP(B23,'SG01'!$B:$E,4,0) -> Phần | F23: =K23/I23 -> 11788 | G23: =L23/I23 -> 39000 | H23: =G23-F23 -> 27212 | I23: =(SUMIF('SG01'!$B:$B,$B23,'SG01'!I:I)*SG01_+SUMIF('SG02'!$B:$B,$B23,'SG02'!I:I)*SG02_+SUMIF('SG03'!$B:$B,$B23,'SG03'!I:I)*SG03_+SUMIF('SG04'!$B:$B,$B23,'SG04'!I:I)*SG04_+SUMIF('SG05'!$B:$B,$B23,'SG05'!I:I)*SG05_+SUMIF('SG06'!$B:$B,$B23,'SG06'!I:I)*SG06_+SUMIF('SG07'!$B:$B,$B23,'SG07'!I:I)*SG07_+SUMIF('SG08'!$B:$B,$B23,'SG08'!I:I)*SG08_+SUMIF('SG09'!$B:$B,$B23,'SG09'!I:I)*SG09_+SUMIF('SG10'!$B:$B,$B23,'SG10'!I:I)*SG10_+SUMIF('SG11'!$B:$B,$B23,'SG11'!I:I)*SG11_+SUMIF('SG12'!$B:$B,$B23,'SG12'!I:I)*SG12_+SUMIF('SG13'!$B:$B,$B23,'SG13'!I:I)*SG13_+SUMIF('SG14'!$B:$B,$B23,'SG14'!I:I)*SG14_+SUMIF('SG15'!$B:$B,$B23,'SG15'!I:I)*SG15_) -> 22 | K23: =(SUMIF('SG01'!$B:$B,$B23,'SG01'!K:K)*SG01_+SUMIF('SG02'!$B:$B,$B23,'SG02'!K:K)*SG02_+SUMIF('SG03'!$B:$B,$B23,'SG03'!K:K)*SG03_+SUMIF('SG04'!$B:$B,$B23,'SG04'!K:K)*SG04_+SUMIF('SG05'!$B:$B,$B23,'SG05'!K:K)*SG05_+SUMIF('SG06'!$B:$B,$B23,'SG06'!K:K)*SG06_+SUMIF('SG07'!$B:$B,$B23,'SG07'!K:K)*SG07_+SUMIF('SG08'!$B:$B,$B23,'SG08'!K:K)*SG08_+SUMIF('SG09'!$B:$B,$B23,'SG09'!K:K)*SG09_+SUMIF('SG10'!$B:$B,$B23,'SG10'!K:K)*SG10_+SUMIF('SG11'!$B:$B,$B23,'SG11'!K:K)*SG11_+SUMIF('SG12'!$B:$B,$B23,'SG12'!K:K)*SG12_+SUMIF('SG13'!$B:$B,$B23,'SG13'!K:K)*SG13_+SUMIF('SG14'!$B:$B,$B23,'SG14'!K:K)*SG14_+SUMIF('SG15'!$B:$B,$B23,'SG15'!K:K)*SG15_) -> 259336 | L23: =(SUMIF('SG01'!$B:$B,$B23,'SG01'!L:L)*SG01_+SUMIF('SG02'!$B:$B,$B23,'SG02'!L:L)*SG02_+SUMIF('SG03'!$B:$B,$B23,'SG03'!L:L)*SG03_+SUMIF('SG04'!$B:$B,$B23,'SG04'!L:L)*SG04_+SUMIF('SG05'!$B:$B,$B23,'SG05'!L:L)*SG05_+SUMIF('SG06'!$B:$B,$B23,'SG06'!L:L)*SG06_+SUMIF('SG07'!$B:$B,$B23,'SG07'!L:L)*SG07_+SUMIF('SG08'!$B:$B,$B23,'SG08'!L:L)*SG08_+SUMIF('SG09'!$B:$B,$B23,'SG09'!L:L)*SG09_+SUMIF('SG10'!$B:$B,$B23,'SG10'!L:L)*SG10_+SUMIF('SG11'!$B:$B,$B23,'SG11'!L:L)*SG11_+SUMIF('SG12'!$B:$B,$B23,'SG12'!L:L)*SG12_+SUMIF('SG13'!$B:$B,$B23,'SG13'!L:L)*SG13_+SUMIF('SG14'!$B:$B,$B23,'SG14'!L:L)*SG14_+SUMIF('SG15'!$B:$B,$B23,'SG15'!L:L)*SG15_) -> 858000 | M23: =L23-K23 -> 598664 | N23: =K23/L23 -> 0.30225641 | O23: =L23/L$10 -> 0.0005533474 | P23: =M23/M$10 -> 0.00058187903 | Q23: =I23/I$10 -> 0.0013705457 | R23: =I23/$K$5*100 -> 0.59572164 | S23: =R23*T$5 -> 1.7501989 | T23: =IFERROR(S23*G23,0) -> 68257.757 | V23: =IF(B23<>"",IFERROR(IF($I23>=$X$10,"High","Low"),""),"") -> Low | W23: =IF(B23<>"",IFERROR(IF($L23>=$X$12,"High","Low"),""),"") -> Low | X23: =IF(B23<>"",IFERROR(IF(AND(V23="high",W23="high"),"Star",IF(AND(V23="low",W23="high"),"Puzzle",(IF(AND(V23="high",W23="low"),"Horse","Dog")))),""),"") -> Dog
A24: =+A23+1 -> 7 | B24: GSKVI010 | C24: =VLOOKUP(B24,'SG02'!$B:$E,2,0) -> Đậu Nành Nhật | E24: =VLOOKUP(B24,'SG01'!$B:$E,4,0) -> Phần | F24: =K24/I24 -> 13625.134 | G24: =L24/I24 -> 50694.444 | H24: =G24-F24 -> 37069.31 | I24: =(SUMIF('SG01'!$B:$B,$B24,'SG01'!I:I)*SG01_+SUMIF('SG02'!$B:$B,$B24,'SG02'!I:I)*SG02_+SUMIF('SG03'!$B:$B,$B24,'SG03'!I:I)*SG03_+SUMIF('SG04'!$B:$B,$B24,'SG04'!I:I)*SG04_+SUMIF('SG05'!$B:$B,$B24,'SG05'!I:I)*SG05_+SUMIF('SG06'!$B:$B,$B24,'SG06'!I:I)*SG06_+SUMIF('SG07'!$B:$B,$B24,'SG07'!I:I)*SG07_+SUMIF('SG08'!$B:$B,$B24,'SG08'!I:I)*SG08_+SUMIF('SG09'!$B:$B,$B24,'SG09'!I:I)*SG09_+SUMIF('SG10'!$B:$B,$B24,'SG10'!I:I)*SG10_+SUMIF('SG11'!$B:$B,$B24,'SG11'!I:I)*SG11_+SUMIF('SG12'!$B:$B,$B24,'SG12'!I:I)*SG12_+SUMIF('SG13'!$B:$B,$B24,'SG13'!I:I)*SG13_+SUMIF('SG14'!$B:$B,$B24,'SG14'!I:I)*SG14_+SUMIF('SG15'!$B:$B,$B24,'SG15'!I:I)*SG15_) -> 72 | K24: =(SUMIF('SG01'!$B:$B,$B24,'SG01'!K:K)*SG01_+SUMIF('SG02'!$B:$B,$B24,'SG02'!K:K)*SG02_+SUMIF('SG03'!$B:$B,$B24,'SG03'!K:K)*SG03_+SUMIF('SG04'!$B:$B,$B24,'SG04'!K:K)*SG04_+SUMIF('SG05'!$B:$B,$B24,'SG05'!K:K)*SG05_+SUMIF('SG06'!$B:$B,$B24,'SG06'!K:K)*SG06_+SUMIF('SG07'!$B:$B,$B24,'SG07'!K:K)*SG07_+SUMIF('SG08'!$B:$B,$B24,'SG08'!K:K)*SG08_+SUMIF('SG09'!$B:$B,$B24,'SG09'!K:K)*SG09_+SUMIF('SG10'!$B:$B,$B24,'SG10'!K:K)*SG10_+SUMIF('SG11'!$B:$B,$B24,'SG11'!K:K)*SG11_+SUMIF('SG12'!$B:$B,$B24,'SG12'!K:K)*SG12_+SUMIF('SG13'!$B:$B,$B24,'SG13'!K:K)*SG13_+SUMIF('SG14'!$B:$B,$B24,'SG14'!K:K)*SG14_+SUMIF('SG15'!$B:$B,$B24,'SG15'!K:K)*SG15_) -> 981009.66 | L24: =(SUMIF('SG01'!$B:$B,$B24,'SG01'!L:L)*SG01_+SUMIF('SG02'!$B:$B,$B24,'SG02'!L:L)*SG02_+SUMIF('SG03'!$B:$B,$B24,'SG03'!L:L)*SG03_+SUMIF('SG04'!$B:$B,$B24,'SG04'!L:L)*SG04_+SUMIF('SG05'!$B:$B,$B24,'SG05'!L:L)*SG05_+SUMIF('SG06'!$B:$B,$B24,'SG06'!L:L)*SG06_+SUMIF('SG07'!$B:$B,$B24,'SG07'!L:L)*SG07_+SUMIF('SG08'!$B:$B,$B24,'SG08'!L:L)*SG08_+SUMIF('SG09'!$B:$B,$B24,'SG09'!L:L)*SG09_+SUMIF('SG10'!$B:$B,$B24,'SG10'!L:L)*SG10_+SUMIF('SG11'!$B:$B,$B24,'SG11'!L:L)*SG11_+SUMIF('SG12'!$B:$B,$B24,'SG12'!L:L)*SG12_+SUMIF('SG13'!$B:$B,$B24,'SG13'!L:L)*SG13_+SUMIF('SG14'!$B:$B,$B24,'SG14'!L:L)*SG14_+SUMIF('SG15'!$B:$B,$B24,'SG15'!L:L)*SG15_) -> 3650000 | M24: =L24-K24 -> 2668990.3 | N24: =K24/L24 -> 0.26876977 | O24: =L24/L$10 -> 0.0023539837 | P24: =M24/M$10 -> 0.0025941588 | Q24: =I24/I$10 -> 0.0044854224 | R24: =I24/$K$5*100 -> 1.9496344 | S24: =R24*T$5 -> 5.7279236 | T24: =IFERROR(S24*G24,0) -> 290373.91 | V24: =IF(B24<>"",IFERROR(IF($I24>=$X$10,"High","Low"),""),"") -> Low | W24: =IF(B24<>"",IFERROR(IF($L24>=$X$12,"High","Low"),""),"") -> High | X24: =IF(B24<>"",IFERROR(IF(AND(V24="high",W24="high"),"Star",IF(AND(V24="low",W24="high"),"Puzzle",(IF(AND(V24="high",W24="low"),"Horse","Dog")))),""),"") -> Puzzle
A25: =+A24+1 -> 8 | B25: GSKVI011 | C25: =VLOOKUP(B25,'SG02'!$B:$E,2,0) -> Bò Tái Xốt Ponzu | E25: =VLOOKUP(B25,'SG01'!$B:$E,4,0) -> Phần | F25: =K25/I25 -> #DIV/0! | G25: =L25/I25 -> #DIV/0! | H25: =G25-F25 -> #DIV/0! | I25: =(SUMIF('SG01'!$B:$B,$B25,'SG01'!I:I)*SG01_+SUMIF('SG02'!$B:$B,$B25,'SG02'!I:I)*SG02_+SUMIF('SG03'!$B:$B,$B25,'SG03'!I:I)*SG03_+SUMIF('SG04'!$B:$B,$B25,'SG04'!I:I)*SG04_+SUMIF('SG05'!$B:$B,$B25,'SG05'!I:I)*SG05_+SUMIF('SG06'!$B:$B,$B25,'SG06'!I:I)*SG06_+SUMIF('SG07'!$B:$B,$B25,'SG07'!I:I)*SG07_+SUMIF('SG08'!$B:$B,$B25,'SG08'!I:I)*SG08_+SUMIF('SG09'!$B:$B,$B25,'SG09'!I:I)*SG09_+SUMIF('SG10'!$B:$B,$B25,'SG10'!I:I)*SG10_+SUMIF('SG11'!$B:$B,$B25,'SG11'!I:I)*SG11_+SUMIF('SG12'!$B:$B,$B25,'SG12'!I:I)*SG12_+SUMIF('SG13'!$B:$B,$B25,'SG13'!I:I)*SG13_+SUMIF('SG14'!$B:$B,$B25,'SG14'!I:I)*SG14_+SUMIF('SG15'!$B:$B,$B25,'SG15'!I:I)*SG15_) -> 0 | K25: =(SUMIF('SG01'!$B:$B,$B25,'SG01'!K:K)*SG01_+SUMIF('SG02'!$B:$B,$B25,'SG02'!K:K)*SG02_+SUMIF('SG03'!$B:$B,$B25,'SG03'!K:K)*SG03_+SUMIF('SG04'!$B:$B,$B25,'SG04'!K:K)*SG04_+SUMIF('SG05'!$B:$B,$B25,'SG05'!K:K)*SG05_+SUMIF('SG06'!$B:$B,$B25,'SG06'!K:K)*SG06_+SUMIF('SG07'!$B:$B,$B25,'SG07'!K:K)*SG07_+SUMIF('SG08'!$B:$B,$B25,'SG08'!K:K)*SG08_+SUMIF('SG09'!$B:$B,$B25,'SG09'!K:K)*SG09_+SUMIF('SG10'!$B:$B,$B25,'SG10'!K:K)*SG10_+SUMIF('SG11'!$B:$B,$B25,'SG11'!K:K)*SG11_+SUMIF('SG12'!$B:$B,$B25,'SG12'!K:K)*SG12_+SUMIF('SG13'!$B:$B,$B25,'SG13'!K:K)*SG13_+SUMIF('SG14'!$B:$B,$B25,'SG14'!K:K)*SG14_+SUMIF('SG15'!$B:$B,$B25,'SG15'!K:K)*SG15_) -> 0 | L25: =(SUMIF('SG01'!$B:$B,$B25,'SG01'!L:L)*SG01_+SUMIF('SG02'!$B:$B,$B25,'SG02'!L:L)*SG02_+SUMIF('SG03'!$B:$B,$B25,'SG03'!L:L)*SG03_+SUMIF('SG04'!$B:$B,$B25,'SG04'!L:L)*SG04_+SUMIF('SG05'!$B:$B,$B25,'SG05'!L:L)*SG05_+SUMIF('SG06'!$B:$B,$B25,'SG06'!L:L)*SG06_+SUMIF('SG07'!$B:$B,$B25,'SG07'!L:L)*SG07_+SUMIF('SG08'!$B:$B,$B25,'SG08'!L:L)*SG08_+SUMIF('SG09'!$B:$B,$B25,'SG09'!L:L)*SG09_+SUMIF('SG10'!$B:$B,$B25,'SG10'!L:L)*SG10_+SUMIF('SG11'!$B:$B,$B25,'SG11'!L:L)*SG11_+SUMIF('SG12'!$B:$B,$B25,'SG12'!L:L)*SG12_+SUMIF('SG13'!$B:$B,$B25,'SG13'!L:L)*SG13_+SUMIF('SG14'!$B:$B,$B25,'SG14'!L:L)*SG14_+SUMIF('SG15'!$B:$B,$B25,'SG15'!L:L)*SG15_) -> 0 | M25: =L25-K25 -> 0 | N25: =K25/L25 -> #DIV/0! | O25: =L25/L$10 -> 0 | P25: =M25/M$10 -> 0 | Q25: =I25/I$10 -> 0 | R25: =I25/$K$5*100 -> 0 | S25: =R25*T$5 -> 0 | T25: =IFERROR(S25*G25,0) -> 0 | V25: =IF(B25<>"",IFERROR(IF($I25>=$X$10,"High","Low"),""),"") -> Low | W25: =IF(B25<>"",IFERROR(IF($L25>=$X$12,"High","Low"),""),"") -> Low | X25: =IF(B25<>"",IFERROR(IF(AND(V25="high",W25="high"),"Star",IF(AND(V25="low",W25="high"),"Puzzle",(IF(AND(V25="high",W25="low"),"Horse","Dog")))),""),"") -> Dog
A26: =+A25+1 -> 9 | B26: GSKVI012 | C26: =VLOOKUP(B26,'SG02'!$B:$E,2,0) -> Khoai Lang Chiên Rong Biển | E26: =VLOOKUP(B26,'SG01'!$B:$E,4,0) -> Phần | F26: =K26/I26 -> 17475.019 | G26: =L26/I26 -> 70833.333 | H26: =G26-F26 -> 53358.314 | I26: =(SUMIF('SG01'!$B:$B,$B26,'SG01'!I:I)*SG01_+SUMIF('SG02'!$B:$B,$B26,'SG02'!I:I)*SG02_+SUMIF('SG03'!$B:$B,$B26,'SG03'!I:I)*SG03_+SUMIF('SG04'!$B:$B,$B26,'SG04'!I:I)*SG04_+SUMIF('SG05'!$B:$B,$B26,'SG05'!I:I)*SG05_+SUMIF('SG06'!$B:$B,$B26,'SG06'!I:I)*SG06_+SUMIF('SG07'!$B:$B,$B26,'SG07'!I:I)*SG07_+SUMIF('SG08'!$B:$B,$B26,'SG08'!I:I)*SG08_+SUMIF('SG09'!$B:$B,$B26,'SG09'!I:I)*SG09_+SUMIF('SG10'!$B:$B,$B26,'SG10'!I:I)*SG10_+SUMIF('SG11'!$B:$B,$B26,'SG11'!I:I)*SG11_+SUMIF('SG12'!$B:$B,$B26,'SG12'!I:I)*SG12_+SUMIF('SG13'!$B:$B,$B26,'SG13'!I:I)*SG13_+SUMIF('SG14'!$B:$B,$B26,'SG14'!I:I)*SG14_+SUMIF('SG15'!$B:$B,$B26,'SG15'!I:I)*SG15_) -> 36 | K26: =(SUMIF('SG01'!$B:$B,$B26,'SG01'!K:K)*SG01_+SUMIF('SG02'!$B:$B,$B26,'SG02'!K:K)*SG02_+SUMIF('SG03'!$B:$B,$B26,'SG03'!K:K)*SG03_+SUMIF('SG04'!$B:$B,$B26,'SG04'!K:K)*SG04_+SUMIF('SG05'!$B:$B,$B26,'SG05'!K:K)*SG05_+SUMIF('SG06'!$B:$B,$B26,'SG06'!K:K)*SG06_+SUMIF('SG07'!$B:$B,$B26,'SG07'!K:K)*SG07_+SUMIF('SG08'!$B:$B,$B26,'SG08'!K:K)*SG08_+SUMIF('SG09'!$B:$B,$B26,'SG09'!K:K)*SG09_+SUMIF('SG10'!$B:$B,$B26,'SG10'!K:K)*SG10_+SUMIF('SG11'!$B:$B,$B26,'SG11'!K:K)*SG11_+SUMIF('SG12'!$B:$B,$B26,'SG12'!K:K)*SG12_+SUMIF('SG13'!$B:$B,$B26,'SG13'!K:K)*SG13_+SUMIF('SG14'!$B:$B,$B26,'SG14'!K:K)*SG14_+SUMIF('SG15'!$B:$B,$B26,'SG15'!K:K)*SG15_) -> 629100.69 | L26: =(SUMIF('SG01'!$B:$B,$B26,'SG01'!L:L)*SG01_+SUMIF('SG02'!$B:$B,$B26,'SG02'!L:L)*SG02_+SUMIF('SG03'!$B:$B,$B26,'SG03'!L:L)*SG03_+SUMIF('SG04'!$B:$B,$B26,'SG04'!L:L)*SG04_+SUMIF('SG05'!$B:$B,$B26,'SG05'!L:L)*SG05_+SUMIF('SG06'!$B:$B,$B26,'SG06'!L:L)*SG06_+SUMIF('SG07'!$B:$B,$B26,'SG07'!L:L)*SG07_+SUMIF('SG08'!$B:$B,$B26,'SG08'!L:L)*SG08_+SUMIF('SG09'!$B:$B,$B26,'SG09'!L:L)*SG09_+SUMIF('SG10'!$B:$B,$B26,'SG10'!L:L)*SG10_+SUMIF('SG11'!$B:$B,$B26,'SG11'!L:L)*SG11_+SUMIF('SG12'!$B:$B,$B26,'SG12'!L:L)*SG12_+SUMIF('SG13'!$B:$B,$B26,'SG13'!L:L)*SG13_+SUMIF('SG14'!$B:$B,$B26,'SG14'!L:L)*SG14_+SUMIF('SG15'!$B:$B,$B26,'SG15'!L:L)*SG15_) -> 2550000 | M26: =L26-K26 -> 1920899.3 | N26: =K26/L26 -> 0.24670615 | O26: =L26/L$10 -> 0.0016445639 | P26: =M26/M$10 -> 0.0018670423 | Q26: =I26/I$10 -> 0.0022427112 | R26: =I26/$K$5*100 -> 0.97481722 | S26: =R26*T$5 -> 2.8639618 | T26: =IFERROR(S26*G26,0) -> 202863.96 | V26: =IF(B26<>"",IFERROR(IF($I26>=$X$10,"High","Low"),""),"") -> Low | W26: =IF(B26<>"",IFERROR(IF($L26>=$X$12,"High","Low"),""),"") -> Low | X26: =IF(B26<>"",IFERROR(IF(AND(V26="high",W26="high"),"Star",IF(AND(V26="low",W26="high"),"Puzzle",(IF(AND(V26="high",W26="low"),"Horse","Dog")))),""),"") -> Dog
A27: =+A26+1 -> 10 | B27: GSKVI013 | C27: =VLOOKUP(B27,'SG02'!$B:$E,2,0) -> Sụn Gà Chiên | E27: =VLOOKUP(B27,'SG01'!$B:$E,4,0) -> Phần | F27: =K27/I27 -> 40652.859 | G27: =L27/I27 -> 121875 | H27: =G27-F27 -> 81222.141 | I27: =(SUMIF('SG01'!$B:$B,$B27,'SG01'!I:I)*SG01_+SUMIF('SG02'!$B:$B,$B27,'SG02'!I:I)*SG02_+SUMIF('SG03'!$B:$B,$B27,'SG03'!I:I)*SG03_+SUMIF('SG04'!$B:$B,$B27,'SG04'!I:I)*SG04_+SUMIF('SG05'!$B:$B,$B27,'SG05'!I:I)*SG05_+SUMIF('SG06'!$B:$B,$B27,'SG06'!I:I)*SG06_+SUMIF('SG07'!$B:$B,$B27,'SG07'!I:I)*SG07_+SUMIF('SG08'!$B:$B,$B27,'SG08'!I:I)*SG08_+SUMIF('SG09'!$B:$B,$B27,'SG09'!I:I)*SG09_+SUMIF('SG10'!$B:$B,$B27,'SG10'!I:I)*SG10_+SUMIF('SG11'!$B:$B,$B27,'SG11'!I:I)*SG11_+SUMIF('SG12'!$B:$B,$B27,'SG12'!I:I)*SG12_+SUMIF('SG13'!$B:$B,$B27,'SG13'!I:I)*SG13_+SUMIF('SG14'!$B:$B,$B27,'SG14'!I:I)*SG14_+SUMIF('SG15'!$B:$B,$B27,'SG15'!I:I)*SG15_) -> 64 | K27: =(SUMIF('SG01'!$B:$B,$B27,'SG01'!K:K)*SG01_+SUMIF('SG02'!$B:$B,$B27,'SG02'!K:K)*SG02_+SUMIF('SG03'!$B:$B,$B27,'SG03'!K:K)*SG03_+SUMIF('SG04'!$B:$B,$B27,'SG04'!K:K)*SG04_+SUMIF('SG05'!$B:$B,$B27,'SG05'!K:K)*SG05_+SUMIF('SG06'!$B:$B,$B27,'SG06'!K:K)*SG06_+SUMIF('SG07'!$B:$B,$B27,'SG07'!K:K)*SG07_+SUMIF('SG08'!$B:$B,$B27,'SG08'!K:K)*SG08_+SUMIF('SG09'!$B:$B,$B27,'SG09'!K:K)*SG09_+SUMIF('SG10'!$B:$B,$B27,'SG10'!K:K)*SG10_+SUMIF('SG11'!$B:$B,$B27,'SG11'!K:K)*SG11_+SUMIF('SG12'!$B:$B,$B27,'SG12'!K:K)*SG12_+SUMIF('SG13'!$B:$B,$B27,'SG13'!K:K)*SG13_+SUMIF('SG14'!$B:$B,$B27,'SG14'!K:K)*SG14_+SUMIF('SG15'!$B:$B,$B27,'SG15'!K:K)*SG15_) -> 2601783 | L27: =(SUMIF('SG01'!$B:$B,$B27,'SG01'!L:L)*SG01_+SUMIF('SG02'!$B:$B,$B27,'SG02'!L:L)*SG02_+SUMIF('SG03'!$B:$B,$B27,'SG03'!L:L)*SG03_+SUMIF('SG04'!$B:$B,$B27,'SG04'!L:L)*SG04_+SUMIF('SG05'!$B:$B,$B27,'SG05'!L:L)*SG05_+SUMIF('SG06'!$B:$B,$B27,'SG06'!L:L)*SG06_+SUMIF('SG07'!$B:$B,$B27,'SG07'!L:L)*SG07_+SUMIF('SG08'!$B:$B,$B27,'SG08'!L:L)*SG08_+SUMIF('SG09'!$B:$B,$B27,'SG09'!L:L)*SG09_+SUMIF('SG10'!$B:$B,$B27,'SG10'!L:L)*SG10_+SUMIF('SG11'!$B:$B,$B27,'SG11'!L:L)*SG11_+SUMIF('SG12'!$B:$B,$B27,'SG12'!L:L)*SG12_+SUMIF('SG13'!$B:$B,$B27,'SG13'!L:L)*SG13_+SUMIF('SG14'!$B:$B,$B27,'SG14'!L:L)*SG14_+SUMIF('SG15'!$B:$B,$B27,'SG15'!L:L)*SG15_) -> 7800000 | M27: =L27-K27 -> 5198217 | N27: =K27/L27 -> 0.33356192 | O27: =L27/L$10 -> 0.0050304309 | P27: =M27/M$10 -> 0.0050524726 | Q27: =I27/I$10 -> 0.0039870421 | R27: =I27/$K$5*100 -> 1.7330084 | S27: =R27*T$5 -> 5.0914877 | T27: =IFERROR(S27*G27,0) -> 620525.06 | V27: =IF(B27<>"",IFERROR(IF($I27>=$X$10,"High","Low"),""),"") -> Low | W27: =IF(B27<>"",IFERROR(IF($L27>=$X$12,"High","Low"),""),"") -> High | X27: =IF(B27<>"",IFERROR(IF(AND(V27="high",W27="high"),"Star",IF(AND(V27="low",W27="high"),"Puzzle",(IF(AND(V27="high",W27="low"),"Horse","Dog")))),""),"") -> Puzzle
A28: =+A27+1 -> 11 | B28: GSKVI014 | C28: =VLOOKUP(B28,'SG02'!$B:$E,2,0) -> Gà Chiên Karaage | E28: =VLOOKUP(B28,'SG01'!$B:$E,4,0) -> Phần | F28: =K28/I28 -> 27727.087 | G28: =L28/I28 -> 106791.04 | H28: =G28-F28 -> 79063.958 | I28: =(SUMIF('SG01'!$B:$B,$B28,'SG01'!I:I)*SG01_+SUMIF('SG02'!$B:$B,$B28,'SG02'!I:I)*SG02_+SUMIF('SG03'!$B:$B,$B28,'SG03'!I:I)*SG03_+SUMIF('SG04'!$B:$B,$B28,'SG04'!I:I)*SG04_+SUMIF('SG05'!$B:$B,$B28,'SG05'!I:I)*SG05_+SUMIF('SG06'!$B:$B,$B28,'SG06'!I:I)*SG06_+SUMIF('SG07'!$B:$B,$B28,'SG07'!I:I)*SG07_+SUMIF('SG08'!$B:$B,$B28,'SG08'!I:I)*SG08_+SUMIF('SG09'!$B:$B,$B28,'SG09'!I:I)*SG09_+SUMIF('SG10'!$B:$B,$B28,'SG10'!I:I)*SG10_+SUMIF('SG11'!$B:$B,$B28,'SG11'!I:I)*SG11_+SUMIF('SG12'!$B:$B,$B28,'SG12'!I:I)*SG12_+SUMIF('SG13'!$B:$B,$B28,'SG13'!I:I)*SG13_+SUMIF('SG14'!$B:$B,$B28,'SG14'!I:I)*SG14_+SUMIF('SG15'!$B:$B,$B28,'SG15'!I:I)*SG15_) -> 67 | K28: =(SUMIF('SG01'!$B:$B,$B28,'SG01'!K:K)*SG01_+SUMIF('SG02'!$B:$B,$B28,'SG02'!K:K)*SG02_+SUMIF('SG03'!$B:$B,$B28,'SG03'!K:K)*SG03_+SUMIF('SG04'!$B:$B,$B28,'SG04'!K:K)*SG04_+SUMIF('SG05'!$B:$B,$B28,'SG05'!K:K)*SG05_+SUMIF('SG06'!$B:$B,$B28,'SG06'!K:K)*SG06_+SUMIF('SG07'!$B:$B,$B28,'SG07'!K:K)*SG07_+SUMIF('SG08'!$B:$B,$B28,'SG08'!K:K)*SG08_+SUMIF('SG09'!$B:$B,$B28,'SG09'!K:K)*SG09_+SUMIF('SG10'!$B:$B,$B28,'SG10'!K:K)*SG10_+SUMIF('SG11'!$B:$B,$B28,'SG11'!K:K)*SG11_+SUMIF('SG12'!$B:$B,$B28,'SG12'!K:K)*SG12_+SUMIF('SG13'!$B:$B,$B28,'SG13'!K:K)*SG13_+SUMIF('SG14'!$B:$B,$B28,'SG14'!K:K)*SG14_+SUMIF('SG15'!$B:$B,$B28,'SG15'!K:K)*SG15_) -> 1857714.8 | L28: =(SUMIF('SG01'!$B:$B,$B28,'SG01'!L:L)*SG01_+SUMIF('SG02'!$B:$B,$B28,'SG02'!L:L)*SG02_+SUMIF('SG03'!$B:$B,$B28,'SG03'!L:L)*SG03_+SUMIF('SG04'!$B:$B,$B28,'SG04'!L:L)*SG04_+SUMIF('SG05'!$B:$B,$B28,'SG05'!L:L)*SG05_+SUMIF('SG06'!$B:$B,$B28,'SG06'!L:L)*SG06_+SUMIF('SG07'!$B:$B,$B28,'SG07'!L:L)*SG07_+SUMIF('SG08'!$B:$B,$B28,'SG08'!L:L)*SG08_+SUMIF('SG09'!$B:$B,$B28,'SG09'!L:L)*SG09_+SUMIF('SG10'!$B:$B,$B28,'SG10'!L:L)*SG10_+SUMIF('SG11'!$B:$B,$B28,'SG11'!L:L)*SG11_+SUMIF('SG12'!$B:$B,$B28,'SG12'!L:L)*SG12_+SUMIF('SG13'!$B:$B,$B28,'SG13'!L:L)*SG13_+SUMIF('SG14'!$B:$B,$B28,'SG14'!L:L)*SG14_+SUMIF('SG15'!$B:$B,$B28,'SG15'!L:L)*SG15_) -> 7155000 | M28: =L28-K28 -> 5297285.2 | N28: =K28/L28 -> 0.25963869 | O28: =L28/L$10 -> 0.0046144529 | P28: =M28/M$10 -> 0.0051487631 | Q28: =I28/I$10 -> 0.0041739347 | R28: =I28/$K$5*100 -> 1.8142432 | S28: =R28*T$5 -> 5.3301512 | T28: =IFERROR(S28*G28,0) -> 569212.41 | V28: =IF(B28<>"",IFERROR(IF($I28>=$X$10,"High","Low"),""),"") -> Low | W28: =IF(B28<>"",IFERROR(IF($L28>=$X$12,"High","Low"),""),"") -> High | X28: =IF(B28<>"",IFERROR(IF(AND(V28="high",W28="high"),"Star",IF(AND(V28="low",W28="high"),"Puzzle",(IF(AND(V28="high",W28="low"),"Horse","Dog")))),""),"") -> Puzzle
A29: =+A28+1 -> 12 | B29: GSKVI015 | C29: =VLOOKUP(B29,'SG02'!$B:$E,2,0) -> Cánh Gà Chiên Tebasaki | E29: =VLOOKUP(B29,'SG01'!$B:$E,4,0) -> Phần | F29: =K29/I29 -> 34897.763 | G29: =L29/I29 -> 101666.67 | H29: =G29-F29 -> 66768.904 | I29: =(SUMIF('SG01'!$B:$B,$B29,'SG01'!I:I)*SG01_+SUMIF('SG02'!$B:$B,$B29,'SG02'!I:I)*SG02_+SUMIF('SG03'!$B:$B,$B29,'SG03'!I:I)*SG03_+SUMIF('SG04'!$B:$B,$B29,'SG04'!I:I)*SG04_+SUMIF('SG05'!$B:$B,$B29,'SG05'!I:I)*SG05_+SUMIF('SG06'!$B:$B,$B29,'SG06'!I:I)*SG06_+SUMIF('SG07'!$B:$B,$B29,'SG07'!I:I)*SG07_+SUMIF('SG08'!$B:$B,$B29,'SG08'!I:I)*SG08_+SUMIF('SG09'!$B:$B,$B29,'SG09'!I:I)*SG09_+SUMIF('SG10'!$B:$B,$B29,'SG10'!I:I)*SG10_+SUMIF('SG11'!$B:$B,$B29,'SG11'!I:I)*SG11_+SUMIF('SG12'!$B:$B,$B29,'SG12'!I:I)*SG12_+SUMIF('SG13'!$B:$B,$B29,'SG13'!I:I)*SG13_+SUMIF('SG14'!$B:$B,$B29,'SG14'!I:I)*SG14_+SUMIF('SG15'!$B:$B,$B29,'SG15'!I:I)*SG15_) -> 30 | K29: =(SUMIF('SG01'!$B:$B,$B29,'SG01'!K:K)*SG01_+SUMIF('SG02'!$B:$B,$B29,'SG02'!K:K)*SG02_+SUMIF('SG03'!$B:$B,$B29,'SG03'!K:K)*SG03_+SUMIF('SG04'!$B:$B,$B29,'SG04'!K:K)*SG04_+SUMIF('SG05'!$B:$B,$B29,'SG05'!K:K)*SG05_+SUMIF('SG06'!$B:$B,$B29,'SG06'!K:K)*SG06_+SUMIF('SG07'!$B:$B,$B29,'SG07'!K:K)*SG07_+SUMIF('SG08'!$B:$B,$B29,'SG08'!K:K)*SG08_+SUMIF('SG09'!$B:$B,$B29,'SG09'!K:K)*SG09_+SUMIF('SG10'!$B:$B,$B29,'SG10'!K:K)*SG10_+SUMIF('SG11'!$B:$B,$B29,'SG11'!K:K)*SG11_+SUMIF('SG12'!$B:$B,$B29,'SG12'!K:K)*SG12_+SUMIF('SG13'!$B:$B,$B29,'SG13'!K:K)*SG13_+SUMIF('SG14'!$B:$B,$B29,'SG14'!K:K)*SG14_+SUMIF('SG15'!$B:$B,$B29,'SG15'!K:K)*SG15_) -> 1046932.9 | L29: =(SUMIF('SG01'!$B:$B,$B29,'SG01'!L:L)*SG01_+SUMIF('SG02'!$B:$B,$B29,'SG02'!L:L)*SG02_+SUMIF('SG03'!$B:$B,$B29,'SG03'!L:L)*SG03_+SUMIF('SG04'!$B:$B,$B29,'SG04'!L:L)*SG04_+SUMIF('SG05'!$B:$B,$B29,'SG05'!L:L)*SG05_+SUMIF('SG06'!$B:$B,$B29,'SG06'!L:L)*SG06_+SUMIF('SG07'!$B:$B,$B29,'SG07'!L:L)*SG07_+SUMIF('SG08'!$B:$B,$B29,'SG08'!L:L)*SG08_+SUMIF('SG09'!$B:$B,$B29,'SG09'!L:L)*SG09_+SUMIF('SG10'!$B:$B,$B29,'SG10'!L:L)*SG10_+SUMIF('SG11'!$B:$B,$B29,'SG11'!L:L)*SG11_+SUMIF('SG12'!$B:$B,$B29,'SG12'!L:L)*SG12_+SUMIF('SG13'!$B:$B,$B29,'SG13'!L:L)*SG13_+SUMIF('SG14'!$B:$B,$B29,'SG14'!L:L)*SG14_+SUMIF('SG15'!$B:$B,$B29,'SG15'!L:L)*SG15_) -> 3050000 | M29: =L29-K29 -> 2003067.1 | N29: =K29/L29 -> 0.34325668 | O29: =L29/L$10 -> 0.0019670275 | P29: =M29/M$10 -> 0.0019469063 | Q29: =I29/I$10 -> 0.001868926 | R29: =I29/$K$5*100 -> 0.81234768 | S29: =R29*T$5 -> 2.3866348 | T29: =IFERROR(S29*G29,0) -> 242641.21 | V29: =IF(B29<>"",IFERROR(IF($I29>=$X$10,"High","Low"),""),"") -> Low | W29: =IF(B29<>"",IFERROR(IF($L29>=$X$12,"High","Low"),""),"") -> High | X29: =IF(B29<>"",IFERROR(IF(AND(V29="high",W29="high"),"Star",IF(AND(V29="low",W29="high"),"Puzzle",(IF(AND(V29="high",W29="low"),"Horse","Dog")))),""),"") -> Puzzle
A30: =+A29+1 -> 13 | B30: GSKVI017 | C30: =VLOOKUP(B30,'SG02'!$B:$E,2,0) -> Khoai Lang Nướng Phô Mai | E30: =VLOOKUP(B30,'SG01'!$B:$E,4,0) -> Phần | F30: =K30/I30 -> 21325.771 | G30: =L30/I30 -> 70426.829 | H30: =G30-F30 -> 49101.058 | I30: =(SUMIF('SG01'!$B:$B,$B30,'SG01'!I:I)*SG01_+SUMIF('SG02'!$B:$B,$B30,'SG02'!I:I)*SG02_+SUMIF('SG03'!$B:$B,$B30,'SG03'!I:I)*SG03_+SUMIF('SG04'!$B:$B,$B30,'SG04'!I:I)*SG04_+SUMIF('SG05'!$B:$B,$B30,'SG05'!I:I)*SG05_+SUMIF('SG06'!$B:$B,$B30,'SG06'!I:I)*SG06_+SUMIF('SG07'!$B:$B,$B30,'SG07'!I:I)*SG07_+SUMIF('SG08'!$B:$B,$B30,'SG08'!I:I)*SG08_+SUMIF('SG09'!$B:$B,$B30,'SG09'!I:I)*SG09_+SUMIF('SG10'!$B:$B,$B30,'SG10'!I:I)*SG10_+SUMIF('SG11'!$B:$B,$B30,'SG11'!I:I)*SG11_+SUMIF('SG12'!$B:$B,$B30,'SG12'!I:I)*SG12_+SUMIF('SG13'!$B:$B,$B30,'SG13'!I:I)*SG13_+SUMIF('SG14'!$B:$B,$B30,'SG14'!I:I)*SG14_+SUMIF('SG15'!$B:$B,$B30,'SG15'!I:I)*SG15_) -> 82 | K30: =(SUMIF('SG01'!$B:$B,$B30,'SG01'!K:K)*SG01_+SUMIF('SG02'!$B:$B,$B30,'SG02'!K:K)*SG02_+SUMIF('SG03'!$B:$B,$B30,'SG03'!K:K)*SG03_+SUMIF('SG04'!$B:$B,$B30,'SG04'!K:K)*SG04_+SUMIF('SG05'!$B:$B,$B30,'SG05'!K:K)*SG05_+SUMIF('SG06'!$B:$B,$B30,'SG06'!K:K)*SG06_+SUMIF('SG07'!$B:$B,$B30,'SG07'!K:K)*SG07_+SUMIF('SG08'!$B:$B,$B30,'SG08'!K:K)*SG08_+SUMIF('SG09'!$B:$B,$B30,'SG09'!K:K)*SG09_+SUMIF('SG10'!$B:$B,$B30,'SG10'!K:K)*SG10_+SUMIF('SG11'!$B:$B,$B30,'SG11'!K:K)*SG11_+SUMIF('SG12'!$B:$B,$B30,'SG12'!K:K)*SG12_+SUMIF('SG13'!$B:$B,$B30,'SG13'!K:K)*SG13_+SUMIF('SG14'!$B:$B,$B30,'SG14'!K:K)*SG14_+SUMIF('SG15'!$B:$B,$B30,'SG15'!K:K)*SG15_) -> 1748713.2 | L30: =(SUMIF('SG01'!$B:$B,$B30,'SG01'!L:L)*SG01_+SUMIF('SG02'!$B:$B,$B30,'SG02'!L:L)*SG02_+SUMIF('SG03'!$B:$B,$B30,'SG03'!L:L)*SG03_+SUMIF('SG04'!$B:$B,$B30,'SG04'!L:L)*SG04_+SUMIF('SG05'!$B:$B,$B30,'SG05'!L:L)*SG05_+SUMIF('SG06'!$B:$B,$B30,'SG06'!L:L)*SG06_+SUMIF('SG07'!$B:$B,$B30,'SG07'!L:L)*SG07_+SUMIF('SG08'!$B:$B,$B30,'SG08'!L:L)*SG08_+SUMIF('SG09'!$B:$B,$B30,'SG09'!L:L)*SG09_+SUMIF('SG10'!$B:$B,$B30,'SG10'!L:L)*SG10_+SUMIF('SG11'!$B:$B,$B30,'SG11'!L:L)*SG11_+SUMIF('SG12'!$B:$B,$B30,'SG12'!L:L)*SG12_+SUMIF('SG13'!$B:$B,$B30,'SG13'!L:L)*SG13_+SUMIF('SG14'!$B:$B,$B30,'SG14'!L:L)*SG14_+SUMIF('SG15'!$B:$B,$B30,'SG15'!L:L)*SG15_) -> 5775000 | M30: =L30-K30 -> 4026286.8 | N30: =K30/L30 -> 0.30280749 | O30: =L30/L$10 -> 0.0037244536 | P30: =M30/M$10 -> 0.0039134002 | Q30: =I30/I$10 -> 0.0051083977 | R30: =I30/$K$5*100 -> 2.220417 | S30: =R30*T$5 -> 6.5234686 | T30: =IFERROR(S30*G30,0) -> 459427.21 | V30: =IF(B30<>"",IFERROR(IF($I30>=$X$10,"High","Low"),""),"") -> Low | W30: =IF(B30<>"",IFERROR(IF($L30>=$X$12,"High","Low"),""),"") -> High | X30: =IF(B30<>"",IFERROR(IF(AND(V30="high",W30="high"),"Star",IF(AND(V30="low",W30="high"),"Puzzle",(IF(AND(V30="high",W30="low"),"Horse","Dog")))),""),"") -> Puzzle
S31: =R31*T$5 -> 0 | T31: =IFERROR(S31*G31,0) -> 0
B32: XIENRCN.GSG | C32: XIÊN RAU - CỦ - NẤM NƯỚNG | I32: =SUBTOTAL(9,I33:I42) -> 755 | K32: =SUBTOTAL(9,K33:K42) -> 3572662.5 | L32: =SUBTOTAL(9,L33:L42) -> 13427000 | M32: =SUBTOTAL(9,M33:M42) -> 9854337.5 | N32: =K32/L32 -> 0.26608048 | O32: =L32/L$10 -> 0.0086594353 | P32: =M32/M$10 -> 0.0095780476 | Q32: =I32/I$10 -> 0.047034637 | R32: =I32/$K$5*100 -> 20.444083 | S32: =R32*T$5 -> 60.063644 | T32: =IFERROR(S32*G32,0) -> 0
A33: 1 | B33: GSRAU009 | C33: =VLOOKUP(B33,'SG02'!$B:$E,2,0) -> Ngô Ngọt Nướng | E33: =VLOOKUP(B33,'SG01'!$B:$E,4,0) -> Phần | F33: =K33/I33 -> 2000.0443 | G33: =L33/I33 -> 15333.333 | H33: =G33-F33 -> 13333.289 | I33: =(SUMIF('SG01'!$B:$B,$B33,'SG01'!I:I)*SG01_+SUMIF('SG02'!$B:$B,$B33,'SG02'!I:I)*SG02_+SUMIF('SG03'!$B:$B,$B33,'SG03'!I:I)*SG03_+SUMIF('SG04'!$B:$B,$B33,'SG04'!I:I)*SG04_+SUMIF('SG05'!$B:$B,$B33,'SG05'!I:I)*SG05_+SUMIF('SG06'!$B:$B,$B33,'SG06'!I:I)*SG06_+SUMIF('SG07'!$B:$B,$B33,'SG07'!I:I)*SG07_+SUMIF('SG08'!$B:$B,$B33,'SG08'!I:I)*SG08_+SUMIF('SG09'!$B:$B,$B33,'SG09'!I:I)*SG09_+SUMIF('SG10'!$B:$B,$B33,'SG10'!I:I)*SG10_+SUMIF('SG11'!$B:$B,$B33,'SG11'!I:I)*SG11_+SUMIF('SG12'!$B:$B,$B33,'SG12'!I:I)*SG12_+SUMIF('SG13'!$B:$B,$B33,'SG13'!I:I)*SG13_+SUMIF('SG14'!$B:$B,$B33,'SG14'!I:I)*SG14_+SUMIF('SG15'!$B:$B,$B33,'SG15'!I:I)*SG15_) -> 144 | K33: =(SUMIF('SG01'!$B:$B,$B33,'SG01'!K:K)*SG01_+SUMIF('SG02'!$B:$B,$B33,'SG02'!K:K)*SG02_+SUMIF('SG03'!$B:$B,$B33,'SG03'!K:K)*SG03_+SUMIF('SG04'!$B:$B,$B33,'SG04'!K:K)*SG04_+SUMIF('SG05'!$B:$B,$B33,'SG05'!K:K)*SG05_+SUMIF('SG06'!$B:$B,$B33,'SG06'!K:K)*SG06_+SUMIF('SG07'!$B:$B,$B33,'SG07'!K:K)*SG07_+SUMIF('SG08'!$B:$B,$B33,'SG08'!K:K)*SG08_+SUMIF('SG09'!$B:$B,$B33,'SG09'!K:K)*SG09_+SUMIF('SG10'!$B:$B,$B33,'SG10'!K:K)*SG10_+SUMIF('SG11'!$B:$B,$B33,'SG11'!K:K)*SG11_+SUMIF('SG12'!$B:$B,$B33,'SG12'!K:K)*SG12_+SUMIF('SG13'!$B:$B,$B33,'SG13'!K:K)*SG13_+SUMIF('SG14'!$B:$B,$B33,'SG14'!K:K)*SG14_+SUMIF('SG15'!$B:$B,$B33,'SG15'!K:K)*SG15_) -> 288006.38 | L33: =(SUMIF('SG01'!$B:$B,$B33,'SG01'!L:L)*SG01_+SUMIF('SG02'!$B:$B,$B33,'SG02'!L:L)*SG02_+SUMIF('SG03'!$B:$B,$B33,'SG03'!L:L)*SG03_+SUMIF('SG04'!$B:$B,$B33,'SG04'!L:L)*SG04_+SUMIF('SG05'!$B:$B,$B33,'SG05'!L:L)*SG05_+SUMIF('SG06'!$B:$B,$B33,'SG06'!L:L)*SG06_+SUMIF('SG07'!$B:$B,$B33,'SG07'!L:L)*SG07_+SUMIF('SG08'!$B:$B,$B33,'SG08'!L:L)*SG08_+SUMIF('SG09'!$B:$B,$B33,'SG09'!L:L)*SG09_+SUMIF('SG10'!$B:$B,$B33,'SG10'!L:L)*SG10_+SUMIF('SG11'!$B:$B,$B33,'SG11'!L:L)*SG11_+SUMIF('SG12'!$B:$B,$B33,'SG12'!L:L)*SG12_+SUMIF('SG13'!$B:$B,$B33,'SG13'!L:L)*SG13_+SUMIF('SG14'!$B:$B,$B33,'SG14'!L:L)*SG14_+SUMIF('SG15'!$B:$B,$B33,'SG15'!L:L)*SG15_) -> 2208000 | M33: =L33-K33 -> 1919993.6 | N33: =K33/L33 -> 0.13043767 | O33: =L33/L$10 -> 0.0014239989 | P33: =M33/M$10 -> 0.001866162 | Q33: =I33/I$10 -> 0.0089708448 | R33: =I33/$K$5*100 -> 3.8992689 | S33: =R33*T$5 -> 11.455847 | T33: =IFERROR(S33*G33,0) -> 175656.32 | V33: =IF(B33<>"",IFERROR(IF($I33>=$X$10,"High","Low"),""),"") -> High | W33: =IF(B33<>"",IFERROR(IF($L33>=$X$12,"High","Low"),""),"") -> Low | X33: =IF(B33<>"",IFERROR(IF(AND(V33="high",W33="high"),"Star",IF(AND(V33="low",W33="high"),"Puzzle",(IF(AND(V33="high",W33="low"),"Horse","Dog")))),""),"") -> Horse
A34: 2 | B34: GSRAU010 | C34: =VLOOKUP(B34,'SG02'!$B:$E,2,0) -> Đậu Bắp Nướng | E34: =VLOOKUP(B34,'SG01'!$B:$E,4,0) -> Phần | F34: =K34/I34 -> 2662.3818 | G34: =L34/I34 -> 15489.13 | H34: =G34-F34 -> 12826.749 | I34: =(SUMIF('SG01'!$B:$B,$B34,'SG01'!I:I)*SG01_+SUMIF('SG02'!$B:$B,$B34,'SG02'!I:I)*SG02_+SUMIF('SG03'!$B:$B,$B34,'SG03'!I:I)*SG03_+SUMIF('SG04'!$B:$B,$B34,'SG04'!I:I)*SG04_+SUMIF('SG05'!$B:$B,$B34,'SG05'!I:I)*SG05_+SUMIF('SG06'!$B:$B,$B34,'SG06'!I:I)*SG06_+SUMIF('SG07'!$B:$B,$B34,'SG07'!I:I)*SG07_+SUMIF('SG08'!$B:$B,$B34,'SG08'!I:I)*SG08_+SUMIF('SG09'!$B:$B,$B34,'SG09'!I:I)*SG09_+SUMIF('SG10'!$B:$B,$B34,'SG10'!I:I)*SG10_+SUMIF('SG11'!$B:$B,$B34,'SG11'!I:I)*SG11_+SUMIF('SG12'!$B:$B,$B34,'SG12'!I:I)*SG12_+SUMIF('SG13'!$B:$B,$B34,'SG13'!I:I)*SG13_+SUMIF('SG14'!$B:$B,$B34,'SG14'!I:I)*SG14_+SUMIF('SG15'!$B:$B,$B34,'SG15'!I:I)*SG15_) -> 184 | K34: =(SUMIF('SG01'!$B:$B,$B34,'SG01'!K:K)*SG01_+SUMIF('SG02'!$B:$B,$B34,'SG02'!K:K)*SG02_+SUMIF('SG03'!$B:$B,$B34,'SG03'!K:K)*SG03_+SUMIF('SG04'!$B:$B,$B34,'SG04'!K:K)*SG04_+SUMIF('SG05'!$B:$B,$B34,'SG05'!K:K)*SG05_+SUMIF('SG06'!$B:$B,$B34,'SG06'!K:K)*SG06_+SUMIF('SG07'!$B:$B,$B34,'SG07'!K:K)*SG07_+SUMIF('SG08'!$B:$B,$B34,'SG08'!K:K)*SG08_+SUMIF('SG09'!$B:$B,$B34,'SG09'!K:K)*SG09_+SUMIF('SG10'!$B:$B,$B34,'SG10'!K:K)*SG10_+SUMIF('SG11'!$B:$B,$B34,'SG11'!K:K)*SG11_+SUMIF('SG12'!$B:$B,$B34,'SG12'!K:K)*SG12_+SUMIF('SG13'!$B:$B,$B34,'SG13'!K:K)*SG13_+SUMIF('SG14'!$B:$B,$B34,'SG14'!K:K)*SG14_+SUMIF('SG15'!$B:$B,$B34,'SG15'!K:K)*SG15_) -> 489878.25 | L34: =(SUMIF('SG01'!$B:$B,$B34,'SG01'!L:L)*SG01_+SUMIF('SG02'!$B:$B,$B34,'SG02'!L:L)*SG02_+SUMIF('SG03'!$B:$B,$B34,'SG03'!L:L)*SG03_+SUMIF('SG04'!$B:$B,$B34,'SG04'!L:L)*SG04_+SUMIF('SG05'!$B:$B,$B34,'SG05'!L:L)*SG05_+SUMIF('SG06'!$B:$B,$B34,'SG06'!L:L)*SG06_+SUMIF('SG07'!$B:$B,$B34,'SG07'!L:L)*SG07_+SUMIF('SG08'!$B:$B,$B34,'SG08'!L:L)*SG08_+SUMIF('SG09'!$B:$B,$B34,'SG09'!L:L)*SG09_+SUMIF('SG10'!$B:$B,$B34,'SG10'!L:L)*SG10_+SUMIF('SG11'!$B:$B,$B34,'SG11'!L:L)*SG11_+SUMIF('SG12'!$B:$B,$B34,'SG12'!L:L)*SG12_+SUMIF('SG13'!$B:$B,$B34,'SG13'!L:L)*SG13_+SUMIF('SG14'!$B:$B,$B34,'SG14'!L:L)*SG14_+SUMIF('SG15'!$B:$B,$B34,'SG15'!L:L)*SG15_) -> 2850000 | M34: =L34-K34 -> 2360121.7 | N34: =K34/L34 -> 0.17188711 | O34: =L34/L$10 -> 0.0018380421 | P34: =M34/M$10 -> 0.0022939501 | Q34: =I34/I$10 -> 0.011462746 | R34: =I34/$K$5*100 -> 4.9823991 | S34: =R34*T$5 -> 14.638027 | T34: =IFERROR(S34*G34,0) -> 226730.31 | V34: =IF(B34<>"",IFERROR(IF($I34>=$X$10,"High","Low"),""),"") -> High | W34: =IF(B34<>"",IFERROR(IF($L34>=$X$12,"High","Low"),""),"") -> Low | X34: =IF(B34<>"",IFERROR(IF(AND(V34="high",W34="high"),"Star",IF(AND(V34="low",W34="high"),"Puzzle",(IF(AND(V34="high",W34="low"),"Horse","Dog")))),""),"") -> Horse
A35: 3 | B35: GSRAU011 | C35: =VLOOKUP(B35,'SG02'!$B:$E,2,0) -> Khoai Tây Nướng | E35: =VLOOKUP(B35,'SG01'!$B:$E,4,0) -> Phần | F35: =K35/I35 -> 4689.5682 | G35: =L35/I35 -> 15108.108 | H35: =G35-F35 -> 10418.54 | I35: =(SUMIF('SG01'!$B:$B,$B35,'SG01'!I:I)*SG01_+SUMIF('SG02'!$B:$B,$B35,'SG02'!I:I)*SG02_+SUMIF('SG03'!$B:$B,$B35,'SG03'!I:I)*SG03_+SUMIF('SG04'!$B:$B,$B35,'SG04'!I:I)*SG04_+SUMIF('SG05'!$B:$B,$B35,'SG05'!I:I)*SG05_+SUMIF('SG06'!$B:$B,$B35,'SG06'!I:I)*SG06_+SUMIF('SG07'!$B:$B,$B35,'SG07'!I:I)*SG07_+SUMIF('SG08'!$B:$B,$B35,'SG08'!I:I)*SG08_+SUMIF('SG09'!$B:$B,$B35,'SG09'!I:I)*SG09_+SUMIF('SG10'!$B:$B,$B35,'SG10'!I:I)*SG10_+SUMIF('SG11'!$B:$B,$B35,'SG11'!I:I)*SG11_+SUMIF('SG12'!$B:$B,$B35,'SG12'!I:I)*SG12_+SUMIF('SG13'!$B:$B,$B35,'SG13'!I:I)*SG13_+SUMIF('SG14'!$B:$B,$B35,'SG14'!I:I)*SG14_+SUMIF('SG15'!$B:$B,$B35,'SG15'!I:I)*SG15_) -> 37 | K35: =(SUMIF('SG01'!$B:$B,$B35,'SG01'!K:K)*SG01_+SUMIF('SG02'!$B:$B,$B35,'SG02'!K:K)*SG02_+SUMIF('SG03'!$B:$B,$B35,'SG03'!K:K)*SG03_+SUMIF('SG04'!$B:$B,$B35,'SG04'!K:K)*SG04_+SUMIF('SG05'!$B:$B,$B35,'SG05'!K:K)*SG05_+SUMIF('SG06'!$B:$B,$B35,'SG06'!K:K)*SG06_+SUMIF('SG07'!$B:$B,$B35,'SG07'!K:K)*SG07_+SUMIF('SG08'!$B:$B,$B35,'SG08'!K:K)*SG08_+SUMIF('SG09'!$B:$B,$B35,'SG09'!K:K)*SG09_+SUMIF('SG10'!$B:$B,$B35,'SG10'!K:K)*SG10_+SUMIF('SG11'!$B:$B,$B35,'SG11'!K:K)*SG11_+SUMIF('SG12'!$B:$B,$B35,'SG12'!K:K)*SG12_+SUMIF('SG13'!$B:$B,$B35,'SG13'!K:K)*SG13_+SUMIF('SG14'!$B:$B,$B35,'SG14'!K:K)*SG14_+SUMIF('SG15'!$B:$B,$B35,'SG15'!K:K)*SG15_) -> 173514.02 | L35: =(SUMIF('SG01'!$B:$B,$B35,'SG01'!L:L)*SG01_+SUMIF('SG02'!$B:$B,$B35,'SG02'!L:L)*SG02_+SUMIF('SG03'!$B:$B,$B35,'SG03'!L:L)*SG03_+SUMIF('SG04'!$B:$B,$B35,'SG04'!L:L)*SG04_+SUMIF('SG05'!$B:$B,$B35,'SG05'!L:L)*SG05_+SUMIF('SG06'!$B:$B,$B35,'SG06'!L:L)*SG06_+SUMIF('SG07'!$B:$B,$B35,'SG07'!L:L)*SG07_+SUMIF('SG08'!$B:$B,$B35,'SG08'!L:L)*SG08_+SUMIF('SG09'!$B:$B,$B35,'SG09'!L:L)*SG09_+SUMIF('SG10'!$B:$B,$B35,'SG10'!L:L)*SG10_+SUMIF('SG11'!$B:$B,$B35,'SG11'!L:L)*SG11_+SUMIF('SG12'!$B:$B,$B35,'SG12'!L:L)*SG12_+SUMIF('SG13'!$B:$B,$B35,'SG13'!L:L)*SG13_+SUMIF('SG14'!$B:$B,$B35,'SG14'!L:L)*SG14_+SUMIF('SG15'!$B:$B,$B35,'SG15'!L:L)*SG15_) -> 559000 | M35: =L35-K35 -> 385485.98 | N35: =K35/L35 -> 0.31040076 | O35: =L35/L$10 -> 0.00036051421 | P35: =M35/M$10 -> 0.00037467796 | Q35: =I35/I$10 -> 0.0023050087 | R35: =I35/$K$5*100 -> 1.0018955 | S35: =R35*T$5 -> 2.9435163 | T35: =IFERROR(S35*G35,0) -> 44470.963 | V35: =IF(B35<>"",IFERROR(IF($I35>=$X$10,"High","Low"),""),"") -> Low | W35: =IF(B35<>"",IFERROR(IF($L35>=$X$12,"High","Low"),""),"") -> Low | X35: =IF(B35<>"",IFERROR(IF(AND(V35="high",W35="high"),"Star",IF(AND(V35="low",W35="high"),"Puzzle",(IF(AND(V35="high",W35="low"),"Horse","Dog")))),""),"") -> Dog
A36: 4 | B36: GSRAU012 | C36: =VLOOKUP(B36,'SG02'!$B:$E,2,0) -> Bí Ngòi Nướng | E36: =VLOOKUP(B36,'SG01'!$B:$E,4,0) -> Phần | F36: =K36/I36 -> 2990.0411 | G36: =L36/I36 -> 15115.942 | H36: =G36-F36 -> 12125.901 | I36: =(SUMIF('SG01'!$B:$B,$B36,'SG01'!I:I)*SG01_+SUMIF('SG02'!$B:$B,$B36,'SG02'!I:I)*SG02_+SUMIF('SG03'!$B:$B,$B36,'SG03'!I:I)*SG03_+SUMIF('SG04'!$B:$B,$B36,'SG04'!I:I)*SG04_+SUMIF('SG05'!$B:$B,$B36,'SG05'!I:I)*SG05_+SUMIF('SG06'!$B:$B,$B36,'SG06'!I:I)*SG06_+SUMIF('SG07'!$B:$B,$B36,'SG07'!I:I)*SG07_+SUMIF('SG08'!$B:$B,$B36,'SG08'!I:I)*SG08_+SUMIF('SG09'!$B:$B,$B36,'SG09'!I:I)*SG09_+SUMIF('SG10'!$B:$B,$B36,'SG10'!I:I)*SG10_+SUMIF('SG11'!$B:$B,$B36,'SG11'!I:I)*SG11_+SUMIF('SG12'!$B:$B,$B36,'SG12'!I:I)*SG12_+SUMIF('SG13'!$B:$B,$B36,'SG13'!I:I)*SG13_+SUMIF('SG14'!$B:$B,$B36,'SG14'!I:I)*SG14_+SUMIF('SG15'!$B:$B,$B36,'SG15'!I:I)*SG15_) -> 69 | K36: =(SUMIF('SG01'!$B:$B,$B36,'SG01'!K:K)*SG01_+SUMIF('SG02'!$B:$B,$B36,'SG02'!K:K)*SG02_+SUMIF('SG03'!$B:$B,$B36,'SG03'!K:K)*SG03_+SUMIF('SG04'!$B:$B,$B36,'SG04'!K:K)*SG04_+SUMIF('SG05'!$B:$B,$B36,'SG05'!K:K)*SG05_+SUMIF('SG06'!$B:$B,$B36,'SG06'!K:K)*SG06_+SUMIF('SG07'!$B:$B,$B36,'SG07'!K:K)*SG07_+SUMIF('SG08'!$B:$B,$B36,'SG08'!K:K)*SG08_+SUMIF('SG09'!$B:$B,$B36,'SG09'!K:K)*SG09_+SUMIF('SG10'!$B:$B,$B36,'SG10'!K:K)*SG10_+SUMIF('SG11'!$B:$B,$B36,'SG11'!K:K)*SG11_+SUMIF('SG12'!$B:$B,$B36,'SG12'!K:K)*SG12_+SUMIF('SG13'!$B:$B,$B36,'SG13'!K:K)*SG13_+SUMIF('SG14'!$B:$B,$B36,'SG14'!K:K)*SG14_+SUMIF('SG15'!$B:$B,$B36,'SG15'!K:K)*SG15_) -> 206312.84 | L36: =(SUMIF('SG01'!$B:$B,$B36,'SG01'!L:L)*SG01_+SUMIF('SG02'!$B:$B,$B36,'SG02'!L:L)*SG02_+SUMIF('SG03'!$B:$B,$B36,'SG03'!L:L)*SG03_+SUMIF('SG04'!$B:$B,$B36,'SG04'!L:L)*SG04_+SUMIF('SG05'!$B:$B,$B36,'SG05'!L:L)*SG05_+SUMIF('SG06'!$B:$B,$B36,'SG06'!L:L)*SG06_+SUMIF('SG07'!$B:$B,$B36,'SG07'!L:L)*SG07_+SUMIF('SG08'!$B:$B,$B36,'SG08'!L:L)*SG08_+SUMIF('SG09'!$B:$B,$B36,'SG09'!L:L)*SG09_+SUMIF('SG10'!$B:$B,$B36,'SG10'!L:L)*SG10_+SUMIF('SG11'!$B:$B,$B36,'SG11'!L:L)*SG11_+SUMIF('SG12'!$B:$B,$B36,'SG12'!L:L)*SG12_+SUMIF('SG13'!$B:$B,$B36,'SG13'!L:L)*SG13_+SUMIF('SG14'!$B:$B,$B36,'SG14'!L:L)*SG14_+SUMIF('SG15'!$B:$B,$B36,'SG15'!L:L)*SG15_) -> 1043000 | M36: =L36-K36 -> 836687.16 | N36: =K36/L36 -> 0.19780713 | O36: =L36/L$10 -> 0.0006726589 | P36: =M36/M$10 -> 0.00081322864 | Q36: =I36/I$10 -> 0.0042985298 | R36: =I36/$K$5*100 -> 1.8683997 | S36: =R36*T$5 -> 5.4892601 | T36: =IFERROR(S36*G36,0) -> 82975.338 | V36: =IF(B36<>"",IFERROR(IF($I36>=$X$10,"High","Low"),""),"") -> Low | W36: =IF(B36<>"",IFERROR(IF($L36>=$X$12,"High","Low"),""),"") -> Low | X36: =IF(B36<>"",IFERROR(IF(AND(V36="high",W36="high"),"Star",IF(AND(V36="low",W36="high"),"Puzzle",(IF(AND(V36="high",W36="low"),"Horse","Dog")))),""),"") -> Dog
A37: 5 | B37: GSRAU013 | C37: =VLOOKUP(B37,'SG02'!$B:$E,2,0) -> Bí Đỏ Nướng | E37: =VLOOKUP(B37,'SG01'!$B:$E,4,0) -> Phần | F37: =K37/I37 -> 3098 | G37: =L37/I37 -> 15222.222 | H37: =G37-F37 -> 12124.222 | I37: =(SUMIF('SG01'!$B:$B,$B37,'SG01'!I:I)*SG01_+SUMIF('SG02'!$B:$B,$B37,'SG02'!I:I)*SG02_+SUMIF('SG03'!$B:$B,$B37,'SG03'!I:I)*SG03_+SUMIF('SG04'!$B:$B,$B37,'SG04'!I:I)*SG04_+SUMIF('SG05'!$B:$B,$B37,'SG05'!I:I)*SG05_+SUMIF('SG06'!$B:$B,$B37,'SG06'!I:I)*SG06_+SUMIF('SG07'!$B:$B,$B37,'SG07'!I:I)*SG07_+SUMIF('SG08'!$B:$B,$B37,'SG08'!I:I)*SG08_+SUMIF('SG09'!$B:$B,$B37,'SG09'!I:I)*SG09_+SUMIF('SG10'!$B:$B,$B37,'SG10'!I:I)*SG10_+SUMIF('SG11'!$B:$B,$B37,'SG11'!I:I)*SG11_+SUMIF('SG12'!$B:$B,$B37,'SG12'!I:I)*SG12_+SUMIF('SG13'!$B:$B,$B37,'SG13'!I:I)*SG13_+SUMIF('SG14'!$B:$B,$B37,'SG14'!I:I)*SG14_+SUMIF('SG15'!$B:$B,$B37,'SG15'!I:I)*SG15_) -> 27 | K37: =(SUMIF('SG01'!$B:$B,$B37,'SG01'!K:K)*SG01_+SUMIF('SG02'!$B:$B,$B37,'SG02'!K:K)*SG02_+SUMIF('SG03'!$B:$B,$B37,'SG03'!K:K)*SG03_+SUMIF('SG04'!$B:$B,$B37,'SG04'!K:K)*SG04_+SUMIF('SG05'!$B:$B,$B37,'SG05'!K:K)*SG05_+SUMIF('SG06'!$B:$B,$B37,'SG06'!K:K)*SG06_+SUMIF('SG07'!$B:$B,$B37,'SG07'!K:K)*SG07_+SUMIF('SG08'!$B:$B,$B37,'SG08'!K:K)*SG08_+SUMIF('SG09'!$B:$B,$B37,'SG09'!K:K)*SG09_+SUMIF('SG10'!$B:$B,$B37,'SG10'!K:K)*SG10_+SUMIF('SG11'!$B:$B,$B37,'SG11'!K:K)*SG11_+SUMIF('SG12'!$B:$B,$B37,'SG12'!K:K)*SG12_+SUMIF('SG13'!$B:$B,$B37,'SG13'!K:K)*SG13_+SUMIF('SG14'!$B:$B,$B37,'SG14'!K:K)*SG14_+SUMIF('SG15'!$B:$B,$B37,'SG15'!K:K)*SG15_) -> 83646 | L37: =(SUMIF('SG01'!$B:$B,$B37,'SG01'!L:L)*SG01_+SUMIF('SG02'!$B:$B,$B37,'SG02'!L:L)*SG02_+SUMIF('SG03'!$B:$B,$B37,'SG03'!L:L)*SG03_+SUMIF('SG04'!$B:$B,$B37,'SG04'!L:L)*SG04_+SUMIF('SG05'!$B:$B,$B37,'SG05'!L:L)*SG05_+SUMIF('SG06'!$B:$B,$B37,'SG06'!L:L)*SG06_+SUMIF('SG07'!$B:$B,$B37,'SG07'!L:L)*SG07_+SUMIF('SG08'!$B:$B,$B37,'SG08'!L:L)*SG08_+SUMIF('SG09'!$B:$B,$B37,'SG09'!L:L)*SG09_+SUMIF('SG10'!$B:$B,$B37,'SG10'!L:L)*SG10_+SUMIF('SG11'!$B:$B,$B37,'SG11'!L:L)*SG11_+SUMIF('SG12'!$B:$B,$B37,'SG12'!L:L)*SG12_+SUMIF('SG13'!$B:$B,$B37,'SG13'!L:L)*SG13_+SUMIF('SG14'!$B:$B,$B37,'SG14'!L:L)*SG14_+SUMIF('SG15'!$B:$B,$B37,'SG15'!L:L)*SG15_) -> 411000 | M37: =L37-K37 -> 327354 | N37: =K37/L37 -> 0.20351825 | O37: =L37/L$10 -> 0.00026506501 | P37: =M37/M$10 -> 0.00031817585 | Q37: =I37/I$10 -> 0.0016820334 | R37: =I37/$K$5*100 -> 0.73111292 | S37: =R37*T$5 -> 2.1479714 | T37: =IFERROR(S37*G37,0) -> 32696.897 | V37: =IF(B37<>"",IFERROR(IF($I37>=$X$10,"High","Low"),""),"") -> Low | W37: =IF(B37<>"",IFERROR(IF($L37>=$X$12,"High","Low"),""),"") -> Low | X37: =IF(B37<>"",IFERROR(IF(AND(V37="high",W37="high"),"Star",IF(AND(V37="low",W37="high"),"Puzzle",(IF(AND(V37="high",W37="low"),"Horse","Dog")))),""),"") -> Dog
A38: 6 | B38: GSRAU014 | C38: =VLOOKUP(B38,'SG02'!$B:$E,2,0) -> Khoai Lang Nướng | E38: =VLOOKUP(B38,'SG01'!$B:$E,4,0) -> Phần | F38: =K38/I38 -> 3284.8462 | G38: =L38/I38 -> 15285.714 | H38: =G38-F38 -> 12000.868 | I38: =(SUMIF('SG01'!$B:$B,$B38,'SG01'!I:I)*SG01_+SUMIF('SG02'!$B:$B,$B38,'SG02'!I:I)*SG02_+SUMIF('SG03'!$B:$B,$B38,'SG03'!I:I)*SG03_+SUMIF('SG04'!$B:$B,$B38,'SG04'!I:I)*SG04_+SUMIF('SG05'!$B:$B,$B38,'SG05'!I:I)*SG05_+SUMIF('SG06'!$B:$B,$B38,'SG06'!I:I)*SG06_+SUMIF('SG07'!$B:$B,$B38,'SG07'!I:I)*SG07_+SUMIF('SG08'!$B:$B,$B38,'SG08'!I:I)*SG08_+SUMIF('SG09'!$B:$B,$B38,'SG09'!I:I)*SG09_+SUMIF('SG10'!$B:$B,$B38,'SG10'!I:I)*SG10_+SUMIF('SG11'!$B:$B,$B38,'SG11'!I:I)*SG11_+SUMIF('SG12'!$B:$B,$B38,'SG12'!I:I)*SG12_+SUMIF('SG13'!$B:$B,$B38,'SG13'!I:I)*SG13_+SUMIF('SG14'!$B:$B,$B38,'SG14'!I:I)*SG14_+SUMIF('SG15'!$B:$B,$B38,'SG15'!I:I)*SG15_) -> 49 | K38: =(SUMIF('SG01'!$B:$B,$B38,'SG01'!K:K)*SG01_+SUMIF('SG02'!$B:$B,$B38,'SG02'!K:K)*SG02_+SUMIF('SG03'!$B:$B,$B38,'SG03'!K:K)*SG03_+SUMIF('SG04'!$B:$B,$B38,'SG04'!K:K)*SG04_+SUMIF('SG05'!$B:$B,$B38,'SG05'!K:K)*SG05_+SUMIF('SG06'!$B:$B,$B38,'SG06'!K:K)*SG06_+SUMIF('SG07'!$B:$B,$B38,'SG07'!K:K)*SG07_+SUMIF('SG08'!$B:$B,$B38,'SG08'!K:K)*SG08_+SUMIF('SG09'!$B:$B,$B38,'SG09'!K:K)*SG09_+SUMIF('SG10'!$B:$B,$B38,'SG10'!K:K)*SG10_+SUMIF('SG11'!$B:$B,$B38,'SG11'!K:K)*SG11_+SUMIF('SG12'!$B:$B,$B38,'SG12'!K:K)*SG12_+SUMIF('SG13'!$B:$B,$B38,'SG13'!K:K)*SG13_+SUMIF('SG14'!$B:$B,$B38,'SG14'!K:K)*SG14_+SUMIF('SG15'!$B:$B,$B38,'SG15'!K:K)*SG15_) -> 160957.46 | L38: =(SUMIF('SG01'!$B:$B,$B38,'SG01'!L:L)*SG01_+SUMIF('SG02'!$B:$B,$B38,'SG02'!L:L)*SG02_+SUMIF('SG03'!$B:$B,$B38,'SG03'!L:L)*SG03_+SUMIF('SG04'!$B:$B,$B38,'SG04'!L:L)*SG04_+SUMIF('SG05'!$B:$B,$B38,'SG05'!L:L)*SG05_+SUMIF('SG06'!$B:$B,$B38,'SG06'!L:L)*SG06_+SUMIF('SG07'!$B:$B,$B38,'SG07'!L:L)*SG07_+SUMIF('SG08'!$B:$B,$B38,'SG08'!L:L)*SG08_+SUMIF('SG09'!$B:$B,$B38,'SG09'!L:L)*SG09_+SUMIF('SG10'!$B:$B,$B38,'SG10'!L:L)*SG10_+SUMIF('SG11'!$B:$B,$B38,'SG11'!L:L)*SG11_+SUMIF('SG12'!$B:$B,$B38,'SG12'!L:L)*SG12_+SUMIF('SG13'!$B:$B,$B38,'SG13'!L:L)*SG13_+SUMIF('SG14'!$B:$B,$B38,'SG14'!L:L)*SG14_+SUMIF('SG15'!$B:$B,$B38,'SG15'!L:L)*SG15_) -> 749000 | M38: =L38-K38 -> 588042.54 | N38: =K38/L38 -> 0.21489648 | O38: =L38/L$10 -> 0.00048305035 | P38: =M38/M$10 -> 0.00057155536 | Q38: =I38/I$10 -> 0.0030525791 | R38: =I38/$K$5*100 -> 1.3268346 | S38: =R38*T$5 -> 3.8981702 | T38: =IFERROR(S38*G38,0) -> 59586.317 | V38: =IF(B38<>"",IFERROR(IF($I38>=$X$10,"High","Low"),""),"") -> Low | W38: =IF(B38<>"",IFERROR(IF($L38>=$X$12,"High","Low"),""),"") -> Low | X38: =IF(B38<>"",IFERROR(IF(AND(V38="high",W38="high"),"Star",IF(AND(V38="low",W38="high"),"Puzzle",(IF(AND(V38="high",W38="low"),"Horse","Dog")))),""),"") -> Dog
A39: 7 | B39: GSRAU015 | C39: =VLOOKUP(B39,'SG02'!$B:$E,2,0) -> Nấm Đùi Gà Nướng | E39: =VLOOKUP(B39,'SG01'!$B:$E,4,0) -> Phần | F39: =K39/I39 -> 3756.1125 | G39: =L39/I39 -> 15336.842 | H39: =G39-F39 -> 11580.73 | I39: =(SUMIF('SG01'!$B:$B,$B39,'SG01'!I:I)*SG01_+SUMIF('SG02'!$B:$B,$B39,'SG02'!I:I)*SG02_+SUMIF('SG03'!$B:$B,$B39,'SG03'!I:I)*SG03_+SUMIF('SG04'!$B:$B,$B39,'SG04'!I:I)*SG04_+SUMIF('SG05'!$B:$B,$B39,'SG05'!I:I)*SG05_+SUMIF('SG06'!$B:$B,$B39,'SG06'!I:I)*SG06_+SUMIF('SG07'!$B:$B,$B39,'SG07'!I:I)*SG07_+SUMIF('SG08'!$B:$B,$B39,'SG08'!I:I)*SG08_+SUMIF('SG09'!$B:$B,$B39,'SG09'!I:I)*SG09_+SUMIF('SG10'!$B:$B,$B39,'SG10'!I:I)*SG10_+SUMIF('SG11'!$B:$B,$B39,'SG11'!I:I)*SG11_+SUMIF('SG12'!$B:$B,$B39,'SG12'!I:I)*SG12_+SUMIF('SG13'!$B:$B,$B39,'SG13'!I:I)*SG13_+SUMIF('SG14'!$B:$B,$B39,'SG14'!I:I)*SG14_+SUMIF('SG15'!$B:$B,$B39,'SG15'!I:I)*SG15_) -> 95 | K39: =(SUMIF('SG01'!$B:$B,$B39,'SG01'!K:K)*SG01_+SUMIF('SG02'!$B:$B,$B39,'SG02'!K:K)*SG02_+SUMIF('SG03'!$B:$B,$B39,'SG03'!K:K)*SG03_+SUMIF('SG04'!$B:$B,$B39,'SG04'!K:K)*SG04_+SUMIF('SG05'!$B:$B,$B39,'SG05'!K:K)*SG05_+SUMIF('SG06'!$B:$B,$B39,'SG06'!K:K)*SG06_+SUMIF('SG07'!$B:$B,$B39,'SG07'!K:K)*SG07_+SUMIF('SG08'!$B:$B,$B39,'SG08'!K:K)*SG08_+SUMIF('SG09'!$B:$B,$B39,'SG09'!K:K)*SG09_+SUMIF('SG10'!$B:$B,$B39,'SG10'!K:K)*SG10_+SUMIF('SG11'!$B:$B,$B39,'SG11'!K:K)*SG11_+SUMIF('SG12'!$B:$B,$B39,'SG12'!K:K)*SG12_+SUMIF('SG13'!$B:$B,$B39,'SG13'!K:K)*SG13_+SUMIF('SG14'!$B:$B,$B39,'SG14'!K:K)*SG14_+SUMIF('SG15'!$B:$B,$B39,'SG15'!K:K)*SG15_) -> 356830.69 | L39: =(SUMIF('SG01'!$B:$B,$B39,'SG01'!L:L)*SG01_+SUMIF('SG02'!$B:$B,$B39,'SG02'!L:L)*SG02_+SUMIF('SG03'!$B:$B,$B39,'SG03'!L:L)*SG03_+SUMIF('SG04'!$B:$B,$B39,'SG04'!L:L)*SG04_+SUMIF('SG05'!$B:$B,$B39,'SG05'!L:L)*SG05_+SUMIF('SG06'!$B:$B,$B39,'SG06'!L:L)*SG06_+SUMIF('SG07'!$B:$B,$B39,'SG07'!L:L)*SG07_+SUMIF('SG08'!$B:$B,$B39,'SG08'!L:L)*SG08_+SUMIF('SG09'!$B:$B,$B39,'SG09'!L:L)*SG09_+SUMIF('SG10'!$B:$B,$B39,'SG10'!L:L)*SG10_+SUMIF('SG11'!$B:$B,$B39,'SG11'!L:L)*SG11_+SUMIF('SG12'!$B:$B,$B39,'SG12'!L:L)*SG12_+SUMIF('SG13'!$B:$B,$B39,'SG13'!L:L)*SG13_+SUMIF('SG14'!$B:$B,$B39,'SG14'!L:L)*SG14_+SUMIF('SG15'!$B:$B,$B39,'SG15'!L:L)*SG15_) -> 1457000 | M39: =L39-K39 -> 1100169.3 | N39: =K39/L39 -> 0.24490782 | O39: =L39/L$10 -> 0.00093965869 | P39: =M39/M$10 -> 0.0010693234 | Q39: =I39/I$10 -> 0.0059182656 | R39: =I39/$K$5*100 -> 2.5724343 | S39: =R39*T$5 -> 7.557677 | T39: =IFERROR(S39*G39,0) -> 115910.9 | V39: =IF(B39<>"",IFERROR(IF($I39>=$X$10,"High","Low"),""),"") -> Low | W39: =IF(B39<>"",IFERROR(IF($L39>=$X$12,"High","Low"),""),"") -> Low | X39: =IF(B39<>"",IFERROR(IF(AND(V39="high",W39="high"),"Star",IF(AND(V39="low",W39="high"),"Puzzle",(IF(AND(V39="high",W39="low"),"Horse","Dog")))),""),"") -> Dog
A40: 8 | B40: GSRAU016 | C40: =VLOOKUP(B40,'SG02'!$B:$E,2,0) -> Nấm Đông Cô Nướng | E40: =VLOOKUP(B40,'SG01'!$B:$E,4,0) -> Phần | F40: =K40/I40 -> 13861.187 | G40: =L40/I40 -> 30104 | H40: =G40-F40 -> 16242.813 | I40: =(SUMIF('SG01'!$B:$B,$B40,'SG01'!I:I)*SG01_+SUMIF('SG02'!$B:$B,$B40,'SG02'!I:I)*SG02_+SUMIF('SG03'!$B:$B,$B40,'SG03'!I:I)*SG03_+SUMIF('SG04'!$B:$B,$B40,'SG04'!I:I)*SG04_+SUMIF('SG05'!$B:$B,$B40,'SG05'!I:I)*SG05_+SUMIF('SG06'!$B:$B,$B40,'SG06'!I:I)*SG06_+SUMIF('SG07'!$B:$B,$B40,'SG07'!I:I)*SG07_+SUMIF('SG08'!$B:$B,$B40,'SG08'!I:I)*SG08_+SUMIF('SG09'!$B:$B,$B40,'SG09'!I:I)*SG09_+SUMIF('SG10'!$B:$B,$B40,'SG10'!I:I)*SG10_+SUMIF('SG11'!$B:$B,$B40,'SG11'!I:I)*SG11_+SUMIF('SG12'!$B:$B,$B40,'SG12'!I:I)*SG12_+SUMIF('SG13'!$B:$B,$B40,'SG13'!I:I)*SG13_+SUMIF('SG14'!$B:$B,$B40,'SG14'!I:I)*SG14_+SUMIF('SG15'!$B:$B,$B40,'SG15'!I:I)*SG15_) -> 125 | K40: =(SUMIF('SG01'!$B:$B,$B40,'SG01'!K:K)*SG01_+SUMIF('SG02'!$B:$B,$B40,'SG02'!K:K)*SG02_+SUMIF('SG03'!$B:$B,$B40,'SG03'!K:K)*SG03_+SUMIF('SG04'!$B:$B,$B40,'SG04'!K:K)*SG04_+SUMIF('SG05'!$B:$B,$B40,'SG05'!K:K)*SG05_+SUMIF('SG06'!$B:$B,$B40,'SG06'!K:K)*SG06_+SUMIF('SG07'!$B:$B,$B40,'SG07'!K:K)*SG07_+SUMIF('SG08'!$B:$B,$B40,'SG08'!K:K)*SG08_+SUMIF('SG09'!$B:$B,$B40,'SG09'!K:K)*SG09_+SUMIF('SG10'!$B:$B,$B40,'SG10'!K:K)*SG10_+SUMIF('SG11'!$B:$B,$B40,'SG11'!K:K)*SG11_+SUMIF('SG12'!$B:$B,$B40,'SG12'!K:K)*SG12_+SUMIF('SG13'!$B:$B,$B40,'SG13'!K:K)*SG13_+SUMIF('SG14'!$B:$B,$B40,'SG14'!K:K)*SG14_+SUMIF('SG15'!$B:$B,$B40,'SG15'!K:K)*SG15_) -> 1732648.4 | L40: =(SUMIF('SG01'!$B:$B,$B40,'SG01'!L:L)*SG01_+SUMIF('SG02'!$B:$B,$B40,'SG02'!L:L)*SG02_+SUMIF('SG03'!$B:$B,$B40,'SG03'!L:L)*SG03_+SUMIF('SG04'!$B:$B,$B40,'SG04'!L:L)*SG04_+SUMIF('SG05'!$B:$B,$B40,'SG05'!L:L)*SG05_+SUMIF('SG06'!$B:$B,$B40,'SG06'!L:L)*SG06_+SUMIF('SG07'!$B:$B,$B40,'SG07'!L:L)*SG07_+SUMIF('SG08'!$B:$B,$B40,'SG08'!L:L)*SG08_+SUMIF('SG09'!$B:$B,$B40,'SG09'!L:L)*SG09_+SUMIF('SG10'!$B:$B,$B40,'SG10'!L:L)*SG10_+SUMIF('SG11'!$B:$B,$B40,'SG11'!L:L)*SG11_+SUMIF('SG12'!$B:$B,$B40,'SG12'!L:L)*SG12_+SUMIF('SG13'!$B:$B,$B40,'SG13'!L:L)*SG13_+SUMIF('SG14'!$B:$B,$B40,'SG14'!L:L)*SG14_+SUMIF('SG15'!$B:$B,$B40,'SG15'!L:L)*SG15_) -> 3763000 | M40: =L40-K40 -> 2030351.6 | N40: =K40/L40 -> 0.46044336 | O40: =L40/L$10 -> 0.0024268604 | P40: =M40/M$10 -> 0.0019734259 | Q40: =I40/I$10 -> 0.0077871916 | R40: =I40/$K$5*100 -> 3.384782 | S40: =R40*T$5 -> 9.9443119 | T40: =IFERROR(S40*G40,0) -> 299363.56 | V40: =IF(B40<>"",IFERROR(IF($I40>=$X$10,"High","Low"),""),"") -> High | W40: =IF(B40<>"",IFERROR(IF($L40>=$X$12,"High","Low"),""),"") -> High | X40: =IF(B40<>"",IFERROR(IF(AND(V40="high",W40="high"),"Star",IF(AND(V40="low",W40="high"),"Puzzle",(IF(AND(V40="high",W40="low"),"Horse","Dog")))),""),"") -> Star
A41: 9 | B41: GSRAU017 | C41: =VLOOKUP(B41,'SG02'!$B:$E,2,0) -> Cà Chua Bi | E41: =VLOOKUP(B41,'SG01'!$B:$E,4,0) -> Phần | F41: =K41/I41 -> 3234.7407 | G41: =L41/I41 -> 15480 | H41: =G41-F41 -> 12245.259 | I41: =(SUMIF('SG01'!$B:$B,$B41,'SG01'!I:I)*SG01_+SUMIF('SG02'!$B:$B,$B41,'SG02'!I:I)*SG02_+SUMIF('SG03'!$B:$B,$B41,'SG03'!I:I)*SG03_+SUMIF('SG04'!$B:$B,$B41,'SG04'!I:I)*SG04_+SUMIF('SG05'!$B:$B,$B41,'SG05'!I:I)*SG05_+SUMIF('SG06'!$B:$B,$B41,'SG06'!I:I)*SG06_+SUMIF('SG07'!$B:$B,$B41,'SG07'!I:I)*SG07_+SUMIF('SG08'!$B:$B,$B41,'SG08'!I:I)*SG08_+SUMIF('SG09'!$B:$B,$B41,'SG09'!I:I)*SG09_+SUMIF('SG10'!$B:$B,$B41,'SG10'!I:I)*SG10_+SUMIF('SG11'!$B:$B,$B41,'SG11'!I:I)*SG11_+SUMIF('SG12'!$B:$B,$B41,'SG12'!I:I)*SG12_+SUMIF('SG13'!$B:$B,$B41,'SG13'!I:I)*SG13_+SUMIF('SG14'!$B:$B,$B41,'SG14'!I:I)*SG14_+SUMIF('SG15'!$B:$B,$B41,'SG15'!I:I)*SG15_) -> 25 | K41: =(SUMIF('SG01'!$B:$B,$B41,'SG01'!K:K)*SG01_+SUMIF('SG02'!$B:$B,$B41,'SG02'!K:K)*SG02_+SUMIF('SG03'!$B:$B,$B41,'SG03'!K:K)*SG03_+SUMIF('SG04'!$B:$B,$B41,'SG04'!K:K)*SG04_+SUMIF('SG05'!$B:$B,$B41,'SG05'!K:K)*SG05_+SUMIF('SG06'!$B:$B,$B41,'SG06'!K:K)*SG06_+SUMIF('SG07'!$B:$B,$B41,'SG07'!K:K)*SG07_+SUMIF('SG08'!$B:$B,$B41,'SG08'!K:K)*SG08_+SUMIF('SG09'!$B:$B,$B41,'SG09'!K:K)*SG09_+SUMIF('SG10'!$B:$B,$B41,'SG10'!K:K)*SG10_+SUMIF('SG11'!$B:$B,$B41,'SG11'!K:K)*SG11_+SUMIF('SG12'!$B:$B,$B41,'SG12'!K:K)*SG12_+SUMIF('SG13'!$B:$B,$B41,'SG13'!K:K)*SG13_+SUMIF('SG14'!$B:$B,$B41,'SG14'!K:K)*SG14_+SUMIF('SG15'!$B:$B,$B41,'SG15'!K:K)*SG15_) -> 80868.519 | L41: =(SUMIF('SG01'!$B:$B,$B41,'SG01'!L:L)*SG01_+SUMIF('SG02'!$B:$B,$B41,'SG02'!L:L)*SG02_+SUMIF('SG03'!$B:$B,$B41,'SG03'!L:L)*SG03_+SUMIF('SG04'!$B:$B,$B41,'SG04'!L:L)*SG04_+SUMIF('SG05'!$B:$B,$B41,'SG05'!L:L)*SG05_+SUMIF('SG06'!$B:$B,$B41,'SG06'!L:L)*SG06_+SUMIF('SG07'!$B:$B,$B41,'SG07'!L:L)*SG07_+SUMIF('SG08'!$B:$B,$B41,'SG08'!L:L)*SG08_+SUMIF('SG09'!$B:$B,$B41,'SG09'!L:L)*SG09_+SUMIF('SG10'!$B:$B,$B41,'SG10'!L:L)*SG10_+SUMIF('SG11'!$B:$B,$B41,'SG11'!L:L)*SG11_+SUMIF('SG12'!$B:$B,$B41,'SG12'!L:L)*SG12_+SUMIF('SG13'!$B:$B,$B41,'SG13'!L:L)*SG13_+SUMIF('SG14'!$B:$B,$B41,'SG14'!L:L)*SG14_+SUMIF('SG15'!$B:$B,$B41,'SG15'!L:L)*SG15_) -> 387000 | M41: =L41-K41 -> 306131.48 | N41: =K41/L41 -> 0.20896258 | O41: =L41/L$10 -> 0.00024958676 | P41: =M41/M$10 -> 0.00029754835 | Q41: =I41/I$10 -> 0.0015574383 | R41: =I41/$K$5*100 -> 0.6769564 | S41: =R41*T$5 -> 1.9888624 | T41: =IFERROR(S41*G41,0) -> 30787.589 | V41: =IF(B41<>"",IFERROR(IF($I41>=$X$10,"High","Low"),""),"") -> Low | W41: =IF(B41<>"",IFERROR(IF($L41>=$X$12,"High","Low"),""),"") -> Low | X41: =IF(B41<>"",IFERROR(IF(AND(V41="high",W41="high"),"Star",IF(AND(V41="low",W41="high"),"Puzzle",(IF(AND(V41="high",W41="low"),"Horse","Dog")))),""),"") -> Dog
S42: =R42*T$5 -> 0 | T42: =IFERROR(S42*G42,0) -> 0
B43: XIENTHIT.GSG | C43: XIÊN THỊT NƯỚNG | I43: =SUBTOTAL(9,I44:I67) -> 1651 | K43: =SUBTOTAL(9,K44:K67) -> 20114375 | L43: =SUBTOTAL(9,L44:L67) -> 66828000 | M43: =SUBTOTAL(9,M44:M67) -> 46713625 | N43: =K43/L43 -> 0.30098724 | O43: =L43/L$10 -> 0.043099184 | P43: =M43/M$10 -> 0.045403897 | Q43: =I43/I$10 -> 0.10285323 | R43: =I43/$K$5*100 -> 44.706201 | S43: =R43*T$5 -> 131.34447 | T43: =IFERROR(S43*G43,0) -> 0
A44: 1 | B44: GSNCD018 | C44: =VLOOKUP(B44,'SG02'!$B:$E,2,0) -> Phần Combo Xiên Nướng 1 | E44: =VLOOKUP(B44,'SG01'!$B:$E,4,0) -> Phần | F44: =K44/I44 -> 49610.053 | G44: =L44/I44 -> 168260.87 | H44: =G44-F44 -> 118650.82 | I44: =(SUMIF('SG01'!$B:$B,$B44,'SG01'!I:I)*SG01_+SUMIF('SG02'!$B:$B,$B44,'SG02'!I:I)*SG02_+SUMIF('SG03'!$B:$B,$B44,'SG03'!I:I)*SG03_+SUMIF('SG04'!$B:$B,$B44,'SG04'!I:I)*SG04_+SUMIF('SG05'!$B:$B,$B44,'SG05'!I:I)*SG05_+SUMIF('SG06'!$B:$B,$B44,'SG06'!I:I)*SG06_+SUMIF('SG07'!$B:$B,$B44,'SG07'!I:I)*SG07_+SUMIF('SG08'!$B:$B,$B44,'SG08'!I:I)*SG08_+SUMIF('SG09'!$B:$B,$B44,'SG09'!I:I)*SG09_+SUMIF('SG10'!$B:$B,$B44,'SG10'!I:I)*SG10_+SUMIF('SG11'!$B:$B,$B44,'SG11'!I:I)*SG11_+SUMIF('SG12'!$B:$B,$B44,'SG12'!I:I)*SG12_+SUMIF('SG13'!$B:$B,$B44,'SG13'!I:I)*SG13_+SUMIF('SG14'!$B:$B,$B44,'SG14'!I:I)*SG14_+SUMIF('SG15'!$B:$B,$B44,'SG15'!I:I)*SG15_) -> 23 | K44: =(SUMIF('SG01'!$B:$B,$B44,'SG01'!K:K)*SG01_+SUMIF('SG02'!$B:$B,$B44,'SG02'!K:K)*SG02_+SUMIF('SG03'!$B:$B,$B44,'SG03'!K:K)*SG03_+SUMIF('SG04'!$B:$B,$B44,'SG04'!K:K)*SG04_+SUMIF('SG05'!$B:$B,$B44,'SG05'!K:K)*SG05_+SUMIF('SG06'!$B:$B,$B44,'SG06'!K:K)*SG06_+SUMIF('SG07'!$B:$B,$B44,'SG07'!K:K)*SG07_+SUMIF('SG08'!$B:$B,$B44,'SG08'!K:K)*SG08_+SUMIF('SG09'!$B:$B,$B44,'SG09'!K:K)*SG09_+SUMIF('SG10'!$B:$B,$B44,'SG10'!K:K)*SG10_+SUMIF('SG11'!$B:$B,$B44,'SG11'!K:K)*SG11_+SUMIF('SG12'!$B:$B,$B44,'SG12'!K:K)*SG12_+SUMIF('SG13'!$B:$B,$B44,'SG13'!K:K)*SG13_+SUMIF('SG14'!$B:$B,$B44,'SG14'!K:K)*SG14_+SUMIF('SG15'!$B:$B,$B44,'SG15'!K:K)*SG15_) -> 1141031.2 | L44: =(SUMIF('SG01'!$B:$B,$B44,'SG01'!L:L)*SG01_+SUMIF('SG02'!$B:$B,$B44,'SG02'!L:L)*SG02_+SUMIF('SG03'!$B:$B,$B44,'SG03'!L:L)*SG03_+SUMIF('SG04'!$B:$B,$B44,'SG04'!L:L)*SG04_+SUMIF('SG05'!$B:$B,$B44,'SG05'!L:L)*SG05_+SUMIF('SG06'!$B:$B,$B44,'SG06'!L:L)*SG06_+SUMIF('SG07'!$B:$B,$B44,'SG07'!L:L)*SG07_+SUMIF('SG08'!$B:$B,$B44,'SG08'!L:L)*SG08_+SUMIF('SG09'!$B:$B,$B44,'SG09'!L:L)*SG09_+SUMIF('SG10'!$B:$B,$B44,'SG10'!L:L)*SG10_+SUMIF('SG11'!$B:$B,$B44,'SG11'!L:L)*SG11_+SUMIF('SG12'!$B:$B,$B44,'SG12'!L:L)*SG12_+SUMIF('SG13'!$B:$B,$B44,'SG13'!L:L)*SG13_+SUMIF('SG14'!$B:$B,$B44,'SG14'!L:L)*SG14_+SUMIF('SG15'!$B:$B,$B44,'SG15'!L:L)*SG15_) -> 3870000 | M44: =L44-K44 -> 2728968.8 | N44: =K44/L44 -> 0.29484011 | O44: =L44/L$10 -> 0.0024958676 | P44: =M44/M$10 -> 0.0026524556 | Q44: =I44/I$10 -> 0.0014328433 | R44: =I44/$K$5*100 -> 0.62279989 | S44: =R44*T$5 -> 1.8297534 | T44: =IFERROR(S44*G44,0) -> 307875.89 | V44: =IF(B44<>"",IFERROR(IF($I44>=$X$10,"High","Low"),""),"") -> Low | W44: =IF(B44<>"",IFERROR(IF($L44>=$X$12,"High","Low"),""),"") -> High | X44: =IF(B44<>"",IFERROR(IF(AND(V44="high",W44="high"),"Star",IF(AND(V44="low",W44="high"),"Puzzle",(IF(AND(V44="high",W44="low"),"Horse","Dog")))),""),"") -> Puzzle
A45: 2 | B45: GSNCD019 | C45: =VLOOKUP(B45,'SG02'!$B:$E,2,0) -> Phần Combo Xiên Nướng 2 | E45: =VLOOKUP(B45,'SG01'!$B:$E,4,0) -> Phần | F45: =K45/I45 -> 45794 | G45: =L45/I45 -> 153173.08 | H45: =G45-F45 -> 107379.08 | I45: =(SUMIF('SG01'!$B:$B,$B45,'SG01'!I:I)*SG01_+SUMIF('SG02'!$B:$B,$B45,'SG02'!I:I)*SG02_+SUMIF('SG03'!$B:$B,$B45,'SG03'!I:I)*SG03_+SUMIF('SG04'!$B:$B,$B45,'SG04'!I:I)*SG04_+SUMIF('SG05'!$B:$B,$B45,'SG05'!I:I)*SG05_+SUMIF('SG06'!$B:$B,$B45,'SG06'!I:I)*SG06_+SUMIF('SG07'!$B:$B,$B45,'SG07'!I:I)*SG07_+SUMIF('SG08'!$B:$B,$B45,'SG08'!I:I)*SG08_+SUMIF('SG09'!$B:$B,$B45,'SG09'!I:I)*SG09_+SUMIF('SG10'!$B:$B,$B45,'SG10'!I:I)*SG10_+SUMIF('SG11'!$B:$B,$B45,'SG11'!I:I)*SG11_+SUMIF('SG12'!$B:$B,$B45,'SG12'!I:I)*SG12_+SUMIF('SG13'!$B:$B,$B45,'SG13'!I:I)*SG13_+SUMIF('SG14'!$B:$B,$B45,'SG14'!I:I)*SG14_+SUMIF('SG15'!$B:$B,$B45,'SG15'!I:I)*SG15_) -> 52 | K45: =(SUMIF('SG01'!$B:$B,$B45,'SG01'!K:K)*SG01_+SUMIF('SG02'!$B:$B,$B45,'SG02'!K:K)*SG02_+SUMIF('SG03'!$B:$B,$B45,'SG03'!K:K)*SG03_+SUMIF('SG04'!$B:$B,$B45,'SG04'!K:K)*SG04_+SUMIF('SG05'!$B:$B,$B45,'SG05'!K:K)*SG05_+SUMIF('SG06'!$B:$B,$B45,'SG06'!K:K)*SG06_+SUMIF('SG07'!$B:$B,$B45,'SG07'!K:K)*SG07_+SUMIF('SG08'!$B:$B,$B45,'SG08'!K:K)*SG08_+SUMIF('SG09'!$B:$B,$B45,'SG09'!K:K)*SG09_+SUMIF('SG10'!$B:$B,$B45,'SG10'!K:K)*SG10_+SUMIF('SG11'!$B:$B,$B45,'SG11'!K:K)*SG11_+SUMIF('SG12'!$B:$B,$B45,'SG12'!K:K)*SG12_+SUMIF('SG13'!$B:$B,$B45,'SG13'!K:K)*SG13_+SUMIF('SG14'!$B:$B,$B45,'SG14'!K:K)*SG14_+SUMIF('SG15'!$B:$B,$B45,'SG15'!K:K)*SG15_) -> 2381288 | L45: =(SUMIF('SG01'!$B:$B,$B45,'SG01'!L:L)*SG01_+SUMIF('SG02'!$B:$B,$B45,'SG02'!L:L)*SG02_+SUMIF('SG03'!$B:$B,$B45,'SG03'!L:L)*SG03_+SUMIF('SG04'!$B:$B,$B45,'SG04'!L:L)*SG04_+SUMIF('SG05'!$B:$B,$B45,'SG05'!L:L)*SG05_+SUMIF('SG06'!$B:$B,$B45,'SG06'!L:L)*SG06_+SUMIF('SG07'!$B:$B,$B45,'SG07'!L:L)*SG07_+SUMIF('SG08'!$B:$B,$B45,'SG08'!L:L)*SG08_+SUMIF('SG09'!$B:$B,$B45,'SG09'!L:L)*SG09_+SUMIF('SG10'!$B:$B,$B45,'SG10'!L:L)*SG10_+SUMIF('SG11'!$B:$B,$B45,'SG11'!L:L)*SG11_+SUMIF('SG12'!$B:$B,$B45,'SG12'!L:L)*SG12_+SUMIF('SG13'!$B:$B,$B45,'SG13'!L:L)*SG13_+SUMIF('SG14'!$B:$B,$B45,'SG14'!L:L)*SG14_+SUMIF('SG15'!$B:$B,$B45,'SG15'!L:L)*SG15_) -> 7965000 | M45: =L45-K45 -> 5583712 | N45: =K45/L45 -> 0.29896899 | O45: =L45/L$10 -> 0.0051368438 | P45: =M45/M$10 -> 0.0054271593 | Q45: =I45/I$10 -> 0.0032394717 | R45: =I45/$K$5*100 -> 1.4080693 | S45: =R45*T$5 -> 4.1368337 | T45: =IFERROR(S45*G45,0) -> 633651.55 | V45: =IF(B45<>"",IFERROR(IF($I45>=$X$10,"High","Low"),""),"") -> Low | W45: =IF(B45<>"",IFERROR(IF($L45>=$X$12,"High","Low"),""),"") -> High | X45: =IF(B45<>"",IFERROR(IF(AND(V45="high",W45="high"),"Star",IF(AND(V45="low",W45="high"),"Puzzle",(IF(AND(V45="high",W45="low"),"Horse","Dog")))),""),"") -> Puzzle
A46: 3 | B46: GSNCD020 | C46: =VLOOKUP(B46,'SG02'!$B:$E,2,0) -> Xiên Sụn Gà Xốt Tare | E46: =VLOOKUP(B46,'SG01'!$B:$E,4,0) -> Phần | F46: =K46/I46 -> 9836.6324 | G46: =L46/I46 -> 25407.767 | H46: =G46-F46 -> 15571.135 | I46: =(SUMIF('SG01'!$B:$B,$B46,'SG01'!I:I)*SG01_+SUMIF('SG02'!$B:$B,$B46,'SG02'!I:I)*SG02_+SUMIF('SG03'!$B:$B,$B46,'SG03'!I:I)*SG03_+SUMIF('SG04'!$B:$B,$B46,'SG04'!I:I)*SG04_+SUMIF('SG05'!$B:$B,$B46,'SG05'!I:I)*SG05_+SUMIF('SG06'!$B:$B,$B46,'SG06'!I:I)*SG06_+SUMIF('SG07'!$B:$B,$B46,'SG07'!I:I)*SG07_+SUMIF('SG08'!$B:$B,$B46,'SG08'!I:I)*SG08_+SUMIF('SG09'!$B:$B,$B46,'SG09'!I:I)*SG09_+SUMIF('SG10'!$B:$B,$B46,'SG10'!I:I)*SG10_+SUMIF('SG11'!$B:$B,$B46,'SG11'!I:I)*SG11_+SUMIF('SG12'!$B:$B,$B46,'SG12'!I:I)*SG12_+SUMIF('SG13'!$B:$B,$B46,'SG13'!I:I)*SG13_+SUMIF('SG14'!$B:$B,$B46,'SG14'!I:I)*SG14_+SUMIF('SG15'!$B:$B,$B46,'SG15'!I:I)*SG15_) -> 206 | K46: =(SUMIF('SG01'!$B:$B,$B46,'SG01'!K:K)*SG01_+SUMIF('SG02'!$B:$B,$B46,'SG02'!K:K)*SG02_+SUMIF('SG03'!$B:$B,$B46,'SG03'!K:K)*SG03_+SUMIF('SG04'!$B:$B,$B46,'SG04'!K:K)*SG04_+SUMIF('SG05'!$B:$B,$B46,'SG05'!K:K)*SG05_+SUMIF('SG06'!$B:$B,$B46,'SG06'!K:K)*SG06_+SUMIF('SG07'!$B:$B,$B46,'SG07'!K:K)*SG07_+SUMIF('SG08'!$B:$B,$B46,'SG08'!K:K)*SG08_+SUMIF('SG09'!$B:$B,$B46,'SG09'!K:K)*SG09_+SUMIF('SG10'!$B:$B,$B46,'SG10'!K:K)*SG10_+SUMIF('SG11'!$B:$B,$B46,'SG11'!K:K)*SG11_+SUMIF('SG12'!$B:$B,$B46,'SG12'!K:K)*SG12_+SUMIF('SG13'!$B:$B,$B46,'SG13'!K:K)*SG13_+SUMIF('SG14'!$B:$B,$B46,'SG14'!K:K)*SG14_+SUMIF('SG15'!$B:$B,$B46,'SG15'!K:K)*SG15_) -> 2026346.3 | L46: =(SUMIF('SG01'!$B:$B,$B46,'SG01'!L:L)*SG01_+SUMIF('SG02'!$B:$B,$B46,'SG02'!L:L)*SG02_+SUMIF('SG03'!$B:$B,$B46,'SG03'!L:L)*SG03_+SUMIF('SG04'!$B:$B,$B46,'SG04'!L:L)*SG04_+SUMIF('SG05'!$B:$B,$B46,'SG05'!L:L)*SG05_+SUMIF('SG06'!$B:$B,$B46,'SG06'!L:L)*SG06_+SUMIF('SG07'!$B:$B,$B46,'SG07'!L:L)*SG07_+SUMIF('SG08'!$B:$B,$B46,'SG08'!L:L)*SG08_+SUMIF('SG09'!$B:$B,$B46,'SG09'!L:L)*SG09_+SUMIF('SG10'!$B:$B,$B46,'SG10'!L:L)*SG10_+SUMIF('SG11'!$B:$B,$B46,'SG11'!L:L)*SG11_+SUMIF('SG12'!$B:$B,$B46,'SG12'!L:L)*SG12_+SUMIF('SG13'!$B:$B,$B46,'SG13'!L:L)*SG13_+SUMIF('SG14'!$B:$B,$B46,'SG14'!L:L)*SG14_+SUMIF('SG15'!$B:$B,$B46,'SG15'!L:L)*SG15_) -> 5234000 | M46: =L46-K46 -> 3207653.7 | N46: =K46/L46 -> 0.3871506 | O46: =L46/L$10 -> 0.0033755481 | P46: =M46/M$10 -> 0.0031177195 | Q46: =I46/I$10 -> 0.012833292 | R46: =I46/$K$5*100 -> 5.5781208 | S46: =R46*T$5 -> 16.388226 | T46: =IFERROR(S46*G46,0) -> 416388.23 | V46: =IF(B46<>"",IFERROR(IF($I46>=$X$10,"High","Low"),""),"") -> High | W46: =IF(B46<>"",IFERROR(IF($L46>=$X$12,"High","Low"),""),"") -> High | X46: =IF(B46<>"",IFERROR(IF(AND(V46="high",W46="high"),"Star",IF(AND(V46="low",W46="high"),"Puzzle",(IF(AND(V46="high",W46="low"),"Horse","Dog")))),""),"") -> Star
A47: 4 | B47: GSNCD021 | C47: =VLOOKUP(B47,'SG02'!$B:$E,2,0) -> Xiên Sụn Gà Xốt Muối | E47: =VLOOKUP(B47,'SG01'!$B:$E,4,0) -> Phần | F47: =K47/I47 -> 9632.9712 | G47: =L47/I47 -> 25220.93 | H47: =G47-F47 -> 15587.959 | I47: =(SUMIF('SG01'!$B:$B,$B47,'SG01'!I:I)*SG01_+SUMIF('SG02'!$B:$B,$B47,'SG02'!I:I)*SG02_+SUMIF('SG03'!$B:$B,$B47,'SG03'!I:I)*SG03_+SUMIF('SG04'!$B:$B,$B47,'SG04'!I:I)*SG04_+SUMIF('SG05'!$B:$B,$B47,'SG05'!I:I)*SG05_+SUMIF('SG06'!$B:$B,$B47,'SG06'!I:I)*SG06_+SUMIF('SG07'!$B:$B,$B47,'SG07'!I:I)*SG07_+SUMIF('SG08'!$B:$B,$B47,'SG08'!I:I)*SG08_+SUMIF('SG09'!$B:$B,$B47,'SG09'!I:I)*SG09_+SUMIF('SG10'!$B:$B,$B47,'SG10'!I:I)*SG10_+SUMIF('SG11'!$B:$B,$B47,'SG11'!I:I)*SG11_+SUMIF('SG12'!$B:$B,$B47,'SG12'!I:I)*SG12_+SUMIF('SG13'!$B:$B,$B47,'SG13'!I:I)*SG13_+SUMIF('SG14'!$B:$B,$B47,'SG14'!I:I)*SG14_+SUMIF('SG15'!$B:$B,$B47,'SG15'!I:I)*SG15_) -> 172 | K47: =(SUMIF('SG01'!$B:$B,$B47,'SG01'!K:K)*SG01_+SUMIF('SG02'!$B:$B,$B47,'SG02'!K:K)*SG02_+SUMIF('SG03'!$B:$B,$B47,'SG03'!K:K)*SG03_+SUMIF('SG04'!$B:$B,$B47,'SG04'!K:K)*SG04_+SUMIF('SG05'!$B:$B,$B47,'SG05'!K:K)*SG05_+SUMIF('SG06'!$B:$B,$B47,'SG06'!K:K)*SG06_+SUMIF('SG07'!$B:$B,$B47,'SG07'!K:K)*SG07_+SUMIF('SG08'!$B:$B,$B47,'SG08'!K:K)*SG08_+SUMIF('SG09'!$B:$B,$B47,'SG09'!K:K)*SG09_+SUMIF('SG10'!$B:$B,$B47,'SG10'!K:K)*SG10_+SUMIF('SG11'!$B:$B,$B47,'SG11'!K:K)*SG11_+SUMIF('SG12'!$B:$B,$B47,'SG12'!K:K)*SG12_+SUMIF('SG13'!$B:$B,$B47,'SG13'!K:K)*SG13_+SUMIF('SG14'!$B:$B,$B47,'SG14'!K:K)*SG14_+SUMIF('SG15'!$B:$B,$B47,'SG15'!K:K)*SG15_) -> 1656871.1 | L47: =(SUMIF('SG01'!$B:$B,$B47,'SG01'!L:L)*SG01_+SUMIF('SG02'!$B:$B,$B47,'SG02'!L:L)*SG02_+SUMIF('SG03'!$B:$B,$B47,'SG03'!L:L)*SG03_+SUMIF('SG04'!$B:$B,$B47,'SG04'!L:L)*SG04_+SUMIF('SG05'!$B:$B,$B47,'SG05'!L:L)*SG05_+SUMIF('SG06'!$B:$B,$B47,'SG06'!L:L)*SG06_+SUMIF('SG07'!$B:$B,$B47,'SG07'!L:L)*SG07_+SUMIF('SG08'!$B:$B,$B47,'SG08'!L:L)*SG08_+SUMIF('SG09'!$B:$B,$B47,'SG09'!L:L)*SG09_+SUMIF('SG10'!$B:$B,$B47,'SG10'!L:L)*SG10_+SUMIF('SG11'!$B:$B,$B47,'SG11'!L:L)*SG11_+SUMIF('SG12'!$B:$B,$B47,'SG12'!L:L)*SG12_+SUMIF('SG13'!$B:$B,$B47,'SG13'!L:L)*SG13_+SUMIF('SG14'!$B:$B,$B47,'SG14'!L:L)*SG14_+SUMIF('SG15'!$B:$B,$B47,'SG15'!L:L)*SG15_) -> 4338000 | M47: =L47-K47 -> 2681128.9 | N47: =K47/L47 -> 0.38194353 | O47: =L47/L$10 -> 0.0027976935 | P47: =M47/M$10 -> 0.0026059571 | Q47: =I47/I$10 -> 0.010715176 | R47: =I47/$K$5*100 -> 4.6574601 | S47: =R47*T$5 -> 13.683373 | T47: =IFERROR(S47*G47,0) -> 345107.4 | V47: =IF(B47<>"",IFERROR(IF($I47>=$X$10,"High","Low"),""),"") -> High | W47: =IF(B47<>"",IFERROR(IF($L47>=$X$12,"High","Low"),""),"") -> High | X47: =IF(B47<>"",IFERROR(IF(AND(V47="high",W47="high"),"Star",IF(AND(V47="low",W47="high"),"Puzzle",(IF(AND(V47="high",W47="low"),"Horse","Dog")))),""),"") -> Star
A48: 5 | B48: GSNCD022 | C48: =VLOOKUP(B48,'SG02'!$B:$E,2,0) -> Xiên Cánh Gà Khúc Giữa Xốt Tare | E48: =VLOOKUP(B48,'SG01'!$B:$E,4,0) -> Phần | F48: =K48/I48 -> 12274.174 | G48: =L48/I48 -> 35820.513 | H48: =G48-F48 -> 23546.339 | I48: =(SUMIF('SG01'!$B:$B,$B48,'SG01'!I:I)*SG01_+SUMIF('SG02'!$B:$B,$B48,'SG02'!I:I)*SG02_+SUMIF('SG03'!$B:$B,$B48,'SG03'!I:I)*SG03_+SUMIF('SG04'!$B:$B,$B48,'SG04'!I:I)*SG04_+SUMIF('SG05'!$B:$B,$B48,'SG05'!I:I)*SG05_+SUMIF('SG06'!$B:$B,$B48,'SG06'!I:I)*SG06_+SUMIF('SG07'!$B:$B,$B48,'SG07'!I:I)*SG07_+SUMIF('SG08'!$B:$B,$B48,'SG08'!I:I)*SG08_+SUMIF('SG09'!$B:$B,$B48,'SG09'!I:I)*SG09_+SUMIF('SG10'!$B:$B,$B48,'SG10'!I:I)*SG10_+SUMIF('SG11'!$B:$B,$B48,'SG11'!I:I)*SG11_+SUMIF('SG12'!$B:$B,$B48,'SG12'!I:I)*SG12_+SUMIF('SG13'!$B:$B,$B48,'SG13'!I:I)*SG13_+SUMIF('SG14'!$B:$B,$B48,'SG14'!I:I)*SG14_+SUMIF('SG15'!$B:$B,$B48,'SG15'!I:I)*SG15_) -> 117 | K48: =(SUMIF('SG01'!$B:$B,$B48,'SG01'!K:K)*SG01_+SUMIF('SG02'!$B:$B,$B48,'SG02'!K:K)*SG02_+SUMIF('SG03'!$B:$B,$B48,'SG03'!K:K)*SG03_+SUMIF('SG04'!$B:$B,$B48,'SG04'!K:K)*SG04_+SUMIF('SG05'!$B:$B,$B48,'SG05'!K:K)*SG05_+SUMIF('SG06'!$B:$B,$B48,'SG06'!K:K)*SG06_+SUMIF('SG07'!$B:$B,$B48,'SG07'!K:K)*SG07_+SUMIF('SG08'!$B:$B,$B48,'SG08'!K:K)*SG08_+SUMIF('SG09'!$B:$B,$B48,'SG09'!K:K)*SG09_+SUMIF('SG10'!$B:$B,$B48,'SG10'!K:K)*SG10_+SUMIF('SG11'!$B:$B,$B48,'SG11'!K:K)*SG11_+SUMIF('SG12'!$B:$B,$B48,'SG12'!K:K)*SG12_+SUMIF('SG13'!$B:$B,$B48,'SG13'!K:K)*SG13_+SUMIF('SG14'!$B:$B,$B48,'SG14'!K:K)*SG14_+SUMIF('SG15'!$B:$B,$B48,'SG15'!K:K)*SG15_) -> 1436078.3 | L48: =(SUMIF('SG01'!$B:$B,$B48,'SG01'!L:L)*SG01_+SUMIF('SG02'!$B:$B,$B48,'SG02'!L:L)*SG02_+SUMIF('SG03'!$B:$B,$B48,'SG03'!L:L)*SG03_+SUMIF('SG04'!$B:$B,$B48,'SG04'!L:L)*SG04_+SUMIF('SG05'!$B:$B,$B48,'SG05'!L:L)*SG05_+SUMIF('SG06'!$B:$B,$B48,'SG06'!L:L)*SG06_+SUMIF('SG07'!$B:$B,$B48,'SG07'!L:L)*SG07_+SUMIF('SG08'!$B:$B,$B48,'SG08'!L:L)*SG08_+SUMIF('SG09'!$B:$B,$B48,'SG09'!L:L)*SG09_+SUMIF('SG10'!$B:$B,$B48,'SG10'!L:L)*SG10_+SUMIF('SG11'!$B:$B,$B48,'SG11'!L:L)*SG11_+SUMIF('SG12'!$B:$B,$B48,'SG12'!L:L)*SG12_+SUMIF('SG13'!$B:$B,$B48,'SG13'!L:L)*SG13_+SUMIF('SG14'!$B:$B,$B48,'SG14'!L:L)*SG14_+SUMIF('SG15'!$B:$B,$B48,'SG15'!L:L)*SG15_) -> 4191000 | M48: =L48-K48 -> 2754921.7 | N48: =K48/L48 -> 0.34265767 | O48: =L48/L$10 -> 0.0027028892 | P48: =M48/M$10 -> 0.0026776809 | Q48: =I48/I$10 -> 0.0072888114 | R48: =I48/$K$5*100 -> 3.168156 | S48: =R48*T$5 -> 9.3078759 | T48: =IFERROR(S48*G48,0) -> 333412.89 | V48: =IF(B48<>"",IFERROR(IF($I48>=$X$10,"High","Low"),""),"") -> High | W48: =IF(B48<>"",IFERROR(IF($L48>=$X$12,"High","Low"),""),"") -> High | X48: =IF(B48<>"",IFERROR(IF(AND(V48="high",W48="high"),"Star",IF(AND(V48="low",W48="high"),"Puzzle",(IF(AND(V48="high",W48="low"),"Horse","Dog")))),""),"") -> Star
A49: 6 | B49: GSNCD023 | C49: =VLOOKUP(B49,'SG02'!$B:$E,2,0) -> Xiên Cánh Gà Khúc Giữa Xốt Muối | E49: =VLOOKUP(B49,'SG01'!$B:$E,4,0) -> Phần | F49: =K49/I49 -> 12070.496 | G49: =L49/I49 -> 35900 | H49: =G49-F49 -> 23829.504 | I49: =(SUMIF('SG01'!$B:$B,$B49,'SG01'!I:I)*SG01_+SUMIF('SG02'!$B:$B,$B49,'SG02'!I:I)*SG02_+SUMIF('SG03'!$B:$B,$B49,'SG03'!I:I)*SG03_+SUMIF('SG04'!$B:$B,$B49,'SG04'!I:I)*SG04_+SUMIF('SG05'!$B:$B,$B49,'SG05'!I:I)*SG05_+SUMIF('SG06'!$B:$B,$B49,'SG06'!I:I)*SG06_+SUMIF('SG07'!$B:$B,$B49,'SG07'!I:I)*SG07_+SUMIF('SG08'!$B:$B,$B49,'SG08'!I:I)*SG08_+SUMIF('SG09'!$B:$B,$B49,'SG09'!I:I)*SG09_+SUMIF('SG10'!$B:$B,$B49,'SG10'!I:I)*SG10_+SUMIF('SG11'!$B:$B,$B49,'SG11'!I:I)*SG11_+SUMIF('SG12'!$B:$B,$B49,'SG12'!I:I)*SG12_+SUMIF('SG13'!$B:$B,$B49,'SG13'!I:I)*SG13_+SUMIF('SG14'!$B:$B,$B49,'SG14'!I:I)*SG14_+SUMIF('SG15'!$B:$B,$B49,'SG15'!I:I)*SG15_) -> 80 | K49: =(SUMIF('SG01'!$B:$B,$B49,'SG01'!K:K)*SG01_+SUMIF('SG02'!$B:$B,$B49,'SG02'!K:K)*SG02_+SUMIF('SG03'!$B:$B,$B49,'SG03'!K:K)*SG03_+SUMIF('SG04'!$B:$B,$B49,'SG04'!K:K)*SG04_+SUMIF('SG05'!$B:$B,$B49,'SG05'!K:K)*SG05_+SUMIF('SG06'!$B:$B,$B49,'SG06'!K:K)*SG06_+SUMIF('SG07'!$B:$B,$B49,'SG07'!K:K)*SG07_+SUMIF('SG08'!$B:$B,$B49,'SG08'!K:K)*SG08_+SUMIF('SG09'!$B:$B,$B49,'SG09'!K:K)*SG09_+SUMIF('SG10'!$B:$B,$B49,'SG10'!K:K)*SG10_+SUMIF('SG11'!$B:$B,$B49,'SG11'!K:K)*SG11_+SUMIF('SG12'!$B:$B,$B49,'SG12'!K:K)*SG12_+SUMIF('SG13'!$B:$B,$B49,'SG13'!K:K)*SG13_+SUMIF('SG14'!$B:$B,$B49,'SG14'!K:K)*SG14_+SUMIF('SG15'!$B:$B,$B49,'SG15'!K:K)*SG15_) -> 965639.67 | L49: =(SUMIF('SG01'!$B:$B,$B49,'SG01'!L:L)*SG01_+SUMIF('SG02'!$B:$B,$B49,'SG02'!L:L)*SG02_+SUMIF('SG03'!$B:$B,$B49,'SG03'!L:L)*SG03_+SUMIF('SG04'!$B:$B,$B49,'SG04'!L:L)*SG04_+SUMIF('SG05'!$B:$B,$B49,'SG05'!L:L)*SG05_+SUMIF('SG06'!$B:$B,$B49,'SG06'!L:L)*SG06_+SUMIF('SG07'!$B:$B,$B49,'SG07'!L:L)*SG07_+SUMIF('SG08'!$B:$B,$B49,'SG08'!L:L)*SG08_+SUMIF('SG09'!$B:$B,$B49,'SG09'!L:L)*SG09_+SUMIF('SG10'!$B:$B,$B49,'SG10'!L:L)*SG10_+SUMIF('SG11'!$B:$B,$B49,'SG11'!L:L)*SG11_+SUMIF('SG12'!$B:$B,$B49,'SG12'!L:L)*SG12_+SUMIF('SG13'!$B:$B,$B49,'SG13'!L:L)*SG13_+SUMIF('SG14'!$B:$B,$B49,'SG14'!L:L)*SG14_+SUMIF('SG15'!$B:$B,$B49,'SG15'!L:L)*SG15_) -> 2872000 | M49: =L49-K49 -> 1906360.3 | N49: =K49/L49 -> 0.33622551 | O49: =L49/L$10 -> 0.0018522304 | P49: =M49/M$10 -> 0.001852911 | Q49: =I49/I$10 -> 0.0049838026 | R49: =I49/$K$5*100 -> 2.1662605 | S49: =R49*T$5 -> 6.3643596 | T49: =IFERROR(S49*G49,0) -> 228480.51 | V49: =IF(B49<>"",IFERROR(IF($I49>=$X$10,"High","Low"),""),"") -> Low | W49: =IF(B49<>"",IFERROR(IF($L49>=$X$12,"High","Low"),""),"") -> Low | X49: =IF(B49<>"",IFERROR(IF(AND(V49="high",W49="high"),"Star",IF(AND(V49="low",W49="high"),"Puzzle",(IF(AND(V49="high",W49="low"),"Horse","Dog")))),""),"") -> Dog
A50: 7 | B50: GSNCD026 | C50: =VLOOKUP(B50,'SG02'!$B:$E,2,0) -> Xiên Chẳng Dừng Xốt Tare | E50: =VLOOKUP(B50,'SG01'!$B:$E,4,0) -> Phần | F50: =K50/I50 -> 11384.212 | G50: =L50/I50 -> 29617.647 | H50: =G50-F50 -> 18233.435 | I50: =(SUMIF('SG01'!$B:$B,$B50,'SG01'!I:I)*SG01_+SUMIF('SG02'!$B:$B,$B50,'SG02'!I:I)*SG02_+SUMIF('SG03'!$B:$B,$B50,'SG03'!I:I)*SG03_+SUMIF('SG04'!$B:$B,$B50,'SG04'!I:I)*SG04_+SUMIF('SG05'!$B:$B,$B50,'SG05'!I:I)*SG05_+SUMIF('SG06'!$B:$B,$B50,'SG06'!I:I)*SG06_+SUMIF('SG07'!$B:$B,$B50,'SG07'!I:I)*SG07_+SUMIF('SG08'!$B:$B,$B50,'SG08'!I:I)*SG08_+SUMIF('SG09'!$B:$B,$B50,'SG09'!I:I)*SG09_+SUMIF('SG10'!$B:$B,$B50,'SG10'!I:I)*SG10_+SUMIF('SG11'!$B:$B,$B50,'SG11'!I:I)*SG11_+SUMIF('SG12'!$B:$B,$B50,'SG12'!I:I)*SG12_+SUMIF('SG13'!$B:$B,$B50,'SG13'!I:I)*SG13_+SUMIF('SG14'!$B:$B,$B50,'SG14'!I:I)*SG14_+SUMIF('SG15'!$B:$B,$B50,'SG15'!I:I)*SG15_) -> 68 | K50: =(SUMIF('SG01'!$B:$B,$B50,'SG01'!K:K)*SG01_+SUMIF('SG02'!$B:$B,$B50,'SG02'!K:K)*SG02_+SUMIF('SG03'!$B:$B,$B50,'SG03'!K:K)*SG03_+SUMIF('SG04'!$B:$B,$B50,'SG04'!K:K)*SG04_+SUMIF('SG05'!$B:$B,$B50,'SG05'!K:K)*SG05_+SUMIF('SG06'!$B:$B,$B50,'SG06'!K:K)*SG06_+SUMIF('SG07'!$B:$B,$B50,'SG07'!K:K)*SG07_+SUMIF('SG08'!$B:$B,$B50,'SG08'!K:K)*SG08_+SUMIF('SG09'!$B:$B,$B50,'SG09'!K:K)*SG09_+SUMIF('SG10'!$B:$B,$B50,'SG10'!K:K)*SG10_+SUMIF('SG11'!$B:$B,$B50,'SG11'!K:K)*SG11_+SUMIF('SG12'!$B:$B,$B50,'SG12'!K:K)*SG12_+SUMIF('SG13'!$B:$B,$B50,'SG13'!K:K)*SG13_+SUMIF('SG14'!$B:$B,$B50,'SG14'!K:K)*SG14_+SUMIF('SG15'!$B:$B,$B50,'SG15'!K:K)*SG15_) -> 774126.42 | L50: =(SUMIF('SG01'!$B:$B,$B50,'SG01'!L:L)*SG01_+SUMIF('SG02'!$B:$B,$B50,'SG02'!L:L)*SG02_+SUMIF('SG03'!$B:$B,$B50,'SG03'!L:L)*SG03_+SUMIF('SG04'!$B:$B,$B50,'SG04'!L:L)*SG04_+SUMIF('SG05'!$B:$B,$B50,'SG05'!L:L)*SG05_+SUMIF('SG06'!$B:$B,$B50,'SG06'!L:L)*SG06_+SUMIF('SG07'!$B:$B,$B50,'SG07'!L:L)*SG07_+SUMIF('SG08'!$B:$B,$B50,'SG08'!L:L)*SG08_+SUMIF('SG09'!$B:$B,$B50,'SG09'!L:L)*SG09_+SUMIF('SG10'!$B:$B,$B50,'SG10'!L:L)*SG10_+SUMIF('SG11'!$B:$B,$B50,'SG11'!L:L)*SG11_+SUMIF('SG12'!$B:$B,$B50,'SG12'!L:L)*SG12_+SUMIF('SG13'!$B:$B,$B50,'SG13'!L:L)*SG13_+SUMIF('SG14'!$B:$B,$B50,'SG14'!L:L)*SG14_+SUMIF('SG15'!$B:$B,$B50,'SG15'!L:L)*SG15_) -> 2014000 | M50: =L50-K50 -> 1239873.6 | N50: =K50/L50 -> 0.3843726 | O50: =L50/L$10 -> 0.0012988831 | P50: =M50/M$10 -> 0.0012051108 | Q50: =I50/I$10 -> 0.0042362322 | R50: =I50/$K$5*100 -> 1.8413214 | S50: =R50*T$5 -> 5.4097056 | T50: =IFERROR(S50*G50,0) -> 160222.75 | V50: =IF(B50<>"",IFERROR(IF($I50>=$X$10,"High","Low"),""),"") -> Low | W50: =IF(B50<>"",IFERROR(IF($L50>=$X$12,"High","Low"),""),"") -> Low | X50: =IF(B50<>"",IFERROR(IF(AND(V50="high",W50="high"),"Star",IF(AND(V50="low",W50="high"),"Puzzle",(IF(AND(V50="high",W50="low"),"Horse","Dog")))),""),"") -> Dog
A51: 8 | B51: GSNCD027 | C51: =VLOOKUP(B51,'SG02'!$B:$E,2,0) -> Xiên Chẳng Dừng Xốt Muối | E51: =VLOOKUP(B51,'SG01'!$B:$E,4,0) -> Phần | F51: =K51/I51 -> 11180.544 | G51: =L51/I51 -> 30469.388 | H51: =G51-F51 -> 19288.844 | I51: =(SUMIF('SG01'!$B:$B,$B51,'SG01'!I:I)*SG01_+SUMIF('SG02'!$B:$B,$B51,'SG02'!I:I)*SG02_+SUMIF('SG03'!$B:$B,$B51,'SG03'!I:I)*SG03_+SUMIF('SG04'!$B:$B,$B51,'SG04'!I:I)*SG04_+SUMIF('SG05'!$B:$B,$B51,'SG05'!I:I)*SG05_+SUMIF('SG06'!$B:$B,$B51,'SG06'!I:I)*SG06_+SUMIF('SG07'!$B:$B,$B51,'SG07'!I:I)*SG07_+SUMIF('SG08'!$B:$B,$B51,'SG08'!I:I)*SG08_+SUMIF('SG09'!$B:$B,$B51,'SG09'!I:I)*SG09_+SUMIF('SG10'!$B:$B,$B51,'SG10'!I:I)*SG10_+SUMIF('SG11'!$B:$B,$B51,'SG11'!I:I)*SG11_+SUMIF('SG12'!$B:$B,$B51,'SG12'!I:I)*SG12_+SUMIF('SG13'!$B:$B,$B51,'SG13'!I:I)*SG13_+SUMIF('SG14'!$B:$B,$B51,'SG14'!I:I)*SG14_+SUMIF('SG15'!$B:$B,$B51,'SG15'!I:I)*SG15_) -> 98 | K51: =(SUMIF('SG01'!$B:$B,$B51,'SG01'!K:K)*SG01_+SUMIF('SG02'!$B:$B,$B51,'SG02'!K:K)*SG02_+SUMIF('SG03'!$B:$B,$B51,'SG03'!K:K)*SG03_+SUMIF('SG04'!$B:$B,$B51,'SG04'!K:K)*SG04_+SUMIF('SG05'!$B:$B,$B51,'SG05'!K:K)*SG05_+SUMIF('SG06'!$B:$B,$B51,'SG06'!K:K)*SG06_+SUMIF('SG07'!$B:$B,$B51,'SG07'!K:K)*SG07_+SUMIF('SG08'!$B:$B,$B51,'SG08'!K:K)*SG08_+SUMIF('SG09'!$B:$B,$B51,'SG09'!K:K)*SG09_+SUMIF('SG10'!$B:$B,$B51,'SG10'!K:K)*SG10_+SUMIF('SG11'!$B:$B,$B51,'SG11'!K:K)*SG11_+SUMIF('SG12'!$B:$B,$B51,'SG12'!K:K)*SG12_+SUMIF('SG13'!$B:$B,$B51,'SG13'!K:K)*SG13_+SUMIF('SG14'!$B:$B,$B51,'SG14'!K:K)*SG14_+SUMIF('SG15'!$B:$B,$B51,'SG15'!K:K)*SG15_) -> 1095693.3 | L51: =(SUMIF('SG01'!$B:$B,$B51,'SG01'!L:L)*SG01_+SUMIF('SG02'!$B:$B,$B51,'SG02'!L:L)*SG02_+SUMIF('SG03'!$B:$B,$B51,'SG03'!L:L)*SG03_+SUMIF('SG04'!$B:$B,$B51,'SG04'!L:L)*SG04_+SUMIF('SG05'!$B:$B,$B51,'SG05'!L:L)*SG05_+SUMIF('SG06'!$B:$B,$B51,'SG06'!L:L)*SG06_+SUMIF('SG07'!$B:$B,$B51,'SG07'!L:L)*SG07_+SUMIF('SG08'!$B:$B,$B51,'SG08'!L:L)*SG08_+SUMIF('SG09'!$B:$B,$B51,'SG09'!L:L)*SG09_+SUMIF('SG10'!$B:$B,$B51,'SG10'!L:L)*SG10_+SUMIF('SG11'!$B:$B,$B51,'SG11'!L:L)*SG11_+SUMIF('SG12'!$B:$B,$B51,'SG12'!L:L)*SG12_+SUMIF('SG13'!$B:$B,$B51,'SG13'!L:L)*SG13_+SUMIF('SG14'!$B:$B,$B51,'SG14'!L:L)*SG14_+SUMIF('SG15'!$B:$B,$B51,'SG15'!L:L)*SG15_) -> 2986000 | M51: =L51-K51 -> 1890306.7 | N51: =K51/L51 -> 0.36694351 | O51: =L51/L$10 -> 0.0019257521 | P51: =M51/M$10 -> 0.0018373074 | Q51: =I51/I$10 -> 0.0061051582 | R51: =I51/$K$5*100 -> 2.6536691 | S51: =R51*T$5 -> 7.7963405 | T51: =IFERROR(S51*G51,0) -> 237549.72 | V51: =IF(B51<>"",IFERROR(IF($I51>=$X$10,"High","Low"),""),"") -> Low | W51: =IF(B51<>"",IFERROR(IF($L51>=$X$12,"High","Low"),""),"") -> Low | X51: =IF(B51<>"",IFERROR(IF(AND(V51="high",W51="high"),"Star",IF(AND(V51="low",W51="high"),"Puzzle",(IF(AND(V51="high",W51="low"),"Horse","Dog")))),""),"") -> Dog
A52: 9 | B52: GSNCD028 | C52: =VLOOKUP(B52,'SG02'!$B:$E,2,0) -> Xiên Ba Chỉ Heo Xốt Tare | E52: =VLOOKUP(B52,'SG01'!$B:$E,4,0) -> Phần | F52: =K52/I52 -> 9641.9313 | G52: =L52/I52 -> 30245.283 | H52: =G52-F52 -> 20603.352 | I52: =(SUMIF('SG01'!$B:$B,$B52,'SG01'!I:I)*SG01_+SUMIF('SG02'!$B:$B,$B52,'SG02'!I:I)*SG02_+SUMIF('SG03'!$B:$B,$B52,'SG03'!I:I)*SG03_+SUMIF('SG04'!$B:$B,$B52,'SG04'!I:I)*SG04_+SUMIF('SG05'!$B:$B,$B52,'SG05'!I:I)*SG05_+SUMIF('SG06'!$B:$B,$B52,'SG06'!I:I)*SG06_+SUMIF('SG07'!$B:$B,$B52,'SG07'!I:I)*SG07_+SUMIF('SG08'!$B:$B,$B52,'SG08'!I:I)*SG08_+SUMIF('SG09'!$B:$B,$B52,'SG09'!I:I)*SG09_+SUMIF('SG10'!$B:$B,$B52,'SG10'!I:I)*SG10_+SUMIF('SG11'!$B:$B,$B52,'SG11'!I:I)*SG11_+SUMIF('SG12'!$B:$B,$B52,'SG12'!I:I)*SG12_+SUMIF('SG13'!$B:$B,$B52,'SG13'!I:I)*SG13_+SUMIF('SG14'!$B:$B,$B52,'SG14'!I:I)*SG14_+SUMIF('SG15'!$B:$B,$B52,'SG15'!I:I)*SG15_) -> 106 | K52: =(SUMIF('SG01'!$B:$B,$B52,'SG01'!K:K)*SG01_+SUMIF('SG02'!$B:$B,$B52,'SG02'!K:K)*SG02_+SUMIF('SG03'!$B:$B,$B52,'SG03'!K:K)*SG03_+SUMIF('SG04'!$B:$B,$B52,'SG04'!K:K)*SG04_+SUMIF('SG05'!$B:$B,$B52,'SG05'!K:K)*SG05_+SUMIF('SG06'!$B:$B,$B52,'SG06'!K:K)*SG06_+SUMIF('SG07'!$B:$B,$B52,'SG07'!K:K)*SG07_+SUMIF('SG08'!$B:$B,$B52,'SG08'!K:K)*SG08_+SUMIF('SG09'!$B:$B,$B52,'SG09'!K:K)*SG09_+SUMIF('SG10'!$B:$B,$B52,'SG10'!K:K)*SG10_+SUMIF('SG11'!$B:$B,$B52,'SG11'!K:K)*SG11_+SUMIF('SG12'!$B:$B,$B52,'SG12'!K:K)*SG12_+SUMIF('SG13'!$B:$B,$B52,'SG13'!K:K)*SG13_+SUMIF('SG14'!$B:$B,$B52,'SG14'!K:K)*SG14_+SUMIF('SG15'!$B:$B,$B52,'SG15'!K:K)*SG15_) -> 1022044.7 | L52: =(SUMIF('SG01'!$B:$B,$B52,'SG01'!L:L)*SG01_+SUMIF('SG02'!$B:$B,$B52,'SG02'!L:L)*SG02_+SUMIF('SG03'!$B:$B,$B52,'SG03'!L:L)*SG03_+SUMIF('SG04'!$B:$B,$B52,'SG04'!L:L)*SG04_+SUMIF('SG05'!$B:$B,$B52,'SG05'!L:L)*SG05_+SUMIF('SG06'!$B:$B,$B52,'SG06'!L:L)*SG06_+SUMIF('SG07'!$B:$B,$B52,'SG07'!L:L)*SG07_+SUMIF('SG08'!$B:$B,$B52,'SG08'!L:L)*SG08_+SUMIF('SG09'!$B:$B,$B52,'SG09'!L:L)*SG09_+SUMIF('SG10'!$B:$B,$B52,'SG10'!L:L)*SG10_+SUMIF('SG11'!$B:$B,$B52,'SG11'!L:L)*SG11_+SUMIF('SG12'!$B:$B,$B52,'SG12'!L:L)*SG12_+SUMIF('SG13'!$B:$B,$B52,'SG13'!L:L)*SG13_+SUMIF('SG14'!$B:$B,$B52,'SG14'!L:L)*SG14_+SUMIF('SG15'!$B:$B,$B52,'SG15'!L:L)*SG15_) -> 3206000 | M52: =L52-K52 -> 2183955.3 | N52: =K52/L52 -> 0.31879124 | O52: =L52/L$10 -> 0.0020676361 | P52: =M52/M$10 -> 0.0021227229 | Q52: =I52/I$10 -> 0.0066035385 | R52: =I52/$K$5*100 -> 2.8702952 | S52: =R52*T$5 -> 8.4327765 | T52: =IFERROR(S52*G52,0) -> 255051.71 | V52: =IF(B52<>"",IFERROR(IF($I52>=$X$10,"High","Low"),""),"") -> High | W52: =IF(B52<>"",IFERROR(IF($L52>=$X$12,"High","Low"),""),"") -> High | X52: =IF(B52<>"",IFERROR(IF(AND(V52="high",W52="high"),"Star",IF(AND(V52="low",W52="high"),"Puzzle",(IF(AND(V52="high",W52="low"),"Horse","Dog")))),""),"") -> Star
A53: 10 | B53: GSNCD029 | C53: =VLOOKUP(B53,'SG02'!$B:$E,2,0) -> Xiên Ba Chỉ Heo Xốt Muối | E53: =VLOOKUP(B53,'SG01'!$B:$E,4,0) -> Phần | F53: =K53/I53 -> 9438.2857 | G53: =L53/I53 -> 29913.043 | H53: =G53-F53 -> 20474.758 | I53: =(SUMIF('SG01'!$B:$B,$B53,'SG01'!I:I)*SG01_+SUMIF('SG02'!$B:$B,$B53,'SG02'!I:I)*SG02_+SUMIF('SG03'!$B:$B,$B53,'SG03'!I:I)*SG03_+SUMIF('SG04'!$B:$B,$B53,'SG04'!I:I)*SG04_+SUMIF('SG05'!$B:$B,$B53,'SG05'!I:I)*SG05_+SUMIF('SG06'!$B:$B,$B53,'SG06'!I:I)*SG06_+SUMIF('SG07'!$B:$B,$B53,'SG07'!I:I)*SG07_+SUMIF('SG08'!$B:$B,$B53,'SG08'!I:I)*SG08_+SUMIF('SG09'!$B:$B,$B53,'SG09'!I:I)*SG09_+SUMIF('SG10'!$B:$B,$B53,'SG10'!I:I)*SG10_+SUMIF('SG11'!$B:$B,$B53,'SG11'!I:I)*SG11_+SUMIF('SG12'!$B:$B,$B53,'SG12'!I:I)*SG12_+SUMIF('SG13'!$B:$B,$B53,'SG13'!I:I)*SG13_+SUMIF('SG14'!$B:$B,$B53,'SG14'!I:I)*SG14_+SUMIF('SG15'!$B:$B,$B53,'SG15'!I:I)*SG15_) -> 92 | K53: =(SUMIF('SG01'!$B:$B,$B53,'SG01'!K:K)*SG01_+SUMIF('SG02'!$B:$B,$B53,'SG02'!K:K)*SG02_+SUMIF('SG03'!$B:$B,$B53,'SG03'!K:K)*SG03_+SUMIF('SG04'!$B:$B,$B53,'SG04'!K:K)*SG04_+SUMIF('SG05'!$B:$B,$B53,'SG05'!K:K)*SG05_+SUMIF('SG06'!$B:$B,$B53,'SG06'!K:K)*SG06_+SUMIF('SG07'!$B:$B,$B53,'SG07'!K:K)*SG07_+SUMIF('SG08'!$B:$B,$B53,'SG08'!K:K)*SG08_+SUMIF('SG09'!$B:$B,$B53,'SG09'!K:K)*SG09_+SUMIF('SG10'!$B:$B,$B53,'SG10'!K:K)*SG10_+SUMIF('SG11'!$B:$B,$B53,'SG11'!K:K)*SG11_+SUMIF('SG12'!$B:$B,$B53,'SG12'!K:K)*SG12_+SUMIF('SG13'!$B:$B,$B53,'SG13'!K:K)*SG13_+SUMIF('SG14'!$B:$B,$B53,'SG14'!K:K)*SG14_+SUMIF('SG15'!$B:$B,$B53,'SG15'!K:K)*SG15_) -> 868322.29 | L53: =(SUMIF('SG01'!$B:$B,$B53,'SG01'!L:L)*SG01_+SUMIF('SG02'!$B:$B,$B53,'SG02'!L:L)*SG02_+SUMIF('SG03'!$B:$B,$B53,'SG03'!L:L)*SG03_+SUMIF('SG04'!$B:$B,$B53,'SG04'!L:L)*SG04_+SUMIF('SG05'!$B:$B,$B53,'SG05'!L:L)*SG05_+SUMIF('SG06'!$B:$B,$B53,'SG06'!L:L)*SG06_+SUMIF('SG07'!$B:$B,$B53,'SG07'!L:L)*SG07_+SUMIF('SG08'!$B:$B,$B53,'SG08'!L:L)*SG08_+SUMIF('SG09'!$B:$B,$B53,'SG09'!L:L)*SG09_+SUMIF('SG10'!$B:$B,$B53,'SG10'!L:L)*SG10_+SUMIF('SG11'!$B:$B,$B53,'SG11'!L:L)*SG11_+SUMIF('SG12'!$B:$B,$B53,'SG12'!L:L)*SG12_+SUMIF('SG13'!$B:$B,$B53,'SG13'!L:L)*SG13_+SUMIF('SG14'!$B:$B,$B53,'SG14'!L:L)*SG14_+SUMIF('SG15'!$B:$B,$B53,'SG15'!L:L)*SG15_) -> 2752000 | M53: =L53-K53 -> 1883677.7 | N53: =K53/L53 -> 0.31552409 | O53: =L53/L$10 -> 0.0017748392 | P53: =M53/M$10 -> 0.0018308643 | Q53: =I53/I$10 -> 0.005731373 | R53: =I53/$K$5*100 -> 2.4911996 | S53: =R53*T$5 -> 7.3190135 | T53: =IFERROR(S53*G53,0) -> 218933.97 | V53: =IF(B53<>"",IFERROR(IF($I53>=$X$10,"High","Low"),""),"") -> Low | W53: =IF(B53<>"",IFERROR(IF($L53>=$X$12,"High","Low"),""),"") -> Low | X53: =IF(B53<>"",IFERROR(IF(AND(V53="high",W53="high"),"Star",IF(AND(V53="low",W53="high"),"Puzzle",(IF(AND(V53="high",W53="low"),"Horse","Dog")))),""),"") -> Dog
A54: 11 | B54: GSNCD030 | C54: =VLOOKUP(B54,'SG02'!$B:$E,2,0) -> Xiên Bò Viên Xốt Tare | E54: =VLOOKUP(B54,'SG01'!$B:$E,4,0) -> Phần | F54: =K54/I54 -> 11350.205 | G54: =L54/I54 -> 39654.545 | H54: =G54-F54 -> 28304.34 | I54: =(SUMIF('SG01'!$B:$B,$B54,'SG01'!I:I)*SG01_+SUMIF('SG02'!$B:$B,$B54,'SG02'!I:I)*SG02_+SUMIF('SG03'!$B:$B,$B54,'SG03'!I:I)*SG03_+SUMIF('SG04'!$B:$B,$B54,'SG04'!I:I)*SG04_+SUMIF('SG05'!$B:$B,$B54,'SG05'!I:I)*SG05_+SUMIF('SG06'!$B:$B,$B54,'SG06'!I:I)*SG06_+SUMIF('SG07'!$B:$B,$B54,'SG07'!I:I)*SG07_+SUMIF('SG08'!$B:$B,$B54,'SG08'!I:I)*SG08_+SUMIF('SG09'!$B:$B,$B54,'SG09'!I:I)*SG09_+SUMIF('SG10'!$B:$B,$B54,'SG10'!I:I)*SG10_+SUMIF('SG11'!$B:$B,$B54,'SG11'!I:I)*SG11_+SUMIF('SG12'!$B:$B,$B54,'SG12'!I:I)*SG12_+SUMIF('SG13'!$B:$B,$B54,'SG13'!I:I)*SG13_+SUMIF('SG14'!$B:$B,$B54,'SG14'!I:I)*SG14_+SUMIF('SG15'!$B:$B,$B54,'SG15'!I:I)*SG15_) -> 55 | K54: =(SUMIF('SG01'!$B:$B,$B54,'SG01'!K:K)*SG01_+SUMIF('SG02'!$B:$B,$B54,'SG02'!K:K)*SG02_+SUMIF('SG03'!$B:$B,$B54,'SG03'!K:K)*SG03_+SUMIF('SG04'!$B:$B,$B54,'SG04'!K:K)*SG04_+SUMIF('SG05'!$B:$B,$B54,'SG05'!K:K)*SG05_+SUMIF('SG06'!$B:$B,$B54,'SG06'!K:K)*SG06_+SUMIF('SG07'!$B:$B,$B54,'SG07'!K:K)*SG07_+SUMIF('SG08'!$B:$B,$B54,'SG08'!K:K)*SG08_+SUMIF('SG09'!$B:$B,$B54,'SG09'!K:K)*SG09_+SUMIF('SG10'!$B:$B,$B54,'SG10'!K:K)*SG10_+SUMIF('SG11'!$B:$B,$B54,'SG11'!K:K)*SG11_+SUMIF('SG12'!$B:$B,$B54,'SG12'!K:K)*SG12_+SUMIF('SG13'!$B:$B,$B54,'SG13'!K:K)*SG13_+SUMIF('SG14'!$B:$B,$B54,'SG14'!K:K)*SG14_+SUMIF('SG15'!$B:$B,$B54,'SG15'!K:K)*SG15_) -> 624261.3 | L54: =(SUMIF('SG01'!$B:$B,$B54,'SG01'!L:L)*SG01_+SUMIF('SG02'!$B:$B,$B54,'SG02'!L:L)*SG02_+SUMIF('SG03'!$B:$B,$B54,'SG03'!L:L)*SG03_+SUMIF('SG04'!$B:$B,$B54,'SG04'!L:L)*SG04_+SUMIF('SG05'!$B:$B,$B54,'SG05'!L:L)*SG05_+SUMIF('SG06'!$B:$B,$B54,'SG06'!L:L)*SG06_+SUMIF('SG07'!$B:$B,$B54,'SG07'!L:L)*SG07_+SUMIF('SG08'!$B:$B,$B54,'SG08'!L:L)*SG08_+SUMIF('SG09'!$B:$B,$B54,'SG09'!L:L)*SG09_+SUMIF('SG10'!$B:$B,$B54,'SG10'!L:L)*SG10_+SUMIF('SG11'!$B:$B,$B54,'SG11'!L:L)*SG11_+SUMIF('SG12'!$B:$B,$B54,'SG12'!L:L)*SG12_+SUMIF('SG13'!$B:$B,$B54,'SG13'!L:L)*SG13_+SUMIF('SG14'!$B:$B,$B54,'SG14'!L:L)*SG14_+SUMIF('SG15'!$B:$B,$B54,'SG15'!L:L)*SG15_) -> 2181000 | M54: =L54-K54 -> 1556738.7 | N54: =K54/L54 -> 0.2862271 | O54: =L54/L$10 -> 0.0014065859 | P54: =M54/M$10 -> 0.0015130918 | Q54: =I54/I$10 -> 0.0034263643 | R54: =I54/$K$5*100 -> 1.4893041 | S54: =R54*T$5 -> 4.3754972 | T54: =IFERROR(S54*G54,0) -> 173508.35 | V54: =IF(B54<>"",IFERROR(IF($I54>=$X$10,"High","Low"),""),"") -> Low | W54: =IF(B54<>"",IFERROR(IF($L54>=$X$12,"High","Low"),""),"") -> Low | X54: =IF(B54<>"",IFERROR(IF(AND(V54="high",W54="high"),"Star",IF(AND(V54="low",W54="high"),"Puzzle",(IF(AND(V54="high",W54="low"),"Horse","Dog")))),""),"") -> Dog
A55: 12 | B55: GSNCD031 | C55: =VLOOKUP(B55,'SG02'!$B:$E,2,0) -> Xiên Bò Viên Xốt Muối | E55: =VLOOKUP(B55,'SG01'!$B:$E,4,0) -> Phần | F55: =K55/I55 -> 10284.224 | G55: =L55/I55 -> 39972.973 | H55: =G55-F55 -> 29688.749 | I55: =(SUMIF('SG01'!$B:$B,$B55,'SG01'!I:I)*SG01_+SUMIF('SG02'!$B:$B,$B55,'SG02'!I:I)*SG02_+SUMIF('SG03'!$B:$B,$B55,'SG03'!I:I)*SG03_+SUMIF('SG04'!$B:$B,$B55,'SG04'!I:I)*SG04_+SUMIF('SG05'!$B:$B,$B55,'SG05'!I:I)*SG05_+SUMIF('SG06'!$B:$B,$B55,'SG06'!I:I)*SG06_+SUMIF('SG07'!$B:$B,$B55,'SG07'!I:I)*SG07_+SUMIF('SG08'!$B:$B,$B55,'SG08'!I:I)*SG08_+SUMIF('SG09'!$B:$B,$B55,'SG09'!I:I)*SG09_+SUMIF('SG10'!$B:$B,$B55,'SG10'!I:I)*SG10_+SUMIF('SG11'!$B:$B,$B55,'SG11'!I:I)*SG11_+SUMIF('SG12'!$B:$B,$B55,'SG12'!I:I)*SG12_+SUMIF('SG13'!$B:$B,$B55,'SG13'!I:I)*SG13_+SUMIF('SG14'!$B:$B,$B55,'SG14'!I:I)*SG14_+SUMIF('SG15'!$B:$B,$B55,'SG15'!I:I)*SG15_) -> 37 | K55: =(SUMIF('SG01'!$B:$B,$B55,'SG01'!K:K)*SG01_+SUMIF('SG02'!$B:$B,$B55,'SG02'!K:K)*SG02_+SUMIF('SG03'!$B:$B,$B55,'SG03'!K:K)*SG03_+SUMIF('SG04'!$B:$B,$B55,'SG04'!K:K)*SG04_+SUMIF('SG05'!$B:$B,$B55,'SG05'!K:K)*SG05_+SUMIF('SG06'!$B:$B,$B55,'SG06'!K:K)*SG06_+SUMIF('SG07'!$B:$B,$B55,'SG07'!K:K)*SG07_+SUMIF('SG08'!$B:$B,$B55,'SG08'!K:K)*SG08_+SUMIF('SG09'!$B:$B,$B55,'SG09'!K:K)*SG09_+SUMIF('SG10'!$B:$B,$B55,'SG10'!K:K)*SG10_+SUMIF('SG11'!$B:$B,$B55,'SG11'!K:K)*SG11_+SUMIF('SG12'!$B:$B,$B55,'SG12'!K:K)*SG12_+SUMIF('SG13'!$B:$B,$B55,'SG13'!K:K)*SG13_+SUMIF('SG14'!$B:$B,$B55,'SG14'!K:K)*SG14_+SUMIF('SG15'!$B:$B,$B55,'SG15'!K:K)*SG15_) -> 380516.28 | L55: =(SUMIF('SG01'!$B:$B,$B55,'SG01'!L:L)*SG01_+SUMIF('SG02'!$B:$B,$B55,'SG02'!L:L)*SG02_+SUMIF('SG03'!$B:$B,$B55,'SG03'!L:L)*SG03_+SUMIF('SG04'!$B:$B,$B55,'SG04'!L:L)*SG04_+SUMIF('SG05'!$B:$B,$B55,'SG05'!L:L)*SG05_+SUMIF('SG06'!$B:$B,$B55,'SG06'!L:L)*SG06_+SUMIF('SG07'!$B:$B,$B55,'SG07'!L:L)*SG07_+SUMIF('SG08'!$B:$B,$B55,'SG08'!L:L)*SG08_+SUMIF('SG09'!$B:$B,$B55,'SG09'!L:L)*SG09_+SUMIF('SG10'!$B:$B,$B55,'SG10'!L:L)*SG10_+SUMIF('SG11'!$B:$B,$B55,'SG11'!L:L)*SG11_+SUMIF('SG12'!$B:$B,$B55,'SG12'!L:L)*SG12_+SUMIF('SG13'!$B:$B,$B55,'SG13'!L:L)*SG13_+SUMIF('SG14'!$B:$B,$B55,'SG14'!L:L)*SG14_+SUMIF('SG15'!$B:$B,$B55,'SG15'!L:L)*SG15_) -> 1479000 | M55: =L55-K55 -> 1098483.7 | N55: =K55/L55 -> 0.25727943 | O55: =L55/L$10 -> 0.00095384709 | P55: =M55/M$10 -> 0.0010676851 | Q55: =I55/I$10 -> 0.0023050087 | R55: =I55/$K$5*100 -> 1.0018955 | S55: =R55*T$5 -> 2.9435163 | T55: =IFERROR(S55*G55,0) -> 117661.1 | V55: =IF(B55<>"",IFERROR(IF($I55>=$X$10,"High","Low"),""),"") -> Low | W55: =IF(B55<>"",IFERROR(IF($L55>=$X$12,"High","Low"),""),"") -> Low | X55: =IF(B55<>"",IFERROR(IF(AND(V55="high",W55="high"),"Star",IF(AND(V55="low",W55="high"),"Puzzle",(IF(AND(V55="high",W55="low"),"Horse","Dog")))),""),"") -> Dog
... A63: 20 | B63: GSNCD039 | C63: =VLOOKUP(B63,'SG02'!$B:$E,2,0) -> Xiên Tim Gà Xốt Muối | E63: =VLOOKUP(B63,'SG01'!$B:$E,4,0) -> Phần | F63: =K63/I63 -> 5774.3478 | G63: =L63/I63 -> 25304.348 | H63: =G63-F63 -> 19530 | I63: =(SUMIF('SG01'!$B:$B,$B63,'SG01'!I:I)*SG01_+SUMIF('SG02'!$B:$B,$B63,'SG02'!I:I)*SG02_+SUMIF('SG03'!$B:$B,$B63,'SG03'!I:I)*SG03_+SUMIF('SG04'!$B:$B,$B63,'SG04'!I:I)*SG04_+SUMIF('SG05'!$B:$B,$B63,'SG05'!I:I)*SG05_+SUMIF('SG06'!$B:$B,$B63,'SG06'!I:I)*SG06_+SUMIF('SG07'!$B:$B,$B63,'SG07'!I:I)*SG07_+SUMIF('SG08'!$B:$B,$B63,'SG08'!I:I)*SG08_+SUMIF('SG09'!$B:$B,$B63,'SG09'!I:I)*SG09_+SUMIF('SG10'!$B:$B,$B63,'SG10'!I:I)*SG10_+SUMIF('SG11'!$B:$B,$B63,'SG11'!I:I)*SG11_+SUMIF('SG12'!$B:$B,$B63,'SG12'!I:I)*SG12_+SUMIF('SG13'!$B:$B,$B63,'SG13'!I:I)*SG13_+SUMIF('SG14'!$B:$B,$B63,'SG14'!I:I)*SG14_+SUMIF('SG15'!$B:$B,$B63,'SG15'!I:I)*SG15_) -> 46 | K63: =(SUMIF('SG01'!$B:$B,$B63,'SG01'!K:K)*SG01_+SUMIF('SG02'!$B:$B,$B63,'SG02'!K:K)*SG02_+SUMIF('SG03'!$B:$B,$B63,'SG03'!K:K)*SG03_+SUMIF('SG04'!$B:$B,$B63,'SG04'!K:K)*SG04_+SUMIF('SG05'!$B:$B,$B63,'SG05'!K:K)*SG05_+SUMIF('SG06'!$B:$B,$B63,'SG06'!K:K)*SG06_+SUMIF('SG07'!$B:$B,$B63,'SG07'!K:K)*SG07_+SUMIF('SG08'!$B:$B,$B63,'SG08'!K:K)*SG08_+SUMIF('SG09'!$B:$B,$B63,'SG09'!K:K)*SG09_+SUMIF('SG10'!$B:$B,$B63,'SG10'!K:K)*SG10_+SUMIF('SG11'!$B:$B,$B63,'SG11'!K:K)*SG11_+SUMIF('SG12'!$B:$B,$B63,'SG12'!K:K)*SG12_+SUMIF('SG13'!$B:$B,$B63,'SG13'!K:K)*SG13_+SUMIF('SG14'!$B:$B,$B63,'SG14'!K:K)*SG14_+SUMIF('SG15'!$B:$B,$B63,'SG15'!K:K)*SG15_) -> 265620 | L63: =(SUMIF('SG01'!$B:$B,$B63,'SG01'!L:L)*SG01_+SUMIF('SG02'!$B:$B,$B63,'SG02'!L:L)*SG02_+SUMIF('SG03'!$B:$B,$B63,'SG03'!L:L)*SG03_+SUMIF('SG04'!$B:$B,$B63,'SG04'!L:L)*SG04_+SUMIF('SG05'!$B:$B,$B63,'SG05'!L:L)*SG05_+SUMIF('SG06'!$B:$B,$B63,'SG06'!L:L)*SG06_+SUMIF('SG07'!$B:$B,$B63,'SG07'!L:L)*SG07_+SUMIF('SG08'!$B:$B,$B63,'SG08'!L:L)*SG08_+SUMIF('SG09'!$B:$B,$B63,'SG09'!L:L)*SG09_+SUMIF('SG10'!$B:$B,$B63,'SG10'!L:L)*SG10_+SUMIF('SG11'!$B:$B,$B63,'SG11'!L:L)*SG11_+SUMIF('SG12'!$B:$B,$B63,'SG12'!L:L)*SG12_+SUMIF('SG13'!$B:$B,$B63,'SG13'!L:L)*SG13_+SUMIF('SG14'!$B:$B,$B63,'SG14'!L:L)*SG14_+SUMIF('SG15'!$B:$B,$B63,'SG15'!L:L)*SG15_) -> 1164000 | M63: =L63-K63 -> 898380 | N63: =K63/L63 -> 0.22819588 | O63: =L63/L$10 -> 0.00075069507 | P63: =M63/M$10 -> 0.00087319177 | Q63: =I63/I$10 -> 0.0028656865 | R63: =I63/$K$5*100 -> 1.2455998 | S63: =R63*T$5 -> 3.6595068 | T63: =IFERROR(S63*G63,0) -> 92601.432 | V63: =IF(B63<>"",IFERROR(IF($I63>=$X$10,"High","Low"),""),"") -> Low | W63: =IF(B63<>"",IFERROR(IF($L63>=$X$12,"High","Low"),""),"") -> Low | X63: =IF(B63<>"",IFERROR(IF(AND(V63="high",W63="high"),"Star",IF(AND(V63="low",W63="high"),"Puzzle",(IF(AND(V63="high",W63="low"),"Horse","Dog")))),""),"") -> Dog
A64: 21 | B64: GSNCD041 | C64: Xiên Trứng Cút Xốt Muối | E64: =VLOOKUP(B64,'SG01'!$B:$E,4,0) -> Phần | F64: =K64/I64 -> 3912.0617 | G64: =L64/I64 -> 29769.231 | H64: =G64-F64 -> 25857.169 | I64: =(SUMIF('SG01'!$B:$B,$B64,'SG01'!I:I)*SG01_+SUMIF('SG02'!$B:$B,$B64,'SG02'!I:I)*SG02_+SUMIF('SG03'!$B:$B,$B64,'SG03'!I:I)*SG03_+SUMIF('SG04'!$B:$B,$B64,'SG04'!I:I)*SG04_+SUMIF('SG05'!$B:$B,$B64,'SG05'!I:I)*SG05_+SUMIF('SG06'!$B:$B,$B64,'SG06'!I:I)*SG06_+SUMIF('SG07'!$B:$B,$B64,'SG07'!I:I)*SG07_+SUMIF('SG08'!$B:$B,$B64,'SG08'!I:I)*SG08_+SUMIF('SG09'!$B:$B,$B64,'SG09'!I:I)*SG09_+SUMIF('SG10'!$B:$B,$B64,'SG10'!I:I)*SG10_+SUMIF('SG11'!$B:$B,$B64,'SG11'!I:I)*SG11_+SUMIF('SG12'!$B:$B,$B64,'SG12'!I:I)*SG12_+SUMIF('SG13'!$B:$B,$B64,'SG13'!I:I)*SG13_+SUMIF('SG14'!$B:$B,$B64,'SG14'!I:I)*SG14_+SUMIF('SG15'!$B:$B,$B64,'SG15'!I:I)*SG15_) -> 39 | K64: =(SUMIF('SG01'!$B:$B,$B64,'SG01'!K:K)*SG01_+SUMIF('SG02'!$B:$B,$B64,'SG02'!K:K)*SG02_+SUMIF('SG03'!$B:$B,$B64,'SG03'!K:K)*SG03_+SUMIF('SG04'!$B:$B,$B64,'SG04'!K:K)*SG04_+SUMIF('SG05'!$B:$B,$B64,'SG05'!K:K)*SG05_+SUMIF('SG06'!$B:$B,$B64,'SG06'!K:K)*SG06_+SUMIF('SG07'!$B:$B,$B64,'SG07'!K:K)*SG07_+SUMIF('SG08'!$B:$B,$B64,'SG08'!K:K)*SG08_+SUMIF('SG09'!$B:$B,$B64,'SG09'!K:K)*SG09_+SUMIF('SG10'!$B:$B,$B64,'SG10'!K:K)*SG10_+SUMIF('SG11'!$B:$B,$B64,'SG11'!K:K)*SG11_+SUMIF('SG12'!$B:$B,$B64,'SG12'!K:K)*SG12_+SUMIF('SG13'!$B:$B,$B64,'SG13'!K:K)*SG13_+SUMIF('SG14'!$B:$B,$B64,'SG14'!K:K)*SG14_+SUMIF('SG15'!$B:$B,$B64,'SG15'!K:K)*SG15_) -> 152570.41 | L64: =(SUMIF('SG01'!$B:$B,$B64,'SG01'!L:L)*SG01_+SUMIF('SG02'!$B:$B,$B64,'SG02'!L:L)*SG02_+SUMIF('SG03'!$B:$B,$B64,'SG03'!L:L)*SG03_+SUMIF('SG04'!$B:$B,$B64,'SG04'!L:L)*SG04_+SUMIF('SG05'!$B:$B,$B64,'SG05'!L:L)*SG05_+SUMIF('SG06'!$B:$B,$B64,'SG06'!L:L)*SG06_+SUMIF('SG07'!$B:$B,$B64,'SG07'!L:L)*SG07_+SUMIF('SG08'!$B:$B,$B64,'SG08'!L:L)*SG08_+SUMIF('SG09'!$B:$B,$B64,'SG09'!L:L)*SG09_+SUMIF('SG10'!$B:$B,$B64,'SG10'!L:L)*SG10_+SUMIF('SG11'!$B:$B,$B64,'SG11'!L:L)*SG11_+SUMIF('SG12'!$B:$B,$B64,'SG12'!L:L)*SG12_+SUMIF('SG13'!$B:$B,$B64,'SG13'!L:L)*SG13_+SUMIF('SG14'!$B:$B,$B64,'SG14'!L:L)*SG14_+SUMIF('SG15'!$B:$B,$B64,'SG15'!L:L)*SG15_) -> 1161000 | M64: =L64-K64 -> 1008429.6 | N64: =K64/L64 -> 0.13141293 | O64: =L64/L$10 -> 0.00074876029 | P64: =M64/M$10 -> 0.00098015586 | Q64: =I64/I$10 -> 0.0024296038 | R64: =I64/$K$5*100 -> 1.056052 | S64: =R64*T$5 -> 3.1026253 | T64: =IFERROR(S64*G64,0) -> 92362.768 | V64: =IF(B64<>"",IFERROR(IF($I64>=$X$10,"High","Low"),""),"") -> Low | W64: =IF(B64<>"",IFERROR(IF($L64>=$X$12,"High","Low"),""),"") -> Low | X64: =IF(B64<>"",IFERROR(IF(AND(V64="high",W64="high"),"Star",IF(AND(V64="low",W64="high"),"Puzzle",(IF(AND(V64="high",W64="low"),"Horse","Dog")))),""),"") -> Dog
A65: 22 | B65: GSNCD042 | C65: =VLOOKUP(B65,'SG02'!$B:$E,2,0) -> Xiên Cá Hồi | E65: =VLOOKUP(B65,'SG01'!$B:$E,4,0) -> Phần | F65: =K65/I65 -> 13870.606 | G65: =L65/I65 -> 85857.143 | H65: =G65-F65 -> 71986.537 | I65: =(SUMIF('SG01'!$B:$B,$B65,'SG01'!I:I)*SG01_+SUMIF('SG02'!$B:$B,$B65,'SG02'!I:I)*SG02_+SUMIF('SG03'!$B:$B,$B65,'SG03'!I:I)*SG03_+SUMIF('SG04'!$B:$B,$B65,'SG04'!I:I)*SG04_+SUMIF('SG05'!$B:$B,$B65,'SG05'!I:I)*SG05_+SUMIF('SG06'!$B:$B,$B65,'SG06'!I:I)*SG06_+SUMIF('SG07'!$B:$B,$B65,'SG07'!I:I)*SG07_+SUMIF('SG08'!$B:$B,$B65,'SG08'!I:I)*SG08_+SUMIF('SG09'!$B:$B,$B65,'SG09'!I:I)*SG09_+SUMIF('SG10'!$B:$B,$B65,'SG10'!I:I)*SG10_+SUMIF('SG11'!$B:$B,$B65,'SG11'!I:I)*SG11_+SUMIF('SG12'!$B:$B,$B65,'SG12'!I:I)*SG12_+SUMIF('SG13'!$B:$B,$B65,'SG13'!I:I)*SG13_+SUMIF('SG14'!$B:$B,$B65,'SG14'!I:I)*SG14_+SUMIF('SG15'!$B:$B,$B65,'SG15'!I:I)*SG15_) -> 35 | K65: =(SUMIF('SG01'!$B:$B,$B65,'SG01'!K:K)*SG01_+SUMIF('SG02'!$B:$B,$B65,'SG02'!K:K)*SG02_+SUMIF('SG03'!$B:$B,$B65,'SG03'!K:K)*SG03_+SUMIF('SG04'!$B:$B,$B65,'SG04'!K:K)*SG04_+SUMIF('SG05'!$B:$B,$B65,'SG05'!K:K)*SG05_+SUMIF('SG06'!$B:$B,$B65,'SG06'!K:K)*SG06_+SUMIF('SG07'!$B:$B,$B65,'SG07'!K:K)*SG07_+SUMIF('SG08'!$B:$B,$B65,'SG08'!K:K)*SG08_+SUMIF('SG09'!$B:$B,$B65,'SG09'!K:K)*SG09_+SUMIF('SG10'!$B:$B,$B65,'SG10'!K:K)*SG10_+SUMIF('SG11'!$B:$B,$B65,'SG11'!K:K)*SG11_+SUMIF('SG12'!$B:$B,$B65,'SG12'!K:K)*SG12_+SUMIF('SG13'!$B:$B,$B65,'SG13'!K:K)*SG13_+SUMIF('SG14'!$B:$B,$B65,'SG14'!K:K)*SG14_+SUMIF('SG15'!$B:$B,$B65,'SG15'!K:K)*SG15_) -> 485471.21 | L65: =(SUMIF('SG01'!$B:$B,$B65,'SG01'!L:L)*SG01_+SUMIF('SG02'!$B:$B,$B65,'SG02'!L:L)*SG02_+SUMIF('SG03'!$B:$B,$B65,'SG03'!L:L)*SG03_+SUMIF('SG04'!$B:$B,$B65,'SG04'!L:L)*SG04_+SUMIF('SG05'!$B:$B,$B65,'SG05'!L:L)*SG05_+SUMIF('SG06'!$B:$B,$B65,'SG06'!L:L)*SG06_+SUMIF('SG07'!$B:$B,$B65,'SG07'!L:L)*SG07_+SUMIF('SG08'!$B:$B,$B65,'SG08'!L:L)*SG08_+SUMIF('SG09'!$B:$B,$B65,'SG09'!L:L)*SG09_+SUMIF('SG10'!$B:$B,$B65,'SG10'!L:L)*SG10_+SUMIF('SG11'!$B:$B,$B65,'SG11'!L:L)*SG11_+SUMIF('SG12'!$B:$B,$B65,'SG12'!L:L)*SG12_+SUMIF('SG13'!$B:$B,$B65,'SG13'!L:L)*SG13_+SUMIF('SG14'!$B:$B,$B65,'SG14'!L:L)*SG14_+SUMIF('SG15'!$B:$B,$B65,'SG15'!L:L)*SG15_) -> 3005000 | M65: =L65-K65 -> 2519528.8 | N65: =K65/L65 -> 0.16155448 | O65: =L65/L$10 -> 0.0019380057 | P65: =M65/M$10 -> 0.0024488878 | Q65: =I65/I$10 -> 0.0021804137 | R65: =I65/$K$5*100 -> 0.94773897 | S65: =R65*T$5 -> 2.7844073 | T65: =IFERROR(S65*G65,0) -> 239061.26 | V65: =IF(B65<>"",IFERROR(IF($I65>=$X$10,"High","Low"),""),"") -> Low | W65: =IF(B65<>"",IFERROR(IF($L65>=$X$12,"High","Low"),""),"") -> High | X65: =IF(B65<>"",IFERROR(IF(AND(V65="high",W65="high"),"Star",IF(AND(V65="low",W65="high"),"Puzzle",(IF(AND(V65="high",W65="low"),"Horse","Dog")))),""),"") -> Puzzle
A66: 23 | B66: GSNCD043 | C66: =VLOOKUP(B66,'SG02'!$B:$E,2,0) -> Cá Thu Đao Nướng Muối | E66: =VLOOKUP(B66,'SG01'!$B:$E,4,0) -> Phần | F66: =K66/I66 -> 14359.821 | G66: =L66/I66 -> 80764.706 | H66: =G66-F66 -> 66404.885 | I66: =(SUMIF('SG01'!$B:$B,$B66,'SG01'!I:I)*SG01_+SUMIF('SG02'!$B:$B,$B66,'SG02'!I:I)*SG02_+SUMIF('SG03'!$B:$B,$B66,'SG03'!I:I)*SG03_+SUMIF('SG04'!$B:$B,$B66,'SG04'!I:I)*SG04_+SUMIF('SG05'!$B:$B,$B66,'SG05'!I:I)*SG05_+SUMIF('SG06'!$B:$B,$B66,'SG06'!I:I)*SG06_+SUMIF('SG07'!$B:$B,$B66,'SG07'!I:I)*SG07_+SUMIF('SG08'!$B:$B,$B66,'SG08'!I:I)*SG08_+SUMIF('SG09'!$B:$B,$B66,'SG09'!I:I)*SG09_+SUMIF('SG10'!$B:$B,$B66,'SG10'!I:I)*SG10_+SUMIF('SG11'!$B:$B,$B66,'SG11'!I:I)*SG11_+SUMIF('SG12'!$B:$B,$B66,'SG12'!I:I)*SG12_+SUMIF('SG13'!$B:$B,$B66,'SG13'!I:I)*SG13_+SUMIF('SG14'!$B:$B,$B66,'SG14'!I:I)*SG14_+SUMIF('SG15'!$B:$B,$B66,'SG15'!I:I)*SG15_) -> 102 | K66: =(SUMIF('SG01'!$B:$B,$B66,'SG01'!K:K)*SG01_+SUMIF('SG02'!$B:$B,$B66,'SG02'!K:K)*SG02_+SUMIF('SG03'!$B:$B,$B66,'SG03'!K:K)*SG03_+SUMIF('SG04'!$B:$B,$B66,'SG04'!K:K)*SG04_+SUMIF('SG05'!$B:$B,$B66,'SG05'!K:K)*SG05_+SUMIF('SG06'!$B:$B,$B66,'SG06'!K:K)*SG06_+SUMIF('SG07'!$B:$B,$B66,'SG07'!K:K)*SG07_+SUMIF('SG08'!$B:$B,$B66,'SG08'!K:K)*SG08_+SUMIF('SG09'!$B:$B,$B66,'SG09'!K:K)*SG09_+SUMIF('SG10'!$B:$B,$B66,'SG10'!K:K)*SG10_+SUMIF('SG11'!$B:$B,$B66,'SG11'!K:K)*SG11_+SUMIF('SG12'!$B:$B,$B66,'SG12'!K:K)*SG12_+SUMIF('SG13'!$B:$B,$B66,'SG13'!K:K)*SG13_+SUMIF('SG14'!$B:$B,$B66,'SG14'!K:K)*SG14_+SUMIF('SG15'!$B:$B,$B66,'SG15'!K:K)*SG15_) -> 1464701.7 | L66: =(SUMIF('SG01'!$B:$B,$B66,'SG01'!L:L)*SG01_+SUMIF('SG02'!$B:$B,$B66,'SG02'!L:L)*SG02_+SUMIF('SG03'!$B:$B,$B66,'SG03'!L:L)*SG03_+SUMIF('SG04'!$B:$B,$B66,'SG04'!L:L)*SG04_+SUMIF('SG05'!$B:$B,$B66,'SG05'!L:L)*SG05_+SUMIF('SG06'!$B:$B,$B66,'SG06'!L:L)*SG06_+SUMIF('SG07'!$B:$B,$B66,'SG07'!L:L)*SG07_+SUMIF('SG08'!$B:$B,$B66,'SG08'!L:L)*SG08_+SUMIF('SG09'!$B:$B,$B66,'SG09'!L:L)*SG09_+SUMIF('SG10'!$B:$B,$B66,'SG10'!L:L)*SG10_+SUMIF('SG11'!$B:$B,$B66,'SG11'!L:L)*SG11_+SUMIF('SG12'!$B:$B,$B66,'SG12'!L:L)*SG12_+SUMIF('SG13'!$B:$B,$B66,'SG13'!L:L)*SG13_+SUMIF('SG14'!$B:$B,$B66,'SG14'!L:L)*SG14_+SUMIF('SG15'!$B:$B,$B66,'SG15'!L:L)*SG15_) -> 8238000 | M66: =L66-K66 -> 6773298.3 | N66: =K66/L66 -> 0.17779822 | O66: =L66/L$10 -> 0.0053129089 | P66: =M66/M$10 -> 0.0065833927 | Q66: =I66/I$10 -> 0.0063543484 | R66: =I66/$K$5*100 -> 2.7619821 | S66: =R66*T$5 -> 8.1145585 | T66: =IFERROR(S66*G66,0) -> 655369.93 | V66: =IF(B66<>"",IFERROR(IF($I66>=$X$10,"High","Low"),""),"") -> High | W66: =IF(B66<>"",IFERROR(IF($L66>=$X$12,"High","Low"),""),"") -> High | X66: =IF(B66<>"",IFERROR(IF(AND(V66="high",W66="high"),"Star",IF(AND(V66="low",W66="high"),"Puzzle",(IF(AND(V66="high",W66="low"),"Horse","Dog")))),""),"") -> Star
S67: =R67*T$5 -> 0 | T67: =IFERROR(S67*G67,0) -> 0
B68: THITBO.GSG | C68: THỊT BÒ | I68: =SUBTOTAL(9,I69:I83) -> 1717 | K68: =SUBTOTAL(9,K69:K83) -> 1.1454154e+08 | L68: =SUBTOTAL(9,L69:L83) -> 346497000 | M68: =SUBTOTAL(9,M69:M83) -> 2.3195546e+08 | N68: =K68/L68 -> 0.33057008 | O68: =L68/L$10 -> 0.22346528 | P68: =M68/M$10 -> 0.22545203 | Q68: =I68/I$10 -> 0.10696486 | R68: =I68/$K$5*100 -> 46.493366 | S68: =R68*T$5 -> 136.59507 | T68: =IFERROR(S68*G68,0) -> 0
A69: 1 | B69: GSTBO001 | C69: =VLOOKUP(B69,'SG01'!$B:$E,2,0) -> Sườn Bò Wagyu Nhật A4 | E69: =VLOOKUP(B69,'SG01'!$B:$E,4,0) -> Phần | F69: =K69/I69 -> 172221.15 | G69: =L69/I69 -> 511796.12 | H69: =G69-F69 -> 339574.97 | I69: =(SUMIF('SG01'!$B:$B,$B69,'SG01'!I:I)*SG01_+SUMIF('SG02'!$B:$B,$B69,'SG02'!I:I)*SG02_+SUMIF('SG03'!$B:$B,$B69,'SG03'!I:I)*SG03_+SUMIF('SG04'!$B:$B,$B69,'SG04'!I:I)*SG04_+SUMIF('SG05'!$B:$B,$B69,'SG05'!I:I)*SG05_+SUMIF('SG06'!$B:$B,$B69,'SG06'!I:I)*SG06_+SUMIF('SG07'!$B:$B,$B69,'SG07'!I:I)*SG07_+SUMIF('SG08'!$B:$B,$B69,'SG08'!I:I)*SG08_+SUMIF('SG09'!$B:$B,$B69,'SG09'!I:I)*SG09_+SUMIF('SG10'!$B:$B,$B69,'SG10'!I:I)*SG10_+SUMIF('SG11'!$B:$B,$B69,'SG11'!I:I)*SG11_+SUMIF('SG12'!$B:$B,$B69,'SG12'!I:I)*SG12_+SUMIF('SG13'!$B:$B,$B69,'SG13'!I:I)*SG13_+SUMIF('SG14'!$B:$B,$B69,'SG14'!I:I)*SG14_+SUMIF('SG15'!$B:$B,$B69,'SG15'!I:I)*SG15_) -> 103 | K69: =(SUMIF('SG01'!$B:$B,$B69,'SG01'!K:K)*SG01_+SUMIF('SG02'!$B:$B,$B69,'SG02'!K:K)*SG02_+SUMIF('SG03'!$B:$B,$B69,'SG03'!K:K)*SG03_+SUMIF('SG04'!$B:$B,$B69,'SG04'!K:K)*SG04_+SUMIF('SG05'!$B:$B,$B69,'SG05'!K:K)*SG05_+SUMIF('SG06'!$B:$B,$B69,'SG06'!K:K)*SG06_+SUMIF('SG07'!$B:$B,$B69,'SG07'!K:K)*SG07_+SUMIF('SG08'!$B:$B,$B69,'SG08'!K:K)*SG08_+SUMIF('SG09'!$B:$B,$B69,'SG09'!K:K)*SG09_+SUMIF('SG10'!$B:$B,$B69,'SG10'!K:K)*SG10_+SUMIF('SG11'!$B:$B,$B69,'SG11'!K:K)*SG11_+SUMIF('SG12'!$B:$B,$B69,'SG12'!K:K)*SG12_+SUMIF('SG13'!$B:$B,$B69,'SG13'!K:K)*SG13_+SUMIF('SG14'!$B:$B,$B69,'SG14'!K:K)*SG14_+SUMIF('SG15'!$B:$B,$B69,'SG15'!K:K)*SG15_) -> 17738778 | L69: =(SUMIF('SG01'!$B:$B,$B69,'SG01'!L:L)*SG01_+SUMIF('SG02'!$B:$B,$B69,'SG02'!L:L)*SG02_+SUMIF('SG03'!$B:$B,$B69,'SG03'!L:L)*SG03_+SUMIF('SG04'!$B:$B,$B69,'SG04'!L:L)*SG04_+SUMIF('SG05'!$B:$B,$B69,'SG05'!L:L)*SG05_+SUMIF('SG06'!$B:$B,$B69,'SG06'!L:L)*SG06_+SUMIF('SG07'!$B:$B,$B69,'SG07'!L:L)*SG07_+SUMIF('SG08'!$B:$B,$B69,'SG08'!L:L)*SG08_+SUMIF('SG09'!$B:$B,$B69,'SG09'!L:L)*SG09_+SUMIF('SG10'!$B:$B,$B69,'SG10'!L:L)*SG10_+SUMIF('SG11'!$B:$B,$B69,'SG11'!L:L)*SG11_+SUMIF('SG12'!$B:$B,$B69,'SG12'!L:L)*SG12_+SUMIF('SG13'!$B:$B,$B69,'SG13'!L:L)*SG13_+SUMIF('SG14'!$B:$B,$B69,'SG14'!L:L)*SG14_+SUMIF('SG15'!$B:$B,$B69,'SG15'!L:L)*SG15_) -> 52715000 | M69: =L69-K69 -> 34976222 | N69: =K69/L69 -> 0.33650342 | O69: =L69/L$10 -> 0.033997329 | P69: =M69/M$10 -> 0.03399558 | Q69: =I69/I$10 -> 0.0064166459 | R69: =I69/$K$5*100 -> 2.7890604 | S69: =R69*T$5 -> 8.194113 | T69: =IFERROR(S69*G69,0) -> 4193715.2 | V69: =IF(B69<>"",IFERROR(IF($I69>=$X$10,"High","Low"),""),"") -> High | W69: =IF(B69<>"",IFERROR(IF($L69>=$X$12,"High","Low"),""),"") -> High | X69: =IF(B69<>"",IFERROR(IF(AND(V69="high",W69="high"),"Star",IF(AND(V69="low",W69="high"),"Puzzle",(IF(AND(V69="high",W69="low"),"Horse","Dog")))),""),"") -> Star
A70: 2 | B70: GSTBO002 | C70: =VLOOKUP(B70,'SG01'!$B:$E,2,0) -> Sườn Bò Hoàng Đế Xốt G.Master | E70: =VLOOKUP(B70,'SG01'!$B:$E,4,0) -> Phần | F70: =K70/I70 -> 72787.685 | G70: =L70/I70 -> 208050.85 | H70: =G70-F70 -> 135263.16 | I70: =(SUMIF('SG01'!$B:$B,$B70,'SG01'!I:I)*SG01_+SUMIF('SG02'!$B:$B,$B70,'SG02'!I:I)*SG02_+SUMIF('SG03'!$B:$B,$B70,'SG03'!I:I)*SG03_+SUMIF('SG04'!$B:$B,$B70,'SG04'!I:I)*SG04_+SUMIF('SG05'!$B:$B,$B70,'SG05'!I:I)*SG05_+SUMIF('SG06'!$B:$B,$B70,'SG06'!I:I)*SG06_+SUMIF('SG07'!$B:$B,$B70,'SG07'!I:I)*SG07_+SUMIF('SG08'!$B:$B,$B70,'SG08'!I:I)*SG08_+SUMIF('SG09'!$B:$B,$B70,'SG09'!I:I)*SG09_+SUMIF('SG10'!$B:$B,$B70,'SG10'!I:I)*SG10_+SUMIF('SG11'!$B:$B,$B70,'SG11'!I:I)*SG11_+SUMIF('SG12'!$B:$B,$B70,'SG12'!I:I)*SG12_+SUMIF('SG13'!$B:$B,$B70,'SG13'!I:I)*SG13_+SUMIF('SG14'!$B:$B,$B70,'SG14'!I:I)*SG14_+SUMIF('SG15'!$B:$B,$B70,'SG15'!I:I)*SG15_) -> 236 | K70: =(SUMIF('SG01'!$B:$B,$B70,'SG01'!K:K)*SG01_+SUMIF('SG02'!$B:$B,$B70,'SG02'!K:K)*SG02_+SUMIF('SG03'!$B:$B,$B70,'SG03'!K:K)*SG03_+SUMIF('SG04'!$B:$B,$B70,'SG04'!K:K)*SG04_+SUMIF('SG05'!$B:$B,$B70,'SG05'!K:K)*SG05_+SUMIF('SG06'!$B:$B,$B70,'SG06'!K:K)*SG06_+SUMIF('SG07'!$B:$B,$B70,'SG07'!K:K)*SG07_+SUMIF('SG08'!$B:$B,$B70,'SG08'!K:K)*SG08_+SUMIF('SG09'!$B:$B,$B70,'SG09'!K:K)*SG09_+SUMIF('SG10'!$B:$B,$B70,'SG10'!K:K)*SG10_+SUMIF('SG11'!$B:$B,$B70,'SG11'!K:K)*SG11_+SUMIF('SG12'!$B:$B,$B70,'SG12'!K:K)*SG12_+SUMIF('SG13'!$B:$B,$B70,'SG13'!K:K)*SG13_+SUMIF('SG14'!$B:$B,$B70,'SG14'!K:K)*SG14_+SUMIF('SG15'!$B:$B,$B70,'SG15'!K:K)*SG15_) -> 17177894 | L70: =(SUMIF('SG01'!$B:$B,$B70,'SG01'!L:L)*SG01_+SUMIF('SG02'!$B:$B,$B70,'SG02'!L:L)*SG02_+SUMIF('SG03'!$B:$B,$B70,'SG03'!L:L)*SG03_+SUMIF('SG04'!$B:$B,$B70,'SG04'!L:L)*SG04_+SUMIF('SG05'!$B:$B,$B70,'SG05'!L:L)*SG05_+SUMIF('SG06'!$B:$B,$B70,'SG06'!L:L)*SG06_+SUMIF('SG07'!$B:$B,$B70,'SG07'!L:L)*SG07_+SUMIF('SG08'!$B:$B,$B70,'SG08'!L:L)*SG08_+SUMIF('SG09'!$B:$B,$B70,'SG09'!L:L)*SG09_+SUMIF('SG10'!$B:$B,$B70,'SG10'!L:L)*SG10_+SUMIF('SG11'!$B:$B,$B70,'SG11'!L:L)*SG11_+SUMIF('SG12'!$B:$B,$B70,'SG12'!L:L)*SG12_+SUMIF('SG13'!$B:$B,$B70,'SG13'!L:L)*SG13_+SUMIF('SG14'!$B:$B,$B70,'SG14'!L:L)*SG14_+SUMIF('SG15'!$B:$B,$B70,'SG15'!L:L)*SG15_) -> 49100000 | M70: =L70-K70 -> 31922106 | N70: =K70/L70 -> 0.34985527 | O70: =L70/L$10 -> 0.031665917 | P70: =M70/M$10 -> 0.031027094 | Q70: =I70/I$10 -> 0.014702218 | R70: =I70/$K$5*100 -> 6.3904685 | S70: =R70*T$5 -> 18.774861 | T70: =IFERROR(S70*G70,0) -> 3906125.7 | V70: =IF(B70<>"",IFERROR(IF($I70>=$X$10,"High","Low"),""),"") -> High | W70: =IF(B70<>"",IFERROR(IF($L70>=$X$12,"High","Low"),""),"") -> High | X70: =IF(B70<>"",IFERROR(IF(AND(V70="high",W70="high"),"Star",IF(AND(V70="low",W70="high"),"Puzzle",(IF(AND(V70="high",W70="low"),"Horse","Dog")))),""),"") -> Star
A71: 3 | B71: GSTBO003 | C71: =VLOOKUP(B71,'SG01'!$B:$E,2,0) -> Sườn Bò Hoàng Đế Xốt Tare | E71: =VLOOKUP(B71,'SG01'!$B:$E,4,0) -> Phần | F71: =K71/I71 -> 60851.006 | G71: =L71/I71 -> 187804.43 | H71: =G71-F71 -> 126953.42 | I71: =(SUMIF('SG01'!$B:$B,$B71,'SG01'!I:I)*SG01_+SUMIF('SG02'!$B:$B,$B71,'SG02'!I:I)*SG02_+SUMIF('SG03'!$B:$B,$B71,'SG03'!I:I)*SG03_+SUMIF('SG04'!$B:$B,$B71,'SG04'!I:I)*SG04_+SUMIF('SG05'!$B:$B,$B71,'SG05'!I:I)*SG05_+SUMIF('SG06'!$B:$B,$B71,'SG06'!I:I)*SG06_+SUMIF('SG07'!$B:$B,$B71,'SG07'!I:I)*SG07_+SUMIF('SG08'!$B:$B,$B71,'SG08'!I:I)*SG08_+SUMIF('SG09'!$B:$B,$B71,'SG09'!I:I)*SG09_+SUMIF('SG10'!$B:$B,$B71,'SG10'!I:I)*SG10_+SUMIF('SG11'!$B:$B,$B71,'SG11'!I:I)*SG11_+SUMIF('SG12'!$B:$B,$B71,'SG12'!I:I)*SG12_+SUMIF('SG13'!$B:$B,$B71,'SG13'!I:I)*SG13_+SUMIF('SG14'!$B:$B,$B71,'SG14'!I:I)*SG14_+SUMIF('SG15'!$B:$B,$B71,'SG15'!I:I)*SG15_) -> 271 | K71: =(SUMIF('SG01'!$B:$B,$B71,'SG01'!K:K)*SG01_+SUMIF('SG02'!$B:$B,$B71,'SG02'!K:K)*SG02_+SUMIF('SG03'!$B:$B,$B71,'SG03'!K:K)*SG03_+SUMIF('SG04'!$B:$B,$B71,'SG04'!K:K)*SG04_+SUMIF('SG05'!$B:$B,$B71,'SG05'!K:K)*SG05_+SUMIF('SG06'!$B:$B,$B71,'SG06'!K:K)*SG06_+SUMIF('SG07'!$B:$B,$B71,'SG07'!K:K)*SG07_+SUMIF('SG08'!$B:$B,$B71,'SG08'!K:K)*SG08_+SUMIF('SG09'!$B:$B,$B71,'SG09'!K:K)*SG09_+SUMIF('SG10'!$B:$B,$B71,'SG10'!K:K)*SG10_+SUMIF('SG11'!$B:$B,$B71,'SG11'!K:K)*SG11_+SUMIF('SG12'!$B:$B,$B71,'SG12'!K:K)*SG12_+SUMIF('SG13'!$B:$B,$B71,'SG13'!K:K)*SG13_+SUMIF('SG14'!$B:$B,$B71,'SG14'!K:K)*SG14_+SUMIF('SG15'!$B:$B,$B71,'SG15'!K:K)*SG15_) -> 16490623 | L71: =(SUMIF('SG01'!$B:$B,$B71,'SG01'!L:L)*SG01_+SUMIF('SG02'!$B:$B,$B71,'SG02'!L:L)*SG02_+SUMIF('SG03'!$B:$B,$B71,'SG03'!L:L)*SG03_+SUMIF('SG04'!$B:$B,$B71,'SG04'!L:L)*SG04_+SUMIF('SG05'!$B:$B,$B71,'SG05'!L:L)*SG05_+SUMIF('SG06'!$B:$B,$B71,'SG06'!L:L)*SG06_+SUMIF('SG07'!$B:$B,$B71,'SG07'!L:L)*SG07_+SUMIF('SG08'!$B:$B,$B71,'SG08'!L:L)*SG08_+SUMIF('SG09'!$B:$B,$B71,'SG09'!L:L)*SG09_+SUMIF('SG10'!$B:$B,$B71,'SG10'!L:L)*SG10_+SUMIF('SG11'!$B:$B,$B71,'SG11'!L:L)*SG11_+SUMIF('SG12'!$B:$B,$B71,'SG12'!L:L)*SG12_+SUMIF('SG13'!$B:$B,$B71,'SG13'!L:L)*SG13_+SUMIF('SG14'!$B:$B,$B71,'SG14'!L:L)*SG14_+SUMIF('SG15'!$B:$B,$B71,'SG15'!L:L)*SG15_) -> 50895000 | M71: =L71-K71 -> 34404377 | N71: =K71/L71 -> 0.32401262 | O71: =L71/L$10 -> 0.032823562 | P71: =M71/M$10 -> 0.033439769 | Q71: =I71/I$10 -> 0.016882631 | R71: =I71/$K$5*100 -> 7.3382074 | S71: =R71*T$5 -> 21.559268 | T71: =IFERROR(S71*G71,0) -> 4048926 | V71: =IF(B71<>"",IFERROR(IF($I71>=$X$10,"High","Low"),""),"") -> High | W71: =IF(B71<>"",IFERROR(IF($L71>=$X$12,"High","Low"),""),"") -> High | X71: =IF(B71<>"",IFERROR(IF(AND(V71="high",W71="high"),"Star",IF(AND(V71="low",W71="high"),"Puzzle",(IF(AND(V71="high",W71="low"),"Horse","Dog")))),""),"") -> Star
A72: 4 | B72: GSTBO004 | C72: =VLOOKUP(B72,'SG01'!$B:$E,2,0) -> Thăn Ngoại Bò Hoàng Đế Nguyên Vị | E72: =VLOOKUP(B72,'SG01'!$B:$E,4,0) -> Phần | F72: =K72/I72 -> 54833.035 | G72: =L72/I72 -> 167586.21 | H72: =G72-F72 -> 112753.17 | I72: =(SUMIF('SG01'!$B:$B,$B72,'SG01'!I:I)*SG01_+SUMIF('SG02'!$B:$B,$B72,'SG02'!I:I)*SG02_+SUMIF('SG03'!$B:$B,$B72,'SG03'!I:I)*SG03_+SUMIF('SG04'!$B:$B,$B72,'SG04'!I:I)*SG04_+SUMIF('SG05'!$B:$B,$B72,'SG05'!I:I)*SG05_+SUMIF('SG06'!$B:$B,$B72,'SG06'!I:I)*SG06_+SUMIF('SG07'!$B:$B,$B72,'SG07'!I:I)*SG07_+SUMIF('SG08'!$B:$B,$B72,'SG08'!I:I)*SG08_+SUMIF('SG09'!$B:$B,$B72,'SG09'!I:I)*SG09_+SUMIF('SG10'!$B:$B,$B72,'SG10'!I:I)*SG10_+SUMIF('SG11'!$B:$B,$B72,'SG11'!I:I)*SG11_+SUMIF('SG12'!$B:$B,$B72,'SG12'!I:I)*SG12_+SUMIF('SG13'!$B:$B,$B72,'SG13'!I:I)*SG13_+SUMIF('SG14'!$B:$B,$B72,'SG14'!I:I)*SG14_+SUMIF('SG15'!$B:$B,$B72,'SG15'!I:I)*SG15_) -> 145 | K72: =(SUMIF('SG01'!$B:$B,$B72,'SG01'!K:K)*SG01_+SUMIF('SG02'!$B:$B,$B72,'SG02'!K:K)*SG02_+SUMIF('SG03'!$B:$B,$B72,'SG03'!K:K)*SG03_+SUMIF('SG04'!$B:$B,$B72,'SG04'!K:K)*SG04_+SUMIF('SG05'!$B:$B,$B72,'SG05'!K:K)*SG05_+SUMIF('SG06'!$B:$B,$B72,'SG06'!K:K)*SG06_+SUMIF('SG07'!$B:$B,$B72,'SG07'!K:K)*SG07_+SUMIF('SG08'!$B:$B,$B72,'SG08'!K:K)*SG08_+SUMIF('SG09'!$B:$B,$B72,'SG09'!K:K)*SG09_+SUMIF('SG10'!$B:$B,$B72,'SG10'!K:K)*SG10_+SUMIF('SG11'!$B:$B,$B72,'SG11'!K:K)*SG11_+SUMIF('SG12'!$B:$B,$B72,'SG12'!K:K)*SG12_+SUMIF('SG13'!$B:$B,$B72,'SG13'!K:K)*SG13_+SUMIF('SG14'!$B:$B,$B72,'SG14'!K:K)*SG14_+SUMIF('SG15'!$B:$B,$B72,'SG15'!K:K)*SG15_) -> 7950790 | L72: =(SUMIF('SG01'!$B:$B,$B72,'SG01'!L:L)*SG01_+SUMIF('SG02'!$B:$B,$B72,'SG02'!L:L)*SG02_+SUMIF('SG03'!$B:$B,$B72,'SG03'!L:L)*SG03_+SUMIF('SG04'!$B:$B,$B72,'SG04'!L:L)*SG04_+SUMIF('SG05'!$B:$B,$B72,'SG05'!L:L)*SG05_+SUMIF('SG06'!$B:$B,$B72,'SG06'!L:L)*SG06_+SUMIF('SG07'!$B:$B,$B72,'SG07'!L:L)*SG07_+SUMIF('SG08'!$B:$B,$B72,'SG08'!L:L)*SG08_+SUMIF('SG09'!$B:$B,$B72,'SG09'!L:L)*SG09_+SUMIF('SG10'!$B:$B,$B72,'SG10'!L:L)*SG10_+SUMIF('SG11'!$B:$B,$B72,'SG11'!L:L)*SG11_+SUMIF('SG12'!$B:$B,$B72,'SG12'!L:L)*SG12_+SUMIF('SG13'!$B:$B,$B72,'SG13'!L:L)*SG13_+SUMIF('SG14'!$B:$B,$B72,'SG14'!L:L)*SG14_+SUMIF('SG15'!$B:$B,$B72,'SG15'!L:L)*SG15_) -> 24300000 | M72: =L72-K72 -> 16349210 | N72: =K72/L72 -> 0.32719301 | O72: =L72/L$10 -> 0.015671727 | P72: =M72/M$10 -> 0.015890821 | Q72: =I72/I$10 -> 0.0090331423 | R72: =I72/$K$5*100 -> 3.9263471 | S72: =R72*T$5 -> 11.535402 | T72: =IFERROR(S72*G72,0) -> 1933174.2 | V72: =IF(B72<>"",IFERROR(IF($I72>=$X$10,"High","Low"),""),"") -> High | W72: =IF(B72<>"",IFERROR(IF($L72>=$X$12,"High","Low"),""),"") -> High | X72: =IF(B72<>"",IFERROR(IF(AND(V72="high",W72="high"),"Star",IF(AND(V72="low",W72="high"),"Puzzle",(IF(AND(V72="high",W72="low"),"Horse","Dog")))),""),"") -> Star
A73: 5 | B73: GSTBO005 | C73: =VLOOKUP(B73,'SG01'!$B:$E,2,0) -> Dẻ Sườn Bò Mỹ Nguyên Vị | E73: =VLOOKUP(B73,'SG01'!$B:$E,4,0) -> Phần | F73: =K73/I73 -> 46317.577 | G73: =L73/I73 -> 168251.23 | H73: =G73-F73 -> 121933.65 | I73: =(SUMIF('SG01'!$B:$B,$B73,'SG01'!I:I)*SG01_+SUMIF('SG02'!$B:$B,$B73,'SG02'!I:I)*SG02_+SUMIF('SG03'!$B:$B,$B73,'SG03'!I:I)*SG03_+SUMIF('SG04'!$B:$B,$B73,'SG04'!I:I)*SG04_+SUMIF('SG05'!$B:$B,$B73,'SG05'!I:I)*SG05_+SUMIF('SG06'!$B:$B,$B73,'SG06'!I:I)*SG06_+SUMIF('SG07'!$B:$B,$B73,'SG07'!I:I)*SG07_+SUMIF('SG08'!$B:$B,$B73,'SG08'!I:I)*SG08_+SUMIF('SG09'!$B:$B,$B73,'SG09'!I:I)*SG09_+SUMIF('SG10'!$B:$B,$B73,'SG10'!I:I)*SG10_+SUMIF('SG11'!$B:$B,$B73,'SG11'!I:I)*SG11_+SUMIF('SG12'!$B:$B,$B73,'SG12'!I:I)*SG12_+SUMIF('SG13'!$B:$B,$B73,'SG13'!I:I)*SG13_+SUMIF('SG14'!$B:$B,$B73,'SG14'!I:I)*SG14_+SUMIF('SG15'!$B:$B,$B73,'SG15'!I:I)*SG15_) -> 203 | K73: =(SUMIF('SG01'!$B:$B,$B73,'SG01'!K:K)*SG01_+SUMIF('SG02'!$B:$B,$B73,'SG02'!K:K)*SG02_+SUMIF('SG03'!$B:$B,$B73,'SG03'!K:K)*SG03_+SUMIF('SG04'!$B:$B,$B73,'SG04'!K:K)*SG04_+SUMIF('SG05'!$B:$B,$B73,'SG05'!K:K)*SG05_+SUMIF('SG06'!$B:$B,$B73,'SG06'!K:K)*SG06_+SUMIF('SG07'!$B:$B,$B73,'SG07'!K:K)*SG07_+SUMIF('SG08'!$B:$B,$B73,'SG08'!K:K)*SG08_+SUMIF('SG09'!$B:$B,$B73,'SG09'!K:K)*SG09_+SUMIF('SG10'!$B:$B,$B73,'SG10'!K:K)*SG10_+SUMIF('SG11'!$B:$B,$B73,'SG11'!K:K)*SG11_+SUMIF('SG12'!$B:$B,$B73,'SG12'!K:K)*SG12_+SUMIF('SG13'!$B:$B,$B73,'SG13'!K:K)*SG13_+SUMIF('SG14'!$B:$B,$B73,'SG14'!K:K)*SG14_+SUMIF('SG15'!$B:$B,$B73,'SG15'!K:K)*SG15_) -> 9402468.1 | L73: =(SUMIF('SG01'!$B:$B,$B73,'SG01'!L:L)*SG01_+SUMIF('SG02'!$B:$B,$B73,'SG02'!L:L)*SG02_+SUMIF('SG03'!$B:$B,$B73,'SG03'!L:L)*SG03_+SUMIF('SG04'!$B:$B,$B73,'SG04'!L:L)*SG04_+SUMIF('SG05'!$B:$B,$B73,'SG05'!L:L)*SG05_+SUMIF('SG06'!$B:$B,$B73,'SG06'!L:L)*SG06_+SUMIF('SG07'!$B:$B,$B73,'SG07'!L:L)*SG07_+SUMIF('SG08'!$B:$B,$B73,'SG08'!L:L)*SG08_+SUMIF('SG09'!$B:$B,$B73,'SG09'!L:L)*SG09_+SUMIF('SG10'!$B:$B,$B73,'SG10'!L:L)*SG10_+SUMIF('SG11'!$B:$B,$B73,'SG11'!L:L)*SG11_+SUMIF('SG12'!$B:$B,$B73,'SG12'!L:L)*SG12_+SUMIF('SG13'!$B:$B,$B73,'SG13'!L:L)*SG13_+SUMIF('SG14'!$B:$B,$B73,'SG14'!L:L)*SG14_+SUMIF('SG15'!$B:$B,$B73,'SG15'!L:L)*SG15_) -> 34155000 | M73: =L73-K73 -> 24752532 | N73: =K73/L73 -> 0.27528819 | O73: =L73/L$10 -> 0.022027483 | P73: =M73/M$10 -> 0.024058536 | Q73: =I73/I$10 -> 0.012646399 | R73: =I73/$K$5*100 -> 5.496886 | S73: =R73*T$5 -> 16.149562 | T73: =IFERROR(S73*G73,0) -> 2717183.8 | V73: =IF(B73<>"",IFERROR(IF($I73>=$X$10,"High","Low"),""),"") -> High | W73: =IF(B73<>"",IFERROR(IF($L73>=$X$12,"High","Low"),""),"") -> High | X73: =IF(B73<>"",IFERROR(IF(AND(V73="high",W73="high"),"Star",IF(AND(V73="low",W73="high"),"Puzzle",(IF(AND(V73="high",W73="low"),"Horse","Dog")))),""),"") -> Star
A74: 6 | B74: GSTBO007 | C74: =VLOOKUP(B74,'SG01'!$B:$E,2,0) -> Thăn Vai Bò Mỹ Nguyên Vị | E74: =VLOOKUP(B74,'SG01'!$B:$E,4,0) -> Phần | F74: =K74/I74 -> 52609.251 | G74: =L74/I74 -> 147333.33 | H74: =G74-F74 -> 94724.082 | I74: =(SUMIF('SG01'!$B:$B,$B74,'SG01'!I:I)*SG01_+SUMIF('SG02'!$B:$B,$B74,'SG02'!I:I)*SG02_+SUMIF('SG03'!$B:$B,$B74,'SG03'!I:I)*SG03_+SUMIF('SG04'!$B:$B,$B74,'SG04'!I:I)*SG04_+SUMIF('SG05'!$B:$B,$B74,'SG05'!I:I)*SG05_+SUMIF('SG06'!$B:$B,$B74,'SG06'!I:I)*SG06_+SUMIF('SG07'!$B:$B,$B74,'SG07'!I:I)*SG07_+SUMIF('SG08'!$B:$B,$B74,'SG08'!I:I)*SG08_+SUMIF('SG09'!$B:$B,$B74,'SG09'!I:I)*SG09_+SUMIF('SG10'!$B:$B,$B74,'SG10'!I:I)*SG10_+SUMIF('SG11'!$B:$B,$B74,'SG11'!I:I)*SG11_+SUMIF('SG12'!$B:$B,$B74,'SG12'!I:I)*SG12_+SUMIF('SG13'!$B:$B,$B74,'SG13'!I:I)*SG13_+SUMIF('SG14'!$B:$B,$B74,'SG14'!I:I)*SG14_+SUMIF('SG15'!$B:$B,$B74,'SG15'!I:I)*SG15_) -> 180 | K74: =(SUMIF('SG01'!$B:$B,$B74,'SG01'!K:K)*SG01_+SUMIF('SG02'!$B:$B,$B74,'SG02'!K:K)*SG02_+SUMIF('SG03'!$B:$B,$B74,'SG03'!K:K)*SG03_+SUMIF('SG04'!$B:$B,$B74,'SG04'!K:K)*SG04_+SUMIF('SG05'!$B:$B,$B74,'SG05'!K:K)*SG05_+SUMIF('SG06'!$B:$B,$B74,'SG06'!K:K)*SG06_+SUMIF('SG07'!$B:$B,$B74,'SG07'!K:K)*SG07_+SUMIF('SG08'!$B:$B,$B74,'SG08'!K:K)*SG08_+SUMIF('SG09'!$B:$B,$B74,'SG09'!K:K)*SG09_+SUMIF('SG10'!$B:$B,$B74,'SG10'!K:K)*SG10_+SUMIF('SG11'!$B:$B,$B74,'SG11'!K:K)*SG11_+SUMIF('SG12'!$B:$B,$B74,'SG12'!K:K)*SG12_+SUMIF('SG13'!$B:$B,$B74,'SG13'!K:K)*SG13_+SUMIF('SG14'!$B:$B,$B74,'SG14'!K:K)*SG14_+SUMIF('SG15'!$B:$B,$B74,'SG15'!K:K)*SG15_) -> 9469665.2 | L74: =(SUMIF('SG01'!$B:$B,$B74,'SG01'!L:L)*SG01_+SUMIF('SG02'!$B:$B,$B74,'SG02'!L:L)*SG02_+SUMIF('SG03'!$B:$B,$B74,'SG03'!L:L)*SG03_+SUMIF('SG04'!$B:$B,$B74,'SG04'!L:L)*SG04_+SUMIF('SG05'!$B:$B,$B74,'SG05'!L:L)*SG05_+SUMIF('SG06'!$B:$B,$B74,'SG06'!L:L)*SG06_+SUMIF('SG07'!$B:$B,$B74,'SG07'!L:L)*SG07_+SUMIF('SG08'!$B:$B,$B74,'SG08'!L:L)*SG08_+SUMIF('SG09'!$B:$B,$B74,'SG09'!L:L)*SG09_+SUMIF('SG10'!$B:$B,$B74,'SG10'!L:L)*SG10_+SUMIF('SG11'!$B:$B,$B74,'SG11'!L:L)*SG11_+SUMIF('SG12'!$B:$B,$B74,'SG12'!L:L)*SG12_+SUMIF('SG13'!$B:$B,$B74,'SG13'!L:L)*SG13_+SUMIF('SG14'!$B:$B,$B74,'SG14'!L:L)*SG14_+SUMIF('SG15'!$B:$B,$B74,'SG15'!L:L)*SG15_) -> 26520000 | M74: =L74-K74 -> 17050335 | N74: =K74/L74 -> 0.35707636 | O74: =L74/L$10 -> 0.017103465 | P74: =M74/M$10 -> 0.016572288 | Q74: =I74/I$10 -> 0.011213556 | R74: =I74/$K$5*100 -> 4.8740861 | S74: =R74*T$5 -> 14.319809 | T74: =IFERROR(S74*G74,0) -> 2109785.2 | V74: =IF(B74<>"",IFERROR(IF($I74>=$X$10,"High","Low"),""),"") -> High | W74: =IF(B74<>"",IFERROR(IF($L74>=$X$12,"High","Low"),""),"") -> High | X74: =IF(B74<>"",IFERROR(IF(AND(V74="high",W74="high"),"Star",IF(AND(V74="low",W74="high"),"Puzzle",(IF(AND(V74="high",W74="low"),"Horse","Dog")))),""),"") -> Star
A75: 7 | B75: GSTBO008 | C75: =VLOOKUP(B75,'SG01'!$B:$E,2,0) -> Thăn Vai Bò Mỹ Xốt G.Master | E75: =VLOOKUP(B75,'SG01'!$B:$E,4,0) -> Phần | F75: =K75/I75 -> 52901.081 | G75: =L75/I75 -> 148036.81 | H75: =G75-F75 -> 95135.729 | I75: =(SUMIF('SG01'!$B:$B,$B75,'SG01'!I:I)*SG01_+SUMIF('SG02'!$B:$B,$B75,'SG02'!I:I)*SG02_+SUMIF('SG03'!$B:$B,$B75,'SG03'!I:I)*SG03_+SUMIF('SG04'!$B:$B,$B75,'SG04'!I:I)*SG04_+SUMIF('SG05'!$B:$B,$B75,'SG05'!I:I)*SG05_+SUMIF('SG06'!$B:$B,$B75,'SG06'!I:I)*SG06_+SUMIF('SG07'!$B:$B,$B75,'SG07'!I:I)*SG07_+SUMIF('SG08'!$B:$B,$B75,'SG08'!I:I)*SG08_+SUMIF('SG09'!$B:$B,$B75,'SG09'!I:I)*SG09_+SUMIF('SG10'!$B:$B,$B75,'SG10'!I:I)*SG10_+SUMIF('SG11'!$B:$B,$B75,'SG11'!I:I)*SG11_+SUMIF('SG12'!$B:$B,$B75,'SG12'!I:I)*SG12_+SUMIF('SG13'!$B:$B,$B75,'SG13'!I:I)*SG13_+SUMIF('SG14'!$B:$B,$B75,'SG14'!I:I)*SG14_+SUMIF('SG15'!$B:$B,$B75,'SG15'!I:I)*SG15_) -> 163 | K75: =(SUMIF('SG01'!$B:$B,$B75,'SG01'!K:K)*SG01_+SUMIF('SG02'!$B:$B,$B75,'SG02'!K:K)*SG02_+SUMIF('SG03'!$B:$B,$B75,'SG03'!K:K)*SG03_+SUMIF('SG04'!$B:$B,$B75,'SG04'!K:K)*SG04_+SUMIF('SG05'!$B:$B,$B75,'SG05'!K:K)*SG05_+SUMIF('SG06'!$B:$B,$B75,'SG06'!K:K)*SG06_+SUMIF('SG07'!$B:$B,$B75,'SG07'!K:K)*SG07_+SUMIF('SG08'!$B:$B,$B75,'SG08'!K:K)*SG08_+SUMIF('SG09'!$B:$B,$B75,'SG09'!K:K)*SG09_+SUMIF('SG10'!$B:$B,$B75,'SG10'!K:K)*SG10_+SUMIF('SG11'!$B:$B,$B75,'SG11'!K:K)*SG11_+SUMIF('SG12'!$B:$B,$B75,'SG12'!K:K)*SG12_+SUMIF('SG13'!$B:$B,$B75,'SG13'!K:K)*SG13_+SUMIF('SG14'!$B:$B,$B75,'SG14'!K:K)*SG14_+SUMIF('SG15'!$B:$B,$B75,'SG15'!K:K)*SG15_) -> 8622876.2 | L75: =(SUMIF('SG01'!$B:$B,$B75,'SG01'!L:L)*SG01_+SUMIF('SG02'!$B:$B,$B75,'SG02'!L:L)*SG02_+SUMIF('SG03'!$B:$B,$B75,'SG03'!L:L)*SG03_+SUMIF('SG04'!$B:$B,$B75,'SG04'!L:L)*SG04_+SUMIF('SG05'!$B:$B,$B75,'SG05'!L:L)*SG05_+SUMIF('SG06'!$B:$B,$B75,'SG06'!L:L)*SG06_+SUMIF('SG07'!$B:$B,$B75,'SG07'!L:L)*SG07_+SUMIF('SG08'!$B:$B,$B75,'SG08'!L:L)*SG08_+SUMIF('SG09'!$B:$B,$B75,'SG09'!L:L)*SG09_+SUMIF('SG10'!$B:$B,$B75,'SG10'!L:L)*SG10_+SUMIF('SG11'!$B:$B,$B75,'SG11'!L:L)*SG11_+SUMIF('SG12'!$B:$B,$B75,'SG12'!L:L)*SG12_+SUMIF('SG13'!$B:$B,$B75,'SG13'!L:L)*SG13_+SUMIF('SG14'!$B:$B,$B75,'SG14'!L:L)*SG14_+SUMIF('SG15'!$B:$B,$B75,'SG15'!L:L)*SG15_) -> 24130000 | M75: =L75-K75 -> 15507124 | N75: =K75/L75 -> 0.35735086 | O75: =L75/L$10 -> 0.015562089 | P75: =M75/M$10 -> 0.015072345 | Q75: =I75/I$10 -> 0.010154498 | R75: =I75/$K$5*100 -> 4.4137558 | S75: =R75*T$5 -> 12.967383 | T75: =IFERROR(S75*G75,0) -> 1919650 | V75: =IF(B75<>"",IFERROR(IF($I75>=$X$10,"High","Low"),""),"") -> High | W75: =IF(B75<>"",IFERROR(IF($L75>=$X$12,"High","Low"),""),"") -> High | X75: =IF(B75<>"",IFERROR(IF(AND(V75="high",W75="high"),"Star",IF(AND(V75="low",W75="high"),"Puzzle",(IF(AND(V75="high",W75="low"),"Horse","Dog")))),""),"") -> Star
A76: 8 | B76: GSTBO009 | C76: =VLOOKUP(B76,'SG01'!$B:$E,2,0) -> Lưỡi Bò Mỹ Nguyên Vị | E76: =VLOOKUP(B76,'SG01'!$B:$E,4,0) -> Phần | F76: =K76/I76 -> 38015.492 | G76: =L76/I76 -> 111416.67 | H76: =G76-F76 -> 73401.175 | I76: =(SUMIF('SG01'!$B:$B,$B76,'SG01'!I:I)*SG01_+SUMIF('SG02'!$B:$B,$B76,'SG02'!I:I)*SG02_+SUMIF('SG03'!$B:$B,$B76,'SG03'!I:I)*SG03_+SUMIF('SG04'!$B:$B,$B76,'SG04'!I:I)*SG04_+SUMIF('SG05'!$B:$B,$B76,'SG05'!I:I)*SG05_+SUMIF('SG06'!$B:$B,$B76,'SG06'!I:I)*SG06_+SUMIF('SG07'!$B:$B,$B76,'SG07'!I:I)*SG07_+SUMIF('SG08'!$B:$B,$B76,'SG08'!I:I)*SG08_+SUMIF('SG09'!$B:$B,$B76,'SG09'!I:I)*SG09_+SUMIF('SG10'!$B:$B,$B76,'SG10'!I:I)*SG10_+SUMIF('SG11'!$B:$B,$B76,'SG11'!I:I)*SG11_+SUMIF('SG12'!$B:$B,$B76,'SG12'!I:I)*SG12_+SUMIF('SG13'!$B:$B,$B76,'SG13'!I:I)*SG13_+SUMIF('SG14'!$B:$B,$B76,'SG14'!I:I)*SG14_+SUMIF('SG15'!$B:$B,$B76,'SG15'!I:I)*SG15_) -> 120 | K76: =(SUMIF('SG01'!$B:$B,$B76,'SG01'!K:K)*SG01_+SUMIF('SG02'!$B:$B,$B76,'SG02'!K:K)*SG02_+SUMIF('SG03'!$B:$B,$B76,'SG03'!K:K)*SG03_+SUMIF('SG04'!$B:$B,$B76,'SG04'!K:K)*SG04_+SUMIF('SG05'!$B:$B,$B76,'SG05'!K:K)*SG05_+SUMIF('SG06'!$B:$B,$B76,'SG06'!K:K)*SG06_+SUMIF('SG07'!$B:$B,$B76,'SG07'!K:K)*SG07_+SUMIF('SG08'!$B:$B,$B76,'SG08'!K:K)*SG08_+SUMIF('SG09'!$B:$B,$B76,'SG09'!K:K)*SG09_+SUMIF('SG10'!$B:$B,$B76,'SG10'!K:K)*SG10_+SUMIF('SG11'!$B:$B,$B76,'SG11'!K:K)*SG11_+SUMIF('SG12'!$B:$B,$B76,'SG12'!K:K)*SG12_+SUMIF('SG13'!$B:$B,$B76,'SG13'!K:K)*SG13_+SUMIF('SG14'!$B:$B,$B76,'SG14'!K:K)*SG14_+SUMIF('SG15'!$B:$B,$B76,'SG15'!K:K)*SG15_) -> 4561859 | L76: =(SUMIF('SG01'!$B:$B,$B76,'SG01'!L:L)*SG01_+SUMIF('SG02'!$B:$B,$B76,'SG02'!L:L)*SG02_+SUMIF('SG03'!$B:$B,$B76,'SG03'!L:L)*SG03_+SUMIF('SG04'!$B:$B,$B76,'SG04'!L:L)*SG04_+SUMIF('SG05'!$B:$B,$B76,'SG05'!L:L)*SG05_+SUMIF('SG06'!$B:$B,$B76,'SG06'!L:L)*SG06_+SUMIF('SG07'!$B:$B,$B76,'SG07'!L:L)*SG07_+SUMIF('SG08'!$B:$B,$B76,'SG08'!L:L)*SG08_+SUMIF('SG09'!$B:$B,$B76,'SG09'!L:L)*SG09_+SUMIF('SG10'!$B:$B,$B76,'SG10'!L:L)*SG10_+SUMIF('SG11'!$B:$B,$B76,'SG11'!L:L)*SG11_+SUMIF('SG12'!$B:$B,$B76,'SG12'!L:L)*SG12_+SUMIF('SG13'!$B:$B,$B76,'SG13'!L:L)*SG13_+SUMIF('SG14'!$B:$B,$B76,'SG14'!L:L)*SG14_+SUMIF('SG15'!$B:$B,$B76,'SG15'!L:L)*SG15_) -> 13370000 | M76: =L76-K76 -> 8808141 | N76: =K76/L76 -> 0.34120112 | O76: =L76/L$10 -> 0.0086226745 | P76: =M76/M$10 -> 0.0085611837 | Q76: =I76/I$10 -> 0.007475704 | R76: =I76/$K$5*100 -> 3.2493907 | S76: =R76*T$5 -> 9.5465394 | T76: =IFERROR(S76*G76,0) -> 1063643.6 | V76: =IF(B76<>"",IFERROR(IF($I76>=$X$10,"High","Low"),""),"") -> High | W76: =IF(B76<>"",IFERROR(IF($L76>=$X$12,"High","Low"),""),"") -> High | X76: =IF(B76<>"",IFERROR(IF(AND(V76="high",W76="high"),"Star",IF(AND(V76="low",W76="high"),"Puzzle",(IF(AND(V76="high",W76="low"),"Horse","Dog")))),""),"") -> Star
A77: 9 | B77: GSTBO011 | C77: =VLOOKUP(B77,'SG01'!$B:$E,2,0) -> Thăn Bò Hoàng Đế Thượng Hạng | E77: =VLOOKUP(B77,'SG01'!$B:$E,4,0) -> Phần | F77: =K77/I77 -> #DIV/0! | G77: =L77/I77 -> #DIV/0! | H77: =G77-F77 -> #DIV/0! | I77: =(SUMIF('SG01'!$B:$B,$B77,'SG01'!I:I)*SG01_+SUMIF('SG02'!$B:$B,$B77,'SG02'!I:I)*SG02_+SUMIF('SG03'!$B:$B,$B77,'SG03'!I:I)*SG03_+SUMIF('SG04'!$B:$B,$B77,'SG04'!I:I)*SG04_+SUMIF('SG05'!$B:$B,$B77,'SG05'!I:I)*SG05_+SUMIF('SG06'!$B:$B,$B77,'SG06'!I:I)*SG06_+SUMIF('SG07'!$B:$B,$B77,'SG07'!I:I)*SG07_+SUMIF('SG08'!$B:$B,$B77,'SG08'!I:I)*SG08_+SUMIF('SG09'!$B:$B,$B77,'SG09'!I:I)*SG09_+SUMIF('SG10'!$B:$B,$B77,'SG10'!I:I)*SG10_+SUMIF('SG11'!$B:$B,$B77,'SG11'!I:I)*SG11_+SUMIF('SG12'!$B:$B,$B77,'SG12'!I:I)*SG12_+SUMIF('SG13'!$B:$B,$B77,'SG13'!I:I)*SG13_+SUMIF('SG14'!$B:$B,$B77,'SG14'!I:I)*SG14_+SUMIF('SG15'!$B:$B,$B77,'SG15'!I:I)*SG15_) -> 0 | K77: =(SUMIF('SG01'!$B:$B,$B77,'SG01'!K:K)*SG01_+SUMIF('SG02'!$B:$B,$B77,'SG02'!K:K)*SG02_+SUMIF('SG03'!$B:$B,$B77,'SG03'!K:K)*SG03_+SUMIF('SG04'!$B:$B,$B77,'SG04'!K:K)*SG04_+SUMIF('SG05'!$B:$B,$B77,'SG05'!K:K)*SG05_+SUMIF('SG06'!$B:$B,$B77,'SG06'!K:K)*SG06_+SUMIF('SG07'!$B:$B,$B77,'SG07'!K:K)*SG07_+SUMIF('SG08'!$B:$B,$B77,'SG08'!K:K)*SG08_+SUMIF('SG09'!$B:$B,$B77,'SG09'!K:K)*SG09_+SUMIF('SG10'!$B:$B,$B77,'SG10'!K:K)*SG10_+SUMIF('SG11'!$B:$B,$B77,'SG11'!K:K)*SG11_+SUMIF('SG12'!$B:$B,$B77,'SG12'!K:K)*SG12_+SUMIF('SG13'!$B:$B,$B77,'SG13'!K:K)*SG13_+SUMIF('SG14'!$B:$B,$B77,'SG14'!K:K)*SG14_+SUMIF('SG15'!$B:$B,$B77,'SG15'!K:K)*SG15_) -> 0 | L77: =(SUMIF('SG01'!$B:$B,$B77,'SG01'!L:L)*SG01_+SUMIF('SG02'!$B:$B,$B77,'SG02'!L:L)*SG02_+SUMIF('SG03'!$B:$B,$B77,'SG03'!L:L)*SG03_+SUMIF('SG04'!$B:$B,$B77,'SG04'!L:L)*SG04_+SUMIF('SG05'!$B:$B,$B77,'SG05'!L:L)*SG05_+SUMIF('SG06'!$B:$B,$B77,'SG06'!L:L)*SG06_+SUMIF('SG07'!$B:$B,$B77,'SG07'!L:L)*SG07_+SUMIF('SG08'!$B:$B,$B77,'SG08'!L:L)*SG08_+SUMIF('SG09'!$B:$B,$B77,'SG09'!L:L)*SG09_+SUMIF('SG10'!$B:$B,$B77,'SG10'!L:L)*SG10_+SUMIF('SG11'!$B:$B,$B77,'SG11'!L:L)*SG11_+SUMIF('SG12'!$B:$B,$B77,'SG12'!L:L)*SG12_+SUMIF('SG13'!$B:$B,$B77,'SG13'!L:L)*SG13_+SUMIF('SG14'!$B:$B,$B77,'SG14'!L:L)*SG14_+SUMIF('SG15'!$B:$B,$B77,'SG15'!L:L)*SG15_) -> 0 | M77: =L77-K77 -> 0 | N77: =K77/L77 -> #DIV/0! | O77: =L77/L$10 -> 0 | P77: =M77/M$10 -> 0 | Q77: =I77/I$10 -> 0 | R77: =I77/$K$5*100 -> 0 | S77: =R77*T$5 -> 0 | T77: =IFERROR(S77*G77,0) -> 0 | V77: =IF(B77<>"",IFERROR(IF($I77>=$X$10,"High","Low"),""),"") -> Low | W77: =IF(B77<>"",IFERROR(IF($L77>=$X$12,"High","Low"),""),"") -> Low | X77: =IF(B77<>"",IFERROR(IF(AND(V77="high",W77="high"),"Star",IF(AND(V77="low",W77="high"),"Puzzle",(IF(AND(V77="high",W77="low"),"Horse","Dog")))),""),"") -> Dog
A78: 10 | B78: GSTBO012 | C78: =VLOOKUP(B78,'SG01'!$B:$E,2,0) -> Sườn Bò Wagyu Nhật Thượng Hạng Otoro A5 | E78: =VLOOKUP(B78,'SG01'!$B:$E,4,0) -> Phần | F78: =K78/I78 -> 172221.16 | G78: =L78/I78 -> 622309.09 | H78: =G78-F78 -> 450087.93 | I78: =(SUMIF('SG01'!$B:$B,$B78,'SG01'!I:I)*SG01_+SUMIF('SG02'!$B:$B,$B78,'SG02'!I:I)*SG02_+SUMIF('SG03'!$B:$B,$B78,'SG03'!I:I)*SG03_+SUMIF('SG04'!$B:$B,$B78,'SG04'!I:I)*SG04_+SUMIF('SG05'!$B:$B,$B78,'SG05'!I:I)*SG05_+SUMIF('SG06'!$B:$B,$B78,'SG06'!I:I)*SG06_+SUMIF('SG07'!$B:$B,$B78,'SG07'!I:I)*SG07_+SUMIF('SG08'!$B:$B,$B78,'SG08'!I:I)*SG08_+SUMIF('SG09'!$B:$B,$B78,'SG09'!I:I)*SG09_+SUMIF('SG10'!$B:$B,$B78,'SG10'!I:I)*SG10_+SUMIF('SG11'!$B:$B,$B78,'SG11'!I:I)*SG11_+SUMIF('SG12'!$B:$B,$B78,'SG12'!I:I)*SG12_+SUMIF('SG13'!$B:$B,$B78,'SG13'!I:I)*SG13_+SUMIF('SG14'!$B:$B,$B78,'SG14'!I:I)*SG14_+SUMIF('SG15'!$B:$B,$B78,'SG15'!I:I)*SG15_) -> 55 | K78: =(SUMIF('SG01'!$B:$B,$B78,'SG01'!K:K)*SG01_+SUMIF('SG02'!$B:$B,$B78,'SG02'!K:K)*SG02_+SUMIF('SG03'!$B:$B,$B78,'SG03'!K:K)*SG03_+SUMIF('SG04'!$B:$B,$B78,'SG04'!K:K)*SG04_+SUMIF('SG05'!$B:$B,$B78,'SG05'!K:K)*SG05_+SUMIF('SG06'!$B:$B,$B78,'SG06'!K:K)*SG06_+SUMIF('SG07'!$B:$B,$B78,'SG07'!K:K)*SG07_+SUMIF('SG08'!$B:$B,$B78,'SG08'!K:K)*SG08_+SUMIF('SG09'!$B:$B,$B78,'SG09'!K:K)*SG09_+SUMIF('SG10'!$B:$B,$B78,'SG10'!K:K)*SG10_+SUMIF('SG11'!$B:$B,$B78,'SG11'!K:K)*SG11_+SUMIF('SG12'!$B:$B,$B78,'SG12'!K:K)*SG12_+SUMIF('SG13'!$B:$B,$B78,'SG13'!K:K)*SG13_+SUMIF('SG14'!$B:$B,$B78,'SG14'!K:K)*SG14_+SUMIF('SG15'!$B:$B,$B78,'SG15'!K:K)*SG15_) -> 9472163.7 | L78: =(SUMIF('SG01'!$B:$B,$B78,'SG01'!L:L)*SG01_+SUMIF('SG02'!$B:$B,$B78,'SG02'!L:L)*SG02_+SUMIF('SG03'!$B:$B,$B78,'SG03'!L:L)*SG03_+SUMIF('SG04'!$B:$B,$B78,'SG04'!L:L)*SG04_+SUMIF('SG05'!$B:$B,$B78,'SG05'!L:L)*SG05_+SUMIF('SG06'!$B:$B,$B78,'SG06'!L:L)*SG06_+SUMIF('SG07'!$B:$B,$B78,'SG07'!L:L)*SG07_+SUMIF('SG08'!$B:$B,$B78,'SG08'!L:L)*SG08_+SUMIF('SG09'!$B:$B,$B78,'SG09'!L:L)*SG09_+SUMIF('SG10'!$B:$B,$B78,'SG10'!L:L)*SG10_+SUMIF('SG11'!$B:$B,$B78,'SG11'!L:L)*SG11_+SUMIF('SG12'!$B:$B,$B78,'SG12'!L:L)*SG12_+SUMIF('SG13'!$B:$B,$B78,'SG13'!L:L)*SG13_+SUMIF('SG14'!$B:$B,$B78,'SG14'!L:L)*SG14_+SUMIF('SG15'!$B:$B,$B78,'SG15'!L:L)*SG15_) -> 34227000 | M78: =L78-K78 -> 24754836 | N78: =K78/L78 -> 0.27674537 | O78: =L78/L$10 -> 0.022073918 | P78: =M78/M$10 -> 0.024060775 | Q78: =I78/I$10 -> 0.0034263643 | R78: =I78/$K$5*100 -> 1.4893041 | S78: =R78*T$5 -> 4.3754972 | T78: =IFERROR(S78*G78,0) -> 2722911.7 | V78: =IF(B78<>"",IFERROR(IF($I78>=$X$10,"High","Low"),""),"") -> Low | W78: =IF(B78<>"",IFERROR(IF($L78>=$X$12,"High","Low"),""),"") -> High | X78: =IF(B78<>"",IFERROR(IF(AND(V78="high",W78="high"),"Star",IF(AND(V78="low",W78="high"),"Puzzle",(IF(AND(V78="high",W78="low"),"Horse","Dog")))),""),"") -> Puzzle
A79: 11 | B79: GSNCD017 | C79: =VLOOKUP(B79,'SG01'!$B:$E,2,0) -> Sườn Bò Nướng Thượng Hạng | E79: =VLOOKUP(B79,'SG01'!$B:$E,4,0) -> Phần | F79: =K79/I79 -> #DIV/0! | G79: =L79/I79 -> #DIV/0! | H79: =G79-F79 -> #DIV/0! | I79: =(SUMIF('SG01'!$B:$B,$B79,'SG01'!I:I)*SG01_+SUMIF('SG02'!$B:$B,$B79,'SG02'!I:I)*SG02_+SUMIF('SG03'!$B:$B,$B79,'SG03'!I:I)*SG03_+SUMIF('SG04'!$B:$B,$B79,'SG04'!I:I)*SG04_+SUMIF('SG05'!$B:$B,$B79,'SG05'!I:I)*SG05_+SUMIF('SG06'!$B:$B,$B79,'SG06'!I:I)*SG06_+SUMIF('SG07'!$B:$B,$B79,'SG07'!I:I)*SG07_+SUMIF('SG08'!$B:$B,$B79,'SG08'!I:I)*SG08_+SUMIF('SG09'!$B:$B,$B79,'SG09'!I:I)*SG09_+SUMIF('SG10'!$B:$B,$B79,'SG10'!I:I)*SG10_+SUMIF('SG11'!$B:$B,$B79,'SG11'!I:I)*SG11_+SUMIF('SG12'!$B:$B,$B79,'SG12'!I:I)*SG12_+SUMIF('SG13'!$B:$B,$B79,'SG13'!I:I)*SG13_+SUMIF('SG14'!$B:$B,$B79,'SG14'!I:I)*SG14_+SUMIF('SG15'!$B:$B,$B79,'SG15'!I:I)*SG15_) -> 0 | K79: =(SUMIF('SG01'!$B:$B,$B79,'SG01'!K:K)*SG01_+SUMIF('SG02'!$B:$B,$B79,'SG02'!K:K)*SG02_+SUMIF('SG03'!$B:$B,$B79,'SG03'!K:K)*SG03_+SUMIF('SG04'!$B:$B,$B79,'SG04'!K:K)*SG04_+SUMIF('SG05'!$B:$B,$B79,'SG05'!K:K)*SG05_+SUMIF('SG06'!$B:$B,$B79,'SG06'!K:K)*SG06_+SUMIF('SG07'!$B:$B,$B79,'SG07'!K:K)*SG07_+SUMIF('SG08'!$B:$B,$B79,'SG08'!K:K)*SG08_+SUMIF('SG09'!$B:$B,$B79,'SG09'!K:K)*SG09_+SUMIF('SG10'!$B:$B,$B79,'SG10'!K:K)*SG10_+SUMIF('SG11'!$B:$B,$B79,'SG11'!K:K)*SG11_+SUMIF('SG12'!$B:$B,$B79,'SG12'!K:K)*SG12_+SUMIF('SG13'!$B:$B,$B79,'SG13'!K:K)*SG13_+SUMIF('SG14'!$B:$B,$B79,'SG14'!K:K)*SG14_+SUMIF('SG15'!$B:$B,$B79,'SG15'!K:K)*SG15_) -> 0 | L79: =(SUMIF('SG01'!$B:$B,$B79,'SG01'!L:L)*SG01_+SUMIF('SG02'!$B:$B,$B79,'SG02'!L:L)*SG02_+SUMIF('SG03'!$B:$B,$B79,'SG03'!L:L)*SG03_+SUMIF('SG04'!$B:$B,$B79,'SG04'!L:L)*SG04_+SUMIF('SG05'!$B:$B,$B79,'SG05'!L:L)*SG05_+SUMIF('SG06'!$B:$B,$B79,'SG06'!L:L)*SG06_+SUMIF('SG07'!$B:$B,$B79,'SG07'!L:L)*SG07_+SUMIF('SG08'!$B:$B,$B79,'SG08'!L:L)*SG08_+SUMIF('SG09'!$B:$B,$B79,'SG09'!L:L)*SG09_+SUMIF('SG10'!$B:$B,$B79,'SG10'!L:L)*SG10_+SUMIF('SG11'!$B:$B,$B79,'SG11'!L:L)*SG11_+SUMIF('SG12'!$B:$B,$B79,'SG12'!L:L)*SG12_+SUMIF('SG13'!$B:$B,$B79,'SG13'!L:L)*SG13_+SUMIF('SG14'!$B:$B,$B79,'SG14'!L:L)*SG14_+SUMIF('SG15'!$B:$B,$B79,'SG15'!L:L)*SG15_) -> 0 | M79: =L79-K79 -> 0 | N79: =K79/L79 -> #DIV/0! | O79: =L79/L$10 -> 0 | P79: =M79/M$10 -> 0 | Q79: =I79/I$10 -> 0 | R79: =I79/$K$5*100 -> 0 | S79: =R79*T$5 -> 0 | T79: =IFERROR(S79*G79,0) -> 0 | V79: =IF(B79<>"",IFERROR(IF($I79>=$X$10,"High","Low"),""),"") -> Low | W79: =IF(B79<>"",IFERROR(IF($L79>=$X$12,"High","Low"),""),"") -> Low | X79: =IF(B79<>"",IFERROR(IF(AND(V79="high",W79="high"),"Star",IF(AND(V79="low",W79="high"),"Puzzle",(IF(AND(V79="high",W79="low"),"Horse","Dog")))),""),"") -> Dog
A80: 12 | B80: GSTBO010 | C80: =VLOOKUP(B80,'SG01'!$B:$E,2,0) -> Lưỡi Bò Xốt Hành Baro | E80: =VLOOKUP(B80,'SG01'!$B:$E,4,0) -> Phần | F80: =K80/I80 -> 42556.128 | G80: =L80/I80 -> 122142.86 | H80: =G80-F80 -> 79586.729 | I80: =(SUMIF('SG01'!$B:$B,$B80,'SG01'!I:I)*SG01_+SUMIF('SG02'!$B:$B,$B80,'SG02'!I:I)*SG02_+SUMIF('SG03'!$B:$B,$B80,'SG03'!I:I)*SG03_+SUMIF('SG04'!$B:$B,$B80,'SG04'!I:I)*SG04_+SUMIF('SG05'!$B:$B,$B80,'SG05'!I:I)*SG05_+SUMIF('SG06'!$B:$B,$B80,'SG06'!I:I)*SG06_+SUMIF('SG07'!$B:$B,$B80,'SG07'!I:I)*SG07_+SUMIF('SG08'!$B:$B,$B80,'SG08'!I:I)*SG08_+SUMIF('SG09'!$B:$B,$B80,'SG09'!I:I)*SG09_+SUMIF('SG10'!$B:$B,$B80,'SG10'!I:I)*SG10_+SUMIF('SG11'!$B:$B,$B80,'SG11'!I:I)*SG11_+SUMIF('SG12'!$B:$B,$B80,'SG12'!I:I)*SG12_+SUMIF('SG13'!$B:$B,$B80,'SG13'!I:I)*SG13_+SUMIF('SG14'!$B:$B,$B80,'SG14'!I:I)*SG14_+SUMIF('SG15'!$B:$B,$B80,'SG15'!I:I)*SG15_) -> 84 | K80: =(SUMIF('SG01'!$B:$B,$B80,'SG01'!K:K)*SG01_+SUMIF('SG02'!$B:$B,$B80,'SG02'!K:K)*SG02_+SUMIF('SG03'!$B:$B,$B80,'SG03'!K:K)*SG03_+SUMIF('SG04'!$B:$B,$B80,'SG04'!K:K)*SG04_+SUMIF('SG05'!$B:$B,$B80,'SG05'!K:K)*SG05_+SUMIF('SG06'!$B:$B,$B80,'SG06'!K:K)*SG06_+SUMIF('SG07'!$B:$B,$B80,'SG07'!K:K)*SG07_+SUMIF('SG08'!$B:$B,$B80,'SG08'!K:K)*SG08_+SUMIF('SG09'!$B:$B,$B80,'SG09'!K:K)*SG09_+SUMIF('SG10'!$B:$B,$B80,'SG10'!K:K)*SG10_+SUMIF('SG11'!$B:$B,$B80,'SG11'!K:K)*SG11_+SUMIF('SG12'!$B:$B,$B80,'SG12'!K:K)*SG12_+SUMIF('SG13'!$B:$B,$B80,'SG13'!K:K)*SG13_+SUMIF('SG14'!$B:$B,$B80,'SG14'!K:K)*SG14_+SUMIF('SG15'!$B:$B,$B80,'SG15'!K:K)*SG15_) -> 3574714.8 | L80: =(SUMIF('SG01'!$B:$B,$B80,'SG01'!L:L)*SG01_+SUMIF('SG02'!$B:$B,$B80,'SG02'!L:L)*SG02_+SUMIF('SG03'!$B:$B,$B80,'SG03'!L:L)*SG03_+SUMIF('SG04'!$B:$B,$B80,'SG04'!L:L)*SG04_+SUMIF('SG05'!$B:$B,$B80,'SG05'!L:L)*SG05_+SUMIF('SG06'!$B:$B,$B80,'SG06'!L:L)*SG06_+SUMIF('SG07'!$B:$B,$B80,'SG07'!L:L)*SG07_+SUMIF('SG08'!$B:$B,$B80,'SG08'!L:L)*SG08_+SUMIF('SG09'!$B:$B,$B80,'SG09'!L:L)*SG09_+SUMIF('SG10'!$B:$B,$B80,'SG10'!L:L)*SG10_+SUMIF('SG11'!$B:$B,$B80,'SG11'!L:L)*SG11_+SUMIF('SG12'!$B:$B,$B80,'SG12'!L:L)*SG12_+SUMIF('SG13'!$B:$B,$B80,'SG13'!L:L)*SG13_+SUMIF('SG14'!$B:$B,$B80,'SG14'!L:L)*SG14_+SUMIF('SG15'!$B:$B,$B80,'SG15'!L:L)*SG15_) -> 10260000 | M80: =L80-K80 -> 6685285.2 | N80: =K80/L80 -> 0.34841275 | O80: =L80/L$10 -> 0.0066169514 | P80: =M80/M$10 -> 0.0064978473 | Q80: =I80/I$10 -> 0.0052329928 | R80: =I80/$K$5*100 -> 2.2745735 | S80: =R80*T$5 -> 6.6825776 | T80: =IFERROR(S80*G80,0) -> 816229.12 | V80: =IF(B80<>"",IFERROR(IF($I80>=$X$10,"High","Low"),""),"") -> Low | W80: =IF(B80<>"",IFERROR(IF($L80>=$X$12,"High","Low"),""),"") -> High | X80: =IF(B80<>"",IFERROR(IF(AND(V80="high",W80="high"),"Star",IF(AND(V80="low",W80="high"),"Puzzle",(IF(AND(V80="high",W80="low"),"Horse","Dog")))),""),"") -> Puzzle
... A82: 14 | B82: GSTBO018 | C82: =VLOOKUP(B82,'SG01'!$B:$E,2,0) -> Lõi Vai Xốt Trái Cây | E82: =VLOOKUP(B82,'SG01'!$B:$E,4,0) -> Phần | F82: =K82/I82 -> 64430.733 | G82: =L82/I82 -> 178191.49 | H82: =G82-F82 -> 113760.76 | I82: =(SUMIF('SG01'!$B:$B,$B82,'SG01'!I:I)*SG01_+SUMIF('SG02'!$B:$B,$B82,'SG02'!I:I)*SG02_+SUMIF('SG03'!$B:$B,$B82,'SG03'!I:I)*SG03_+SUMIF('SG04'!$B:$B,$B82,'SG04'!I:I)*SG04_+SUMIF('SG05'!$B:$B,$B82,'SG05'!I:I)*SG05_+SUMIF('SG06'!$B:$B,$B82,'SG06'!I:I)*SG06_+SUMIF('SG07'!$B:$B,$B82,'SG07'!I:I)*SG07_+SUMIF('SG08'!$B:$B,$B82,'SG08'!I:I)*SG08_+SUMIF('SG09'!$B:$B,$B82,'SG09'!I:I)*SG09_+SUMIF('SG10'!$B:$B,$B82,'SG10'!I:I)*SG10_+SUMIF('SG11'!$B:$B,$B82,'SG11'!I:I)*SG11_+SUMIF('SG12'!$B:$B,$B82,'SG12'!I:I)*SG12_+SUMIF('SG13'!$B:$B,$B82,'SG13'!I:I)*SG13_+SUMIF('SG14'!$B:$B,$B82,'SG14'!I:I)*SG14_+SUMIF('SG15'!$B:$B,$B82,'SG15'!I:I)*SG15_) -> 47 | K82: =(SUMIF('SG01'!$B:$B,$B82,'SG01'!K:K)*SG01_+SUMIF('SG02'!$B:$B,$B82,'SG02'!K:K)*SG02_+SUMIF('SG03'!$B:$B,$B82,'SG03'!K:K)*SG03_+SUMIF('SG04'!$B:$B,$B82,'SG04'!K:K)*SG04_+SUMIF('SG05'!$B:$B,$B82,'SG05'!K:K)*SG05_+SUMIF('SG06'!$B:$B,$B82,'SG06'!K:K)*SG06_+SUMIF('SG07'!$B:$B,$B82,'SG07'!K:K)*SG07_+SUMIF('SG08'!$B:$B,$B82,'SG08'!K:K)*SG08_+SUMIF('SG09'!$B:$B,$B82,'SG09'!K:K)*SG09_+SUMIF('SG10'!$B:$B,$B82,'SG10'!K:K)*SG10_+SUMIF('SG11'!$B:$B,$B82,'SG11'!K:K)*SG11_+SUMIF('SG12'!$B:$B,$B82,'SG12'!K:K)*SG12_+SUMIF('SG13'!$B:$B,$B82,'SG13'!K:K)*SG13_+SUMIF('SG14'!$B:$B,$B82,'SG14'!K:K)*SG14_+SUMIF('SG15'!$B:$B,$B82,'SG15'!K:K)*SG15_) -> 3028244.5 | L82: =(SUMIF('SG01'!$B:$B,$B82,'SG01'!L:L)*SG01_+SUMIF('SG02'!$B:$B,$B82,'SG02'!L:L)*SG02_+SUMIF('SG03'!$B:$B,$B82,'SG03'!L:L)*SG03_+SUMIF('SG04'!$B:$B,$B82,'SG04'!L:L)*SG04_+SUMIF('SG05'!$B:$B,$B82,'SG05'!L:L)*SG05_+SUMIF('SG06'!$B:$B,$B82,'SG06'!L:L)*SG06_+SUMIF('SG07'!$B:$B,$B82,'SG07'!L:L)*SG07_+SUMIF('SG08'!$B:$B,$B82,'SG08'!L:L)*SG08_+SUMIF('SG09'!$B:$B,$B82,'SG09'!L:L)*SG09_+SUMIF('SG10'!$B:$B,$B82,'SG10'!L:L)*SG10_+SUMIF('SG11'!$B:$B,$B82,'SG11'!L:L)*SG11_+SUMIF('SG12'!$B:$B,$B82,'SG12'!L:L)*SG12_+SUMIF('SG13'!$B:$B,$B82,'SG13'!L:L)*SG13_+SUMIF('SG14'!$B:$B,$B82,'SG14'!L:L)*SG14_+SUMIF('SG15'!$B:$B,$B82,'SG15'!L:L)*SG15_) -> 8375000 | M82: =L82-K82 -> 5346755.5 | N82: =K82/L82 -> 0.36158143 | O82: =L82/L$10 -> 0.0054012639 | P82: =M82/M$10 -> 0.0051968465 | Q82: =I82/I$10 -> 0.0029279841 | R82: =I82/$K$5*100 -> 1.272678 | S82: =R82*T$5 -> 3.7390613 | T82: =IFERROR(S82*G82,0) -> 666268.89 | V82: =IF(B82<>"",IFERROR(IF($I82>=$X$10,"High","Low"),""),"") -> Low | W82: =IF(B82<>"",IFERROR(IF($L82>=$X$12,"High","Low"),""),"") -> High | X82: =IF(B82<>"",IFERROR(IF(AND(V82="high",W82="high"),"Star",IF(AND(V82="low",W82="high"),"Puzzle",(IF(AND(V82="high",W82="low"),"Horse","Dog")))),""),"") -> Puzzle
S83: =R83*T$5 -> 0 | T83: =IFERROR(S83*G83,0) -> 0 | V83: =IF(B83<>"",IFERROR(IF($I83>=$X$10,"High","Low"),""),"")
B84: THITHEO.GSG | C84: THỊT HEO | I84: =SUBTOTAL(9,I85:I90) -> 750 | K84: =SUBTOTAL(9,K85:K90) -> 23825924 | L84: =SUBTOTAL(9,L85:L90) -> 75740000 | M84: =SUBTOTAL(9,M85:M90) -> 51914076 | N84: =K84/L84 -> 0.31457518 | O84: =L84/L$10 -> 0.048846774 | P84: =M84/M$10 -> 0.050458541 | Q84: =I84/I$10 -> 0.04672315 | R84: =I84/$K$5*100 -> 20.308692 | S84: =R84*T$5 -> 59.665871 | T84: =IFERROR(S84*G84,0) -> 0 | V84: =IF(B84<>"",IFERROR(IF($I84>=$X$10,"High","Low"),""),"") -> High
A85: 1 | B85: GSHGC012 | C85: =VLOOKUP(B85,'SG02'!$B:$E,2,0) -> Chẳng Dừng Xốt Shio | E85: =VLOOKUP(B85,'SG01'!$B:$E,4,0) -> Phần | F85: =K85/I85 -> 31568.938 | G85: =L85/I85 -> 101213.74 | H85: =G85-F85 -> 69644.802 | I85: =(SUMIF('SG01'!$B:$B,$B85,'SG01'!I:I)*SG01_+SUMIF('SG02'!$B:$B,$B85,'SG02'!I:I)*SG02_+SUMIF('SG03'!$B:$B,$B85,'SG03'!I:I)*SG03_+SUMIF('SG04'!$B:$B,$B85,'SG04'!I:I)*SG04_+SUMIF('SG05'!$B:$B,$B85,'SG05'!I:I)*SG05_+SUMIF('SG06'!$B:$B,$B85,'SG06'!I:I)*SG06_+SUMIF('SG07'!$B:$B,$B85,'SG07'!I:I)*SG07_+SUMIF('SG08'!$B:$B,$B85,'SG08'!I:I)*SG08_+SUMIF('SG09'!$B:$B,$B85,'SG09'!I:I)*SG09_+SUMIF('SG10'!$B:$B,$B85,'SG10'!I:I)*SG10_+SUMIF('SG11'!$B:$B,$B85,'SG11'!I:I)*SG11_+SUMIF('SG12'!$B:$B,$B85,'SG12'!I:I)*SG12_+SUMIF('SG13'!$B:$B,$B85,'SG13'!I:I)*SG13_+SUMIF('SG14'!$B:$B,$B85,'SG14'!I:I)*SG14_+SUMIF('SG15'!$B:$B,$B85,'SG15'!I:I)*SG15_) -> 131 | K85: =(SUMIF('SG01'!$B:$B,$B85,'SG01'!K:K)*SG01_+SUMIF('SG02'!$B:$B,$B85,'SG02'!K:K)*SG02_+SUMIF('SG03'!$B:$B,$B85,'SG03'!K:K)*SG03_+SUMIF('SG04'!$B:$B,$B85,'SG04'!K:K)*SG04_+SUMIF('SG05'!$B:$B,$B85,'SG05'!K:K)*SG05_+SUMIF('SG06'!$B:$B,$B85,'SG06'!K:K)*SG06_+SUMIF('SG07'!$B:$B,$B85,'SG07'!K:K)*SG07_+SUMIF('SG08'!$B:$B,$B85,'SG08'!K:K)*SG08_+SUMIF('SG09'!$B:$B,$B85,'SG09'!K:K)*SG09_+SUMIF('SG10'!$B:$B,$B85,'SG10'!K:K)*SG10_+SUMIF('SG11'!$B:$B,$B85,'SG11'!K:K)*SG11_+SUMIF('SG12'!$B:$B,$B85,'SG12'!K:K)*SG12_+SUMIF('SG13'!$B:$B,$B85,'SG13'!K:K)*SG13_+SUMIF('SG14'!$B:$B,$B85,'SG14'!K:K)*SG14_+SUMIF('SG15'!$B:$B,$B85,'SG15'!K:K)*SG15_) -> 4135530.9 | L85: =(SUMIF('SG01'!$B:$B,$B85,'SG01'!L:L)*SG01_+SUMIF('SG02'!$B:$B,$B85,'SG02'!L:L)*SG02_+SUMIF('SG03'!$B:$B,$B85,'SG03'!L:L)*SG03_+SUMIF('SG04'!$B:$B,$B85,'SG04'!L:L)*SG04_+SUMIF('SG05'!$B:$B,$B85,'SG05'!L:L)*SG05_+SUMIF('SG06'!$B:$B,$B85,'SG06'!L:L)*SG06_+SUMIF('SG07'!$B:$B,$B85,'SG07'!L:L)*SG07_+SUMIF('SG08'!$B:$B,$B85,'SG08'!L:L)*SG08_+SUMIF('SG09'!$B:$B,$B85,'SG09'!L:L)*SG09_+SUMIF('SG10'!$B:$B,$B85,'SG10'!L:L)*SG10_+SUMIF('SG11'!$B:$B,$B85,'SG11'!L:L)*SG11_+SUMIF('SG12'!$B:$B,$B85,'SG12'!L:L)*SG12_+SUMIF('SG13'!$B:$B,$B85,'SG13'!L:L)*SG13_+SUMIF('SG14'!$B:$B,$B85,'SG14'!L:L)*SG14_+SUMIF('SG15'!$B:$B,$B85,'SG15'!L:L)*SG15_) -> 13259000 | M85: =L85-K85 -> 9123469.1 | N85: =K85/L85 -> 0.31190368 | O85: =L85/L$10 -> 0.0085510876 | P85: =M85/M$10 -> 0.0088676708 | Q85: =I85/I$10 -> 0.0081609768 | R85: =I85/$K$5*100 -> 3.5472516 | S85: =R85*T$5 -> 10.421639 | T85: =IFERROR(S85*G85,0) -> 1054813 | V85: =IF(B85<>"",IFERROR(IF($I85>=$X$10,"High","Low"),""),"") -> High | W85: =IF(B85<>"",IFERROR(IF($L85>=$X$12,"High","Low"),""),"") -> High | X85: =IF(B85<>"",IFERROR(IF(AND(V85="high",W85="high"),"Star",IF(AND(V85="low",W85="high"),"Puzzle",(IF(AND(V85="high",W85="low"),"Horse","Dog")))),""),"") -> Star
A86: 2 | B86: GSHGC013 | C86: =VLOOKUP(B86,'SG02'!$B:$E,2,0) -> Ba Chỉ Heo Xốt Shio | E86: =VLOOKUP(B86,'SG01'!$B:$E,4,0) -> Phần | F86: =K86/I86 -> 26009.344 | G86: =L86/I86 -> 101321.43 | H86: =G86-F86 -> 75312.085 | I86: =(SUMIF('SG01'!$B:$B,$B86,'SG01'!I:I)*SG01_+SUMIF('SG02'!$B:$B,$B86,'SG02'!I:I)*SG02_+SUMIF('SG03'!$B:$B,$B86,'SG03'!I:I)*SG03_+SUMIF('SG04'!$B:$B,$B86,'SG04'!I:I)*SG04_+SUMIF('SG05'!$B:$B,$B86,'SG05'!I:I)*SG05_+SUMIF('SG06'!$B:$B,$B86,'SG06'!I:I)*SG06_+SUMIF('SG07'!$B:$B,$B86,'SG07'!I:I)*SG07_+SUMIF('SG08'!$B:$B,$B86,'SG08'!I:I)*SG08_+SUMIF('SG09'!$B:$B,$B86,'SG09'!I:I)*SG09_+SUMIF('SG10'!$B:$B,$B86,'SG10'!I:I)*SG10_+SUMIF('SG11'!$B:$B,$B86,'SG11'!I:I)*SG11_+SUMIF('SG12'!$B:$B,$B86,'SG12'!I:I)*SG12_+SUMIF('SG13'!$B:$B,$B86,'SG13'!I:I)*SG13_+SUMIF('SG14'!$B:$B,$B86,'SG14'!I:I)*SG14_+SUMIF('SG15'!$B:$B,$B86,'SG15'!I:I)*SG15_) -> 168 | K86: =(SUMIF('SG01'!$B:$B,$B86,'SG01'!K:K)*SG01_+SUMIF('SG02'!$B:$B,$B86,'SG02'!K:K)*SG02_+SUMIF('SG03'!$B:$B,$B86,'SG03'!K:K)*SG03_+SUMIF('SG04'!$B:$B,$B86,'SG04'!K:K)*SG04_+SUMIF('SG05'!$B:$B,$B86,'SG05'!K:K)*SG05_+SUMIF('SG06'!$B:$B,$B86,'SG06'!K:K)*SG06_+SUMIF('SG07'!$B:$B,$B86,'SG07'!K:K)*SG07_+SUMIF('SG08'!$B:$B,$B86,'SG08'!K:K)*SG08_+SUMIF('SG09'!$B:$B,$B86,'SG09'!K:K)*SG09_+SUMIF('SG10'!$B:$B,$B86,'SG10'!K:K)*SG10_+SUMIF('SG11'!$B:$B,$B86,'SG11'!K:K)*SG11_+SUMIF('SG12'!$B:$B,$B86,'SG12'!K:K)*SG12_+SUMIF('SG13'!$B:$B,$B86,'SG13'!K:K)*SG13_+SUMIF('SG14'!$B:$B,$B86,'SG14'!K:K)*SG14_+SUMIF('SG15'!$B:$B,$B86,'SG15'!K:K)*SG15_) -> 4369569.8 | L86: =(SUMIF('SG01'!$B:$B,$B86,'SG01'!L:L)*SG01_+SUMIF('SG02'!$B:$B,$B86,'SG02'!L:L)*SG02_+SUMIF('SG03'!$B:$B,$B86,'SG03'!L:L)*SG03_+SUMIF('SG04'!$B:$B,$B86,'SG04'!L:L)*SG04_+SUMIF('SG05'!$B:$B,$B86,'SG05'!L:L)*SG05_+SUMIF('SG06'!$B:$B,$B86,'SG06'!L:L)*SG06_+SUMIF('SG07'!$B:$B,$B86,'SG07'!L:L)*SG07_+SUMIF('SG08'!$B:$B,$B86,'SG08'!L:L)*SG08_+SUMIF('SG09'!$B:$B,$B86,'SG09'!L:L)*SG09_+SUMIF('SG10'!$B:$B,$B86,'SG10'!L:L)*SG10_+SUMIF('SG11'!$B:$B,$B86,'SG11'!L:L)*SG11_+SUMIF('SG12'!$B:$B,$B86,'SG12'!L:L)*SG12_+SUMIF('SG13'!$B:$B,$B86,'SG13'!L:L)*SG13_+SUMIF('SG14'!$B:$B,$B86,'SG14'!L:L)*SG14_+SUMIF('SG15'!$B:$B,$B86,'SG15'!L:L)*SG15_) -> 17022000 | M86: =L86-K86 -> 12652430 | N86: =K86/L86 -> 0.25670131 | O86: =L86/L$10 -> 0.010977948 | P86: =M86/M$10 -> 0.012297689 | Q86: =I86/I$10 -> 0.010465986 | R86: =I86/$K$5*100 -> 4.549147 | S86: =R86*T$5 -> 13.365155 | T86: =IFERROR(S86*G86,0) -> 1354176.6 | V86: =IF(B86<>"",IFERROR(IF($I86>=$X$10,"High","Low"),""),"") -> High | W86: =IF(B86<>"",IFERROR(IF($L86>=$X$12,"High","Low"),""),"") -> High | X86: =IF(B86<>"",IFERROR(IF(AND(V86="high",W86="high"),"Star",IF(AND(V86="low",W86="high"),"Puzzle",(IF(AND(V86="high",W86="low"),"Horse","Dog")))),""),"") -> Star
A87: 3 | B87: GSHGC014 | C87: =VLOOKUP(B87,'SG02'!$B:$E,2,0) -> Ba Chỉ Heo Xốt Trái Cây | E87: =VLOOKUP(B87,'SG01'!$B:$E,4,0) -> Phần | F87: =K87/I87 -> 27040.044 | G87: =L87/I87 -> 100666.67 | H87: =G87-F87 -> 73626.623 | I87: =(SUMIF('SG01'!$B:$B,$B87,'SG01'!I:I)*SG01_+SUMIF('SG02'!$B:$B,$B87,'SG02'!I:I)*SG02_+SUMIF('SG03'!$B:$B,$B87,'SG03'!I:I)*SG03_+SUMIF('SG04'!$B:$B,$B87,'SG04'!I:I)*SG04_+SUMIF('SG05'!$B:$B,$B87,'SG05'!I:I)*SG05_+SUMIF('SG06'!$B:$B,$B87,'SG06'!I:I)*SG06_+SUMIF('SG07'!$B:$B,$B87,'SG07'!I:I)*SG07_+SUMIF('SG08'!$B:$B,$B87,'SG08'!I:I)*SG08_+SUMIF('SG09'!$B:$B,$B87,'SG09'!I:I)*SG09_+SUMIF('SG10'!$B:$B,$B87,'SG10'!I:I)*SG10_+SUMIF('SG11'!$B:$B,$B87,'SG11'!I:I)*SG11_+SUMIF('SG12'!$B:$B,$B87,'SG12'!I:I)*SG12_+SUMIF('SG13'!$B:$B,$B87,'SG13'!I:I)*SG13_+SUMIF('SG14'!$B:$B,$B87,'SG14'!I:I)*SG14_+SUMIF('SG15'!$B:$B,$B87,'SG15'!I:I)*SG15_) -> 120 | K87: =(SUMIF('SG01'!$B:$B,$B87,'SG01'!K:K)*SG01_+SUMIF('SG02'!$B:$B,$B87,'SG02'!K:K)*SG02_+SUMIF('SG03'!$B:$B,$B87,'SG03'!K:K)*SG03_+SUMIF('SG04'!$B:$B,$B87,'SG04'!K:K)*SG04_+SUMIF('SG05'!$B:$B,$B87,'SG05'!K:K)*SG05_+SUMIF('SG06'!$B:$B,$B87,'SG06'!K:K)*SG06_+SUMIF('SG07'!$B:$B,$B87,'SG07'!K:K)*SG07_+SUMIF('SG08'!$B:$B,$B87,'SG08'!K:K)*SG08_+SUMIF('SG09'!$B:$B,$B87,'SG09'!K:K)*SG09_+SUMIF('SG10'!$B:$B,$B87,'SG10'!K:K)*SG10_+SUMIF('SG11'!$B:$B,$B87,'SG11'!K:K)*SG11_+SUMIF('SG12'!$B:$B,$B87,'SG12'!K:K)*SG12_+SUMIF('SG13'!$B:$B,$B87,'SG13'!K:K)*SG13_+SUMIF('SG14'!$B:$B,$B87,'SG14'!K:K)*SG14_+SUMIF('SG15'!$B:$B,$B87,'SG15'!K:K)*SG15_) -> 3244805.3 | L87: =(SUMIF('SG01'!$B:$B,$B87,'SG01'!L:L)*SG01_+SUMIF('SG02'!$B:$B,$B87,'SG02'!L:L)*SG02_+SUMIF('SG03'!$B:$B,$B87,'SG03'!L:L)*SG03_+SUMIF('SG04'!$B:$B,$B87,'SG04'!L:L)*SG04_+SUMIF('SG05'!$B:$B,$B87,'SG05'!L:L)*SG05_+SUMIF('SG06'!$B:$B,$B87,'SG06'!L:L)*SG06_+SUMIF('SG07'!$B:$B,$B87,'SG07'!L:L)*SG07_+SUMIF('SG08'!$B:$B,$B87,'SG08'!L:L)*SG08_+SUMIF('SG09'!$B:$B,$B87,'SG09'!L:L)*SG09_+SUMIF('SG10'!$B:$B,$B87,'SG10'!L:L)*SG10_+SUMIF('SG11'!$B:$B,$B87,'SG11'!L:L)*SG11_+SUMIF('SG12'!$B:$B,$B87,'SG12'!L:L)*SG12_+SUMIF('SG13'!$B:$B,$B87,'SG13'!L:L)*SG13_+SUMIF('SG14'!$B:$B,$B87,'SG14'!L:L)*SG14_+SUMIF('SG15'!$B:$B,$B87,'SG15'!L:L)*SG15_) -> 12080000 | M87: =L87-K87 -> 8835194.7 | N87: =K87/L87 -> 0.26860971 | O87: =L87/L$10 -> 0.0077907186 | P87: =M87/M$10 -> 0.0085874789 | Q87: =I87/I$10 -> 0.007475704 | R87: =I87/$K$5*100 -> 3.2493907 | S87: =R87*T$5 -> 9.5465394 | T87: =IFERROR(S87*G87,0) -> 961018.3 | V87: =IF(B87<>"",IFERROR(IF($I87>=$X$10,"High","Low"),""),"") -> High | W87: =IF(B87<>"",IFERROR(IF($L87>=$X$12,"High","Low"),""),"") -> High | X87: =IF(B87<>"",IFERROR(IF(AND(V87="high",W87="high"),"Star",IF(AND(V87="low",W87="high"),"Puzzle",(IF(AND(V87="high",W87="low"),"Horse","Dog")))),""),"") -> Star
A88: 4 | B88: GSHGC015 | C88: =VLOOKUP(B88,'SG02'!$B:$E,2,0) -> Má Heo Xốt Trái Cây | E88: =VLOOKUP(B88,'SG01'!$B:$E,4,0) -> Phần | F88: =K88/I88 -> 36727.953 | G88: =L88/I88 -> 100583.33 | H88: =G88-F88 -> 63855.38 | I88: =(SUMIF('SG01'!$B:$B,$B88,'SG01'!I:I)*SG01_+SUMIF('SG02'!$B:$B,$B88,'SG02'!I:I)*SG02_+SUMIF('SG03'!$B:$B,$B88,'SG03'!I:I)*SG03_+SUMIF('SG04'!$B:$B,$B88,'SG04'!I:I)*SG04_+SUMIF('SG05'!$B:$B,$B88,'SG05'!I:I)*SG05_+SUMIF('SG06'!$B:$B,$B88,'SG06'!I:I)*SG06_+SUMIF('SG07'!$B:$B,$B88,'SG07'!I:I)*SG07_+SUMIF('SG08'!$B:$B,$B88,'SG08'!I:I)*SG08_+SUMIF('SG09'!$B:$B,$B88,'SG09'!I:I)*SG09_+SUMIF('SG10'!$B:$B,$B88,'SG10'!I:I)*SG10_+SUMIF('SG11'!$B:$B,$B88,'SG11'!I:I)*SG11_+SUMIF('SG12'!$B:$B,$B88,'SG12'!I:I)*SG12_+SUMIF('SG13'!$B:$B,$B88,'SG13'!I:I)*SG13_+SUMIF('SG14'!$B:$B,$B88,'SG14'!I:I)*SG14_+SUMIF('SG15'!$B:$B,$B88,'SG15'!I:I)*SG15_) -> 120 | K88: =(SUMIF('SG01'!$B:$B,$B88,'SG01'!K:K)*SG01_+SUMIF('SG02'!$B:$B,$B88,'SG02'!K:K)*SG02_+SUMIF('SG03'!$B:$B,$B88,'SG03'!K:K)*SG03_+SUMIF('SG04'!$B:$B,$B88,'SG04'!K:K)*SG04_+SUMIF('SG05'!$B:$B,$B88,'SG05'!K:K)*SG05_+SUMIF('SG06'!$B:$B,$B88,'SG06'!K:K)*SG06_+SUMIF('SG07'!$B:$B,$B88,'SG07'!K:K)*SG07_+SUMIF('SG08'!$B:$B,$B88,'SG08'!K:K)*SG08_+SUMIF('SG09'!$B:$B,$B88,'SG09'!K:K)*SG09_+SUMIF('SG10'!$B:$B,$B88,'SG10'!K:K)*SG10_+SUMIF('SG11'!$B:$B,$B88,'SG11'!K:K)*SG11_+SUMIF('SG12'!$B:$B,$B88,'SG12'!K:K)*SG12_+SUMIF('SG13'!$B:$B,$B88,'SG13'!K:K)*SG13_+SUMIF('SG14'!$B:$B,$B88,'SG14'!K:K)*SG14_+SUMIF('SG15'!$B:$B,$B88,'SG15'!K:K)*SG15_) -> 4407354.4 | L88: =(SUMIF('SG01'!$B:$B,$B88,'SG01'!L:L)*SG01_+SUMIF('SG02'!$B:$B,$B88,'SG02'!L:L)*SG02_+SUMIF('SG03'!$B:$B,$B88,'SG03'!L:L)*SG03_+SUMIF('SG04'!$B:$B,$B88,'SG04'!L:L)*SG04_+SUMIF('SG05'!$B:$B,$B88,'SG05'!L:L)*SG05_+SUMIF('SG06'!$B:$B,$B88,'SG06'!L:L)*SG06_+SUMIF('SG07'!$B:$B,$B88,'SG07'!L:L)*SG07_+SUMIF('SG08'!$B:$B,$B88,'SG08'!L:L)*SG08_+SUMIF('SG09'!$B:$B,$B88,'SG09'!L:L)*SG09_+SUMIF('SG10'!$B:$B,$B88,'SG10'!L:L)*SG10_+SUMIF('SG11'!$B:$B,$B88,'SG11'!L:L)*SG11_+SUMIF('SG12'!$B:$B,$B88,'SG12'!L:L)*SG12_+SUMIF('SG13'!$B:$B,$B88,'SG13'!L:L)*SG13_+SUMIF('SG14'!$B:$B,$B88,'SG14'!L:L)*SG14_+SUMIF('SG15'!$B:$B,$B88,'SG15'!L:L)*SG15_) -> 12070000 | M88: =L88-K88 -> 7662645.6 | N88: =K88/L88 -> 0.3651495 | O88: =L88/L$10 -> 0.0077842693 | P88: =M88/M$10 -> 0.007447805 | Q88: =I88/I$10 -> 0.007475704 | R88: =I88/$K$5*100 -> 3.2493907 | S88: =R88*T$5 -> 9.5465394 | T88: =IFERROR(S88*G88,0) -> 960222.75 | V88: =IF(B88<>"",IFERROR(IF($I88>=$X$10,"High","Low"),""),"") -> High | W88: =IF(B88<>"",IFERROR(IF($L88>=$X$12,"High","Low"),""),"") -> High | X88: =IF(B88<>"",IFERROR(IF(AND(V88="high",W88="high"),"Star",IF(AND(V88="low",W88="high"),"Puzzle",(IF(AND(V88="high",W88="low"),"Horse","Dog")))),""),"") -> Star
A89: 5 | B89: GSHGC016 | C89: =VLOOKUP(B89,'SG02'!$B:$E,2,0) -> Má Heo Xốt BBQ | E89: =VLOOKUP(B89,'SG01'!$B:$E,4,0) -> Phần | F89: =K89/I89 -> 36344.378 | G89: =L89/I89 -> 100990.52 | H89: =G89-F89 -> 64646.143 | I89: =(SUMIF('SG01'!$B:$B,$B89,'SG01'!I:I)*SG01_+SUMIF('SG02'!$B:$B,$B89,'SG02'!I:I)*SG02_+SUMIF('SG03'!$B:$B,$B89,'SG03'!I:I)*SG03_+SUMIF('SG04'!$B:$B,$B89,'SG04'!I:I)*SG04_+SUMIF('SG05'!$B:$B,$B89,'SG05'!I:I)*SG05_+SUMIF('SG06'!$B:$B,$B89,'SG06'!I:I)*SG06_+SUMIF('SG07'!$B:$B,$B89,'SG07'!I:I)*SG07_+SUMIF('SG08'!$B:$B,$B89,'SG08'!I:I)*SG08_+SUMIF('SG09'!$B:$B,$B89,'SG09'!I:I)*SG09_+SUMIF('SG10'!$B:$B,$B89,'SG10'!I:I)*SG10_+SUMIF('SG11'!$B:$B,$B89,'SG11'!I:I)*SG11_+SUMIF('SG12'!$B:$B,$B89,'SG12'!I:I)*SG12_+SUMIF('SG13'!$B:$B,$B89,'SG13'!I:I)*SG13_+SUMIF('SG14'!$B:$B,$B89,'SG14'!I:I)*SG14_+SUMIF('SG15'!$B:$B,$B89,'SG15'!I:I)*SG15_) -> 211 | K89: =(SUMIF('SG01'!$B:$B,$B89,'SG01'!K:K)*SG01_+SUMIF('SG02'!$B:$B,$B89,'SG02'!K:K)*SG02_+SUMIF('SG03'!$B:$B,$B89,'SG03'!K:K)*SG03_+SUMIF('SG04'!$B:$B,$B89,'SG04'!K:K)*SG04_+SUMIF('SG05'!$B:$B,$B89,'SG05'!K:K)*SG05_+SUMIF('SG06'!$B:$B,$B89,'SG06'!K:K)*SG06_+SUMIF('SG07'!$B:$B,$B89,'SG07'!K:K)*SG07_+SUMIF('SG08'!$B:$B,$B89,'SG08'!K:K)*SG08_+SUMIF('SG09'!$B:$B,$B89,'SG09'!K:K)*SG09_+SUMIF('SG10'!$B:$B,$B89,'SG10'!K:K)*SG10_+SUMIF('SG11'!$B:$B,$B89,'SG11'!K:K)*SG11_+SUMIF('SG12'!$B:$B,$B89,'SG12'!K:K)*SG12_+SUMIF('SG13'!$B:$B,$B89,'SG13'!K:K)*SG13_+SUMIF('SG14'!$B:$B,$B89,'SG14'!K:K)*SG14_+SUMIF('SG15'!$B:$B,$B89,'SG15'!K:K)*SG15_) -> 7668663.8 | L89: =(SUMIF('SG01'!$B:$B,$B89,'SG01'!L:L)*SG01_+SUMIF('SG02'!$B:$B,$B89,'SG02'!L:L)*SG02_+SUMIF('SG03'!$B:$B,$B89,'SG03'!L:L)*SG03_+SUMIF('SG04'!$B:$B,$B89,'SG04'!L:L)*SG04_+SUMIF('SG05'!$B:$B,$B89,'SG05'!L:L)*SG05_+SUMIF('SG06'!$B:$B,$B89,'SG06'!L:L)*SG06_+SUMIF('SG07'!$B:$B,$B89,'SG07'!L:L)*SG07_+SUMIF('SG08'!$B:$B,$B89,'SG08'!L:L)*SG08_+SUMIF('SG09'!$B:$B,$B89,'SG09'!L:L)*SG09_+SUMIF('SG10'!$B:$B,$B89,'SG10'!L:L)*SG10_+SUMIF('SG11'!$B:$B,$B89,'SG11'!L:L)*SG11_+SUMIF('SG12'!$B:$B,$B89,'SG12'!L:L)*SG12_+SUMIF('SG13'!$B:$B,$B89,'SG13'!L:L)*SG13_+SUMIF('SG14'!$B:$B,$B89,'SG14'!L:L)*SG14_+SUMIF('SG15'!$B:$B,$B89,'SG15'!L:L)*SG15_) -> 21309000 | M89: =L89-K89 -> 13640336 | N89: =K89/L89 -> 0.3598791 | O89: =L89/L$10 -> 0.01374275 | P89: =M89/M$10 -> 0.013257897 | Q89: =I89/I$10 -> 0.013144779 | R89: =I89/$K$5*100 -> 5.713512 | S89: =R89*T$5 -> 16.785998 | T89: =IFERROR(S89*G89,0) -> 1695226.7 | V89: =IF(B89<>"",IFERROR(IF($I89>=$X$10,"High","Low"),""),"") -> High | W89: =IF(B89<>"",IFERROR(IF($L89>=$X$12,"High","Low"),""),"") -> High | X89: =IF(B89<>"",IFERROR(IF(AND(V89="high",W89="high"),"Star",IF(AND(V89="low",W89="high"),"Puzzle",(IF(AND(V89="high",W89="low"),"Horse","Dog")))),""),"") -> Star
S90: =R90*T$5 -> 0 | T90: =IFERROR(S90*G90,0) -> 0
B91: HSAN.GSG | C91: HẢI SẢN | I91: =SUBTOTAL(9,I92:I98) -> 521 | K91: =SUBTOTAL(9,K92:K98) -> 21202070 | L91: =SUBTOTAL(9,L92:L98) -> 66870000 | M91: =SUBTOTAL(9,M92:M98) -> 45667930 | N91: =K91/L91 -> 0.317064 | O91: =L91/L$10 -> 0.043126271 | P91: =M91/M$10 -> 0.044387521 | Q91: =I91/I$10 -> 0.032457015 | R91: =I91/$K$5*100 -> 14.107771 | S91: =R91*T$5 -> 41.447892 | T91: =IFERROR(S91*G91,0) -> 0
A92: 1 | B92: GSHAS001 | C92: =VLOOKUP(B92,'SG01'!$B:$E,2,0) -> Tôm Nướng Xốt Bơ Tỏi | E92: =VLOOKUP(B92,'SG01'!$B:$E,4,0) -> Phần | F92: =K92/I92 -> 33913.72 | G92: =L92/I92 -> 90861.702 | H92: =G92-F92 -> 56947.982 | I92: =(SUMIF('SG01'!$B:$B,$B92,'SG01'!I:I)*SG01_+SUMIF('SG02'!$B:$B,$B92,'SG02'!I:I)*SG02_+SUMIF('SG03'!$B:$B,$B92,'SG03'!I:I)*SG03_+SUMIF('SG04'!$B:$B,$B92,'SG04'!I:I)*SG04_+SUMIF('SG05'!$B:$B,$B92,'SG05'!I:I)*SG05_+SUMIF('SG06'!$B:$B,$B92,'SG06'!I:I)*SG06_+SUMIF('SG07'!$B:$B,$B92,'SG07'!I:I)*SG07_+SUMIF('SG08'!$B:$B,$B92,'SG08'!I:I)*SG08_+SUMIF('SG09'!$B:$B,$B92,'SG09'!I:I)*SG09_+SUMIF('SG10'!$B:$B,$B92,'SG10'!I:I)*SG10_+SUMIF('SG11'!$B:$B,$B92,'SG11'!I:I)*SG11_+SUMIF('SG12'!$B:$B,$B92,'SG12'!I:I)*SG12_+SUMIF('SG13'!$B:$B,$B92,'SG13'!I:I)*SG13_+SUMIF('SG14'!$B:$B,$B92,'SG14'!I:I)*SG14_+SUMIF('SG15'!$B:$B,$B92,'SG15'!I:I)*SG15_) -> 94 | K92: =(SUMIF('SG01'!$B:$B,$B92,'SG01'!K:K)*SG01_+SUMIF('SG02'!$B:$B,$B92,'SG02'!K:K)*SG02_+SUMIF('SG03'!$B:$B,$B92,'SG03'!K:K)*SG03_+SUMIF('SG04'!$B:$B,$B92,'SG04'!K:K)*SG04_+SUMIF('SG05'!$B:$B,$B92,'SG05'!K:K)*SG05_+SUMIF('SG06'!$B:$B,$B92,'SG06'!K:K)*SG06_+SUMIF('SG07'!$B:$B,$B92,'SG07'!K:K)*SG07_+SUMIF('SG08'!$B:$B,$B92,'SG08'!K:K)*SG08_+SUMIF('SG09'!$B:$B,$B92,'SG09'!K:K)*SG09_+SUMIF('SG10'!$B:$B,$B92,'SG10'!K:K)*SG10_+SUMIF('SG11'!$B:$B,$B92,'SG11'!K:K)*SG11_+SUMIF('SG12'!$B:$B,$B92,'SG12'!K:K)*SG12_+SUMIF('SG13'!$B:$B,$B92,'SG13'!K:K)*SG13_+SUMIF('SG14'!$B:$B,$B92,'SG14'!K:K)*SG14_+SUMIF('SG15'!$B:$B,$B92,'SG15'!K:K)*SG15_) -> 3187889.7 | L92: =(SUMIF('SG01'!$B:$B,$B92,'SG01'!L:L)*SG01_+SUMIF('SG02'!$B:$B,$B92,'SG02'!L:L)*SG02_+SUMIF('SG03'!$B:$B,$B92,'SG03'!L:L)*SG03_+SUMIF('SG04'!$B:$B,$B92,'SG04'!L:L)*SG04_+SUMIF('SG05'!$B:$B,$B92,'SG05'!L:L)*SG05_+SUMIF('SG06'!$B:$B,$B92,'SG06'!L:L)*SG06_+SUMIF('SG07'!$B:$B,$B92,'SG07'!L:L)*SG07_+SUMIF('SG08'!$B:$B,$B92,'SG08'!L:L)*SG08_+SUMIF('SG09'!$B:$B,$B92,'SG09'!L:L)*SG09_+SUMIF('SG10'!$B:$B,$B92,'SG10'!L:L)*SG10_+SUMIF('SG11'!$B:$B,$B92,'SG11'!L:L)*SG11_+SUMIF('SG12'!$B:$B,$B92,'SG12'!L:L)*SG12_+SUMIF('SG13'!$B:$B,$B92,'SG13'!L:L)*SG13_+SUMIF('SG14'!$B:$B,$B92,'SG14'!L:L)*SG14_+SUMIF('SG15'!$B:$B,$B92,'SG15'!L:L)*SG15_) -> 8541000 | M92: =L92-K92 -> 5353110.3 | N92: =K92/L92 -> 0.37324548 | O92: =L92/L$10 -> 0.0055083218 | P92: =M92/M$10 -> 0.0052030231 | Q92: =I92/I$10 -> 0.0058559681 | R92: =I92/$K$5*100 -> 2.5453561 | S92: =R92*T$5 -> 7.4781225 | T92: =IFERROR(S92*G92,0) -> 679474.94 | V92: =IF(B92<>"",IFERROR(IF($I92>=$X$10,"High","Low"),""),"") -> Low | W92: =IF(B92<>"",IFERROR(IF($L92>=$X$12,"High","Low"),""),"") -> High | X92: =IF(B92<>"",IFERROR(IF(AND(V92="high",W92="high"),"Star",IF(AND(V92="low",W92="high"),"Puzzle",(IF(AND(V92="high",W92="low"),"Horse","Dog")))),""),"") -> Puzzle
A93: 2 | B93: GSHAS002 | C93: =VLOOKUP(B93,'SG01'!$B:$E,2,0) -> Hàu Nướng Mỡ Hành | E93: =VLOOKUP(B93,'SG01'!$B:$E,4,0) -> Phần | F93: =K93/I93 -> 33299.84 | G93: =L93/I93 -> 106902.26 | H93: =G93-F93 -> 73602.415 | I93: =(SUMIF('SG01'!$B:$B,$B93,'SG01'!I:I)*SG01_+SUMIF('SG02'!$B:$B,$B93,'SG02'!I:I)*SG02_+SUMIF('SG03'!$B:$B,$B93,'SG03'!I:I)*SG03_+SUMIF('SG04'!$B:$B,$B93,'SG04'!I:I)*SG04_+SUMIF('SG05'!$B:$B,$B93,'SG05'!I:I)*SG05_+SUMIF('SG06'!$B:$B,$B93,'SG06'!I:I)*SG06_+SUMIF('SG07'!$B:$B,$B93,'SG07'!I:I)*SG07_+SUMIF('SG08'!$B:$B,$B93,'SG08'!I:I)*SG08_+SUMIF('SG09'!$B:$B,$B93,'SG09'!I:I)*SG09_+SUMIF('SG10'!$B:$B,$B93,'SG10'!I:I)*SG10_+SUMIF('SG11'!$B:$B,$B93,'SG11'!I:I)*SG11_+SUMIF('SG12'!$B:$B,$B93,'SG12'!I:I)*SG12_+SUMIF('SG13'!$B:$B,$B93,'SG13'!I:I)*SG13_+SUMIF('SG14'!$B:$B,$B93,'SG14'!I:I)*SG14_+SUMIF('SG15'!$B:$B,$B93,'SG15'!I:I)*SG15_) -> 133 | K93: =(SUMIF('SG01'!$B:$B,$B93,'SG01'!K:K)*SG01_+SUMIF('SG02'!$B:$B,$B93,'SG02'!K:K)*SG02_+SUMIF('SG03'!$B:$B,$B93,'SG03'!K:K)*SG03_+SUMIF('SG04'!$B:$B,$B93,'SG04'!K:K)*SG04_+SUMIF('SG05'!$B:$B,$B93,'SG05'!K:K)*SG05_+SUMIF('SG06'!$B:$B,$B93,'SG06'!K:K)*SG06_+SUMIF('SG07'!$B:$B,$B93,'SG07'!K:K)*SG07_+SUMIF('SG08'!$B:$B,$B93,'SG08'!K:K)*SG08_+SUMIF('SG09'!$B:$B,$B93,'SG09'!K:K)*SG09_+SUMIF('SG10'!$B:$B,$B93,'SG10'!K:K)*SG10_+SUMIF('SG11'!$B:$B,$B93,'SG11'!K:K)*SG11_+SUMIF('SG12'!$B:$B,$B93,'SG12'!K:K)*SG12_+SUMIF('SG13'!$B:$B,$B93,'SG13'!K:K)*SG13_+SUMIF('SG14'!$B:$B,$B93,'SG14'!K:K)*SG14_+SUMIF('SG15'!$B:$B,$B93,'SG15'!K:K)*SG15_) -> 4428878.8 | L93: =(SUMIF('SG01'!$B:$B,$B93,'SG01'!L:L)*SG01_+SUMIF('SG02'!$B:$B,$B93,'SG02'!L:L)*SG02_+SUMIF('SG03'!$B:$B,$B93,'SG03'!L:L)*SG03_+SUMIF('SG04'!$B:$B,$B93,'SG04'!L:L)*SG04_+SUMIF('SG05'!$B:$B,$B93,'SG05'!L:L)*SG05_+SUMIF('SG06'!$B:$B,$B93,'SG06'!L:L)*SG06_+SUMIF('SG07'!$B:$B,$B93,'SG07'!L:L)*SG07_+SUMIF('SG08'!$B:$B,$B93,'SG08'!L:L)*SG08_+SUMIF('SG09'!$B:$B,$B93,'SG09'!L:L)*SG09_+SUMIF('SG10'!$B:$B,$B93,'SG10'!L:L)*SG10_+SUMIF('SG11'!$B:$B,$B93,'SG11'!L:L)*SG11_+SUMIF('SG12'!$B:$B,$B93,'SG12'!L:L)*SG12_+SUMIF('SG13'!$B:$B,$B93,'SG13'!L:L)*SG13_+SUMIF('SG14'!$B:$B,$B93,'SG14'!L:L)*SG14_+SUMIF('SG15'!$B:$B,$B93,'SG15'!L:L)*SG15_) -> 14218000 | M93: =L93-K93 -> 9789121.2 | N93: =K93/L93 -> 0.31149801 | O93: =L93/L$10 -> 0.0091695726 | P93: =M93/M$10 -> 0.0095146599 | Q93: =I93/I$10 -> 0.0082855719 | R93: =I93/$K$5*100 -> 3.6014081 | S93: =R93*T$5 -> 10.580748 | T93: =IFERROR(S93*G93,0) -> 1131105.8 | V93: =IF(B93<>"",IFERROR(IF($I93>=$X$10,"High","Low"),""),"") -> High | W93: =IF(B93<>"",IFERROR(IF($L93>=$X$12,"High","Low"),""),"") -> High | X93: =IF(B93<>"",IFERROR(IF(AND(V93="high",W93="high"),"Star",IF(AND(V93="low",W93="high"),"Puzzle",(IF(AND(V93="high",W93="low"),"Horse","Dog")))),""),"") -> Star
A94: 3 | B94: GSHAS003 | C94: =VLOOKUP(B94,'SG01'!$B:$E,2,0) -> Mực Ống Nướng | E94: =VLOOKUP(B94,'SG01'!$B:$E,4,0) -> Phần | F94: =K94/I94 -> 65910.133 | G94: =L94/I94 -> 177531.25 | H94: =G94-F94 -> 111621.12 | I94: =(SUMIF('SG01'!$B:$B,$B94,'SG01'!I:I)*SG01_+SUMIF('SG02'!$B:$B,$B94,'SG02'!I:I)*SG02_+SUMIF('SG03'!$B:$B,$B94,'SG03'!I:I)*SG03_+SUMIF('SG04'!$B:$B,$B94,'SG04'!I:I)*SG04_+SUMIF('SG05'!$B:$B,$B94,'SG05'!I:I)*SG05_+SUMIF('SG06'!$B:$B,$B94,'SG06'!I:I)*SG06_+SUMIF('SG07'!$B:$B,$B94,'SG07'!I:I)*SG07_+SUMIF('SG08'!$B:$B,$B94,'SG08'!I:I)*SG08_+SUMIF('SG09'!$B:$B,$B94,'SG09'!I:I)*SG09_+SUMIF('SG10'!$B:$B,$B94,'SG10'!I:I)*SG10_+SUMIF('SG11'!$B:$B,$B94,'SG11'!I:I)*SG11_+SUMIF('SG12'!$B:$B,$B94,'SG12'!I:I)*SG12_+SUMIF('SG13'!$B:$B,$B94,'SG13'!I:I)*SG13_+SUMIF('SG14'!$B:$B,$B94,'SG14'!I:I)*SG14_+SUMIF('SG15'!$B:$B,$B94,'SG15'!I:I)*SG15_) -> 64 | K94: =(SUMIF('SG01'!$B:$B,$B94,'SG01'!K:K)*SG01_+SUMIF('SG02'!$B:$B,$B94,'SG02'!K:K)*SG02_+SUMIF('SG03'!$B:$B,$B94,'SG03'!K:K)*SG03_+SUMIF('SG04'!$B:$B,$B94,'SG04'!K:K)*SG04_+SUMIF('SG05'!$B:$B,$B94,'SG05'!K:K)*SG05_+SUMIF('SG06'!$B:$B,$B94,'SG06'!K:K)*SG06_+SUMIF('SG07'!$B:$B,$B94,'SG07'!K:K)*SG07_+SUMIF('SG08'!$B:$B,$B94,'SG08'!K:K)*SG08_+SUMIF('SG09'!$B:$B,$B94,'SG09'!K:K)*SG09_+SUMIF('SG10'!$B:$B,$B94,'SG10'!K:K)*SG10_+SUMIF('SG11'!$B:$B,$B94,'SG11'!K:K)*SG11_+SUMIF('SG12'!$B:$B,$B94,'SG12'!K:K)*SG12_+SUMIF('SG13'!$B:$B,$B94,'SG13'!K:K)*SG13_+SUMIF('SG14'!$B:$B,$B94,'SG14'!K:K)*SG14_+SUMIF('SG15'!$B:$B,$B94,'SG15'!K:K)*SG15_) -> 4218248.5 | L94: =(SUMIF('SG01'!$B:$B,$B94,'SG01'!L:L)*SG01_+SUMIF('SG02'!$B:$B,$B94,'SG02'!L:L)*SG02_+SUMIF('SG03'!$B:$B,$B94,'SG03'!L:L)*SG03_+SUMIF('SG04'!$B:$B,$B94,'SG04'!L:L)*SG04_+SUMIF('SG05'!$B:$B,$B94,'SG05'!L:L)*SG05_+SUMIF('SG06'!$B:$B,$B94,'SG06'!L:L)*SG06_+SUMIF('SG07'!$B:$B,$B94,'SG07'!L:L)*SG07_+SUMIF('SG08'!$B:$B,$B94,'SG08'!L:L)*SG08_+SUMIF('SG09'!$B:$B,$B94,'SG09'!L:L)*SG09_+SUMIF('SG10'!$B:$B,$B94,'SG10'!L:L)*SG10_+SUMIF('SG11'!$B:$B,$B94,'SG11'!L:L)*SG11_+SUMIF('SG12'!$B:$B,$B94,'SG12'!L:L)*SG12_+SUMIF('SG13'!$B:$B,$B94,'SG13'!L:L)*SG13_+SUMIF('SG14'!$B:$B,$B94,'SG14'!L:L)*SG14_+SUMIF('SG15'!$B:$B,$B94,'SG15'!L:L)*SG15_) -> 11362000 | M94: =L94-K94 -> 7143751.5 | N94: =K94/L94 -> 0.37125933 | O94: =L94/L$10 -> 0.007327661 | P94: =M94/M$10 -> 0.0069434594 | Q94: =I94/I$10 -> 0.0039870421 | R94: =I94/$K$5*100 -> 1.7330084 | S94: =R94*T$5 -> 5.0914877 | T94: =IFERROR(S94*G94,0) -> 903898.17 | V94: =IF(B94<>"",IFERROR(IF($I94>=$X$10,"High","Low"),""),"") -> Low | W94: =IF(B94<>"",IFERROR(IF($L94>=$X$12,"High","Low"),""),"") -> High | X94: =IF(B94<>"",IFERROR(IF(AND(V94="high",W94="high"),"Star",IF(AND(V94="low",W94="high"),"Puzzle",(IF(AND(V94="high",W94="low"),"Horse","Dog")))),""),"") -> Puzzle
A95: 4 | B95: GSHGC006 | C95: =VLOOKUP(B95,'SG01'!$B:$E,2,0) -> Cá Hồi Xốt Miso Vang Đỏ | E95: =VLOOKUP(B95,'SG01'!$B:$E,4,0) -> Phần | F95: =K95/I95 -> 31444.901 | G95: =L95/I95 -> 138200 | H95: =G95-F95 -> 106755.1 | I95: =(SUMIF('SG01'!$B:$B,$B95,'SG01'!I:I)*SG01_+SUMIF('SG02'!$B:$B,$B95,'SG02'!I:I)*SG02_+SUMIF('SG03'!$B:$B,$B95,'SG03'!I:I)*SG03_+SUMIF('SG04'!$B:$B,$B95,'SG04'!I:I)*SG04_+SUMIF('SG05'!$B:$B,$B95,'SG05'!I:I)*SG05_+SUMIF('SG06'!$B:$B,$B95,'SG06'!I:I)*SG06_+SUMIF('SG07'!$B:$B,$B95,'SG07'!I:I)*SG07_+SUMIF('SG08'!$B:$B,$B95,'SG08'!I:I)*SG08_+SUMIF('SG09'!$B:$B,$B95,'SG09'!I:I)*SG09_+SUMIF('SG10'!$B:$B,$B95,'SG10'!I:I)*SG10_+SUMIF('SG11'!$B:$B,$B95,'SG11'!I:I)*SG11_+SUMIF('SG12'!$B:$B,$B95,'SG12'!I:I)*SG12_+SUMIF('SG13'!$B:$B,$B95,'SG13'!I:I)*SG13_+SUMIF('SG14'!$B:$B,$B95,'SG14'!I:I)*SG14_+SUMIF('SG15'!$B:$B,$B95,'SG15'!I:I)*SG15_) -> 70 | K95: =(SUMIF('SG01'!$B:$B,$B95,'SG01'!K:K)*SG01_+SUMIF('SG02'!$B:$B,$B95,'SG02'!K:K)*SG02_+SUMIF('SG03'!$B:$B,$B95,'SG03'!K:K)*SG03_+SUMIF('SG04'!$B:$B,$B95,'SG04'!K:K)*SG04_+SUMIF('SG05'!$B:$B,$B95,'SG05'!K:K)*SG05_+SUMIF('SG06'!$B:$B,$B95,'SG06'!K:K)*SG06_+SUMIF('SG07'!$B:$B,$B95,'SG07'!K:K)*SG07_+SUMIF('SG08'!$B:$B,$B95,'SG08'!K:K)*SG08_+SUMIF('SG09'!$B:$B,$B95,'SG09'!K:K)*SG09_+SUMIF('SG10'!$B:$B,$B95,'SG10'!K:K)*SG10_+SUMIF('SG11'!$B:$B,$B95,'SG11'!K:K)*SG11_+SUMIF('SG12'!$B:$B,$B95,'SG12'!K:K)*SG12_+SUMIF('SG13'!$B:$B,$B95,'SG13'!K:K)*SG13_+SUMIF('SG14'!$B:$B,$B95,'SG14'!K:K)*SG14_+SUMIF('SG15'!$B:$B,$B95,'SG15'!K:K)*SG15_) -> 2201143.1 | L95: =(SUMIF('SG01'!$B:$B,$B95,'SG01'!L:L)*SG01_+SUMIF('SG02'!$B:$B,$B95,'SG02'!L:L)*SG02_+SUMIF('SG03'!$B:$B,$B95,'SG03'!L:L)*SG03_+SUMIF('SG04'!$B:$B,$B95,'SG04'!L:L)*SG04_+SUMIF('SG05'!$B:$B,$B95,'SG05'!L:L)*SG05_+SUMIF('SG06'!$B:$B,$B95,'SG06'!L:L)*SG06_+SUMIF('SG07'!$B:$B,$B95,'SG07'!L:L)*SG07_+SUMIF('SG08'!$B:$B,$B95,'SG08'!L:L)*SG08_+SUMIF('SG09'!$B:$B,$B95,'SG09'!L:L)*SG09_+SUMIF('SG10'!$B:$B,$B95,'SG10'!L:L)*SG10_+SUMIF('SG11'!$B:$B,$B95,'SG11'!L:L)*SG11_+SUMIF('SG12'!$B:$B,$B95,'SG12'!L:L)*SG12_+SUMIF('SG13'!$B:$B,$B95,'SG13'!L:L)*SG13_+SUMIF('SG14'!$B:$B,$B95,'SG14'!L:L)*SG14_+SUMIF('SG15'!$B:$B,$B95,'SG15'!L:L)*SG15_) -> 9674000 | M95: =L95-K95 -> 7472856.9 | N95: =K95/L95 -> 0.22753185 | O95: =L95/L$10 -> 0.0062390241 | P95: =M95/M$10 -> 0.0072633375 | Q95: =I95/I$10 -> 0.0043608273 | R95: =I95/$K$5*100 -> 1.8954779 | S95: =R95*T$5 -> 5.5688146 | T95: =IFERROR(S95*G95,0) -> 769610.18 | V95: =IF(B95<>"",IFERROR(IF($I95>=$X$10,"High","Low"),""),"") -> Low | W95: =IF(B95<>"",IFERROR(IF($L95>=$X$12,"High","Low"),""),"") -> High | X95: =IF(B95<>"",IFERROR(IF(AND(V95="high",W95="high"),"Star",IF(AND(V95="low",W95="high"),"Puzzle",(IF(AND(V95="high",W95="low"),"Horse","Dog")))),""),"") -> Puzzle
